Workbook
Name RichCapital: '15_DB_SGX_Industry'!$A$406

Sheet 00_Ref
A1: Version: v1.0 | Last updated: 8 Nov 2025
A3: Sheet: 00_ReadMe — Setup and Content Guide
A5: 📌 Purpose
A7: This tab acts as the front cover and navigation guide for the entire workbook. It should be the first sheet users see when opening the file.
A9: 🧩 Section 1: File Metadata
A11: Field | B11: Recommended Entry Example
A12: File Title | B12: SME Valuation Toolkit – Excel Companion
A13: Version | B13: v1.0 (November 2025)
A14: Author Contact | B14: Isaac Wong
A15: Last Updated | B15: =TODAY() -> 46154
A16: Excel Version | B16: Requires Excel 2016 or later
A17: Macros | B17: No macros used — safe for all environments
A19: 🧭 Section 2: Sheet-to-Chapter Mapping
A21: Sheet Name | B21: Corresponds to Chapter
A22: Inputs | B22: Chapter 2 – Normalization
A23: Beta Estimator | B23: Chapter 3 – Estimating Beta
A24: WACC Calculator | B24: Chapter 5 – Weighted Average Cost of Capital
A25: Risk Premiums | B25: Chapters 3, 10–11 – IRP, SCP, CSRP, DLOC, DLOM
A26: DCF Model | B26: Chapter 6 – Integrated Valuation Flow
A27: Income Model - Capitalization | B27: Chapter 7 - Income Based
A28: Market Multiple Model | B28: Chapter 8 - Market Based
A29: Asset Based Model | B29: Chapter 9 - Asset Based
A30: Adjustment Table | B30: Chapters 11 – Post-Valuation Adjustments
A31: Valuation Summary | B31: Chapter 12 – Communicating Findings
A32: Report Template | B32: Chapter 13 – Stakeholder Reporting
... A37: Checklist | B37: Chapter 19
A39: 📘 Section 3: Usage Instructions
A41: How to use this Toolkit: This Excel workbook supports SME valuation using free data and structured logic. Each sheet corresponds to a chapter in the guidebook and automates key steps — from normalization and beta estimation to WACC, DCF modeling, and post-valuation adjustments. Start with the Inputs tab, follow the sheet sequence, and refer to the Checklist for completeness. All formulas are unlocked and editable. No macros are used. This toolkit is designed for transparency, defensibility, and ease of use by CPAs and SME advisors.
A43: Section 4: Quick Start Checklist
A45: Step 1 — Confirm Setup
A47: [ ] Open the workbook in Excel 2016 or later (Microsoft 365 recommended for best compatibility).
A49: [ ] Ensure macros are disabled (none are used in this file).
A51: [ ] Check that the Inputs sheet is visible and accessible.
A53: Step 2 — Enter Key Inputs (01_Inputs)
A55: [ ] Fill in Risk-Free Rate (Rf) (e.g., MAS 10Y yield).
A57: [ ] Enter Equity Risk Premium (ERP) (e.g., NYU Stern data).
A59: [ ] Confirm Corporate Tax Rate (default 17% for Singapore).
A61: [ ] Input Small Company Premium (SCP) and Industry Risk Premium (IRP) if applicable.
... A149: [14_Case Study] → [15_DB_SGX_Industry]

Sheet 00_Dashboard
A1: SME Valuation Dashboard (Sheet: 00_Dashboard)
A3: 🧭 Layout Overview
A5: Section | B5: Purpose | C5: Formatting Tips
A6: A: Key Inputs | B6: Show all named inputs from 01_Inputs | C6: Use light blue header, bold labels
A7: B: Valuation Methods | B7: Show FMV & FV results from each method | C7: Use side-by-side layout, color-coded
A8: C: Final Summary | B8: Show FMV vs FV per share, DLOC/DLOM | C8: Use bold fonts, highlight differences
A9: D: Visual Snapshot | B9: Optional chart (FMV vs FV comparison) | C9: Insert bar chart or heatmap
A11: Section A: Key Inputs
A13: Label | B13: Value | C13: Notes
A14: Risk-Free Rate (Rf) | B14: ='01_Inputs'!E11 -> 2.22 | C14: MAS 10Y yield
A15: Equity Risk Premium | B15: ='01_Inputs'!E12 -> 4.65 | C15: NYU Stern
A16: Corporate Tax Rate | B16: ='01_Inputs'!E13 -> 0.17 | C16: Singapore default 17%
A17: Re-levered Beta | B17: ='01_Inputs'!E14 -> 1.3462115 | C17: From Beta Estimator
A18: WACC | B18: ='01_Inputs'!E18 -> 7.9647855 | C18: From WACC Calculator
A19: Sustainable growth rate/Terminal Growth rate | B19: ='01_Inputs'!E22 -> 0.03 | C19: From Normalization sheet
A20: Shares Outstanding | B20: ='01_Inputs'!E21 -> 500000 | C20: Used for per-share calc
A21: DLOC | B21: ='01_Inputs'!E20 -> 0.26340601 | C21: Discount for lack of control
A22: DLOM | B22: ='01_Inputs'!E19 -> 0.15 | C22: Discount for marketability
A24: Section B: Valuation Methods
A26: Method | B26: FMV (S$) | C26: FV (S$) | D26: Notes | E26: Ratio
A27: Asset-Based | B27: =C27 -> 3683286.9 | C27: ='09_Asset_Based'!E21 -> 3683286.9 | D27: Adjusted net assets | E27: 20
A28: Income-Based (DCF) | B28: =C28 -> 10906059 | C28: ='06_Income_Based DCF'!C34 -> 10906059 | D28: Terminal value applied | E28: 20
A29: Capitalization | B29: =C29 -> 5459562.3 | C29: ='07_Income_Based_Capitalization'!E17 -> 5459562.3 | D29: Based on normalized earnings | E29: 40
A30: Market Multiple | B30: =C30 -> 3427233 | C30: ='08_Market_Multiple'!E33 -> 3427233 | D30: Peer benchmarked | E30: 20
A32: Section C: Final Summary
A34: Metric | B34: FMV (S$) | C34: FV (S$) | D34: Notes
A35: Enterprise Value | B35: =C35 -> 5787140.8 | C35: =(C27*E27%)+(C28*E28%)+(C29*E29%)+(C30*E30%) -> 5787140.8 | D35: From valuation summary
A36: Net Debt | B36: =C36 -> 3825982 | C36: ='05_WACC'!E11 -> 3825982 | D36: Collateralized property loan
A37: Equity Value | B37: =C37 -> 1961158.8 | C37: =C35-C36 -> 1961158.8 | D37: Before discounts
A38: Per Share Value | B38: =C38 -> 3.9223176 | C38: =C37/B20 -> 3.9223176 | D38: Before DLOC/DLOM
A39: Final Value | B39: =B38-(B38*B21*B22) -> 3.7673433 | C39: =C38 -> 3.9223176 | D39: After DLOC/DLOM (FMV only)
A41: 📈 Section D: Visual Snapshot
A43: Insert a clustered bar chart comparing FMV vs FV per method
A45: Use color coding:
A49: FMV = Blue
A51: FV = Green
A53: Label axes:
A57: X-axis = Valuation Method
A59: Y-axis = Value (S$)
A61: Title: “FMV vs FV Comparison by Method”
A63: ✅ Benefits
A65: Gives users a one-screen summary of valuation logic and results
A67: Reinforces your FMV vs FV framework
A69: Makes the toolkit presentation-ready for clients, stakeholders, and regulators

Sheet 000_Steps in screenshot
A1: A | B1: How to draw out public listed companies comparables from your toolkit:
B2: -In this example: Select Industry [Real Estate], SubIndustry [Real Estate Development and Real Estate Services], Profile [Property Development] [Design Specialty] [Building Material-Marble]
B7: 1. Select Worksheet [DB_SGX_Industry]
B11: 2. Select from [DB_SGX_Industry] -(i) "active" in column B (ii) both "m" and "c" in Column C (iii) "Real Estate" in Column D (iv) "Real Estate Development" in Column E and (v) "Property Development" & "Design (vi) "SGD" & "MYR" Specialty" and "Marble"
B28: After checking the dropdown to select items in each column with the steps (i) to (vi):
B46: Fill in the listed companies market and financial data into each columns. The data can be obtained from either SGX or Yahoo Finance.
B68: Next After completed filled in all the data into each companies, move those companies with market capitalization of less than S$300 million in the Mainboard ("m") to the Catalyst ("c") rows:
B86: Calculate the Risk premium for Industry & Small Size Companies:
B120: Compute the Company-Specific Risk Premium (CSRP):
B121: - This figures is obtained from Worksheet [10_CSRP_Scoring]. Use your professional judgement.
B144: Updating the CAPM model in Worksheet [04_CAPM] :
B164: Setting up Market Peers Comparables.
B165: In this case, there are two listed companies of the similar business activities which is Design specialty i.e. Figtree and GRC. Compare their Gross Revenue, EBITDA, Total Assets, FCF, Total Debts and Total Equity, you will find that Figtree is the more relevant for the Market Approach method for valuation.
B208: WACC for DCF Valuation Method. WACC obtained from [05_WACC] and [10_CSRP Scoring]

Sheet 01_Inputs
A1: Disclaimer: This guidebook and its companion toolkit are provided for educational purposes only. They are not intended as financial advice. Users should apply professional judgment and consult relevant standards, regulations, and authorities when performing valuations.
A4: 01_Inputs — Review & Fix Checklist
A6: 🧩 Must-Have Named Inputs
A8: Ensure the following named ranges exist and are clearly labeled in the sheet:
A10: Label in Sheet | B10: Named Range | C10: Suggested Cell | D10: Notes | E10: Inputs
A11: Risk-free rate | B11: Rf | C11: B2 | D11: e.g., 0.025 for 2.5% | E11: =' 04_CAPM'!D4 -> 2.22
A12: Equity risk premium | B12: ERP | C12: B3 | D12: e.g., 0.055 | E12: =' 04_CAPM'!D7 -> 4.65
A13: Corporate tax rate | B13: Singapore Corporate Tax Rate | C13: B4 | D13: Default 0.17 | E13: 0.17
A14: Re-levered Beta | B14: βL=βU×(1+(1−T)*D/E) | D14: Company specific | E14: ='03_Beta_Calculation'!E67 -> 1.3462115
A15: Industry risk premium | B15: IRP | C15: B6 | D15: Optional if not embedded in beta | E15: ='03_Beta_Calculation'!J63 -> 1.6098834
A16: Small-company premium | B16: SCP | C16: B5 | D16: e.g., 0.02 | E16: ='03b_Size Premium Method 15Y'!E27 -> 6.0302554
A17: CSRP | E17: ='10_CSRP_Scoring'!B21 -> 4.4
A18: WACC | E18: ='05_WACC'!E21 -> 7.9647855
A19: DLOM Factor | B19: Floor_DLOM | C19: B7 | D19: Default 0.15 | E19: ='11b_DLOM'!D49 -> 0.15
A20: Control premium (decimal) | B20: Control_Premium | C20: B9 | D20: e.g., 0.30 | E20: ='11a_DLOC'!D32 -> 0.26340601
A21: Shares outstanding | B21: Shares | C21: B10 | D21: e.g., 1,000,000 | E21: ='14_Case Study_Gamma'!B5 -> 500000
A22: Sustainable long term growth rate | B22: g | E22: =' 04_CAPM'!D18 -> 0.03
A24: 💡 Tip: Use Excel’s Name Manager (Ctrl + F3) to confirm these ranges are defined and scoped to the workbook.
A26: ✅ Data Validation Rules
A28: Apply data validation to prevent input errors:
A30: Named Range | B30: Validation Rule | C30: Notes
A31: Rf, ERP, SCP, IRP, TaxRate | B31: Decimal between 0 and 1 | C31: Prevents >100% errors
A32: Floor_DLOM, Cap_DLOM | B32: Decimal between 0 and 1 | C32: Cap must be ≥ Floor
A33: Control_Premium | B33: Decimal between 0 and 1 | C33: e.g., 0.30 for 30%
A34: Shares | B34: Whole number > 0 | C34: No decimals allowed
A36: 📌 Add conditional formatting to flag if Cap_DLOM < Floor_DLOM.
A38: 🔍 Formula Audit: Replace Hard-Coding
A40: Search all other sheets (especially WACC, DCF, Risk Premiums, Adjustment Table) for hard-coded values like:
A42: 0.17 → replace with =Inputs!TaxRate
A44: 0.055 → replace with =Inputs!ERP
A46: 0.02, 0.03, etc. → replace with =Inputs!SCP, =Inputs!IRP, etc.
A48: Use Find & Replace (Ctrl + F) to locate and replace hard-coded values with named ranges.
A50: 🧾 Presentation Tips
A52: Use a clean, two-column layout: Label in Column A, Input Value in Column B.
A54: Add a third column (Column C) for Comments or Default Guidance (e.g., “Default 17% for Singapore corporate tax”).
A56: Freeze top row and left column for usability.
A58: Consider light shading or borders to distinguish input cells.
... A68: [ ] Sheet is clearly labeled and user-friendly.

Sheet 02_Normalization
A3: Reconstructed Income Statements | Q3: Unaudited | R3: Normalised @
A4: The summary of the most recent annual historic Income Statements and the appropriate adjustments are summarised in the table below: | Q4: @ 31 Dec 2026 | R4: 44651
K5: Balance Sheet Items | L5: 2021 | M5: 2022 | N5: 2023 | O5: 2024 | P5: 2025 | Q5: 2026 | R5: @ 31 Mar 2022 | S5: Adjusted
B6: Audited Accounts
A7: Historic Income / Expense Items | B7: 2021 | C7: 2022 | D7: 2023 | E7: 2024 | F7: 2025 | K7: Current Assets
A9: Revenues | B9: 3549913 | C9: 3852126 | D9: 4297121 | E9: 3536194 | F9: 5394455 | K9: Inventories | L9: 0 | M9: 12160 | N9: 12160 | O9: 0 | P9: 0 | R9: 0 | S9: =P9+R9 -> 0
A11: Cost of Goods Sold (COGS) | B11: 2002710 | C11: 2900887 | D11: 3191245 | E11: 2345295 | F11: 2999566 | K11: Trade receivables | L11: =930180+23372 -> 953552 | M11: =717115+63541 -> 780656 | N11: 798757 | O11: 999440 | P11: 1231473 | Q11: =333113+108398 -> 441511 | R11: =394408+5091 -> 399499 | S11: =P11+R11 -> 1630972
A13: Gross Profit | B13: =B9-B11 -> 1547203 | C13: =C9-C11 -> 951239 | D13: =D9-D11 -> 1105876 | E13: =E9-E11 -> 1190899 | F13: =F9-F11 -> 2394889 | K13: Other receivables | L13: 31427 | M13: 40911 | N13: 69573 | O13: 35594 | P13: 328911 | Q13: 12980 | R13: 13143 | S13: =P13+R13 -> 342054
A15: Operating Expenses | B15: =B91 -> 950694 | C15: =C91 -> 1144657 | D15: =D91 -> 1096546 | E15: =E91 -> 1124337 | F15: =F91 -> 1653376 | K15: Amount due from a shareholder | L15: 0 | M15: 208800 | N15: 200000 | O15: 0 | P15: 0 | Q15: 300000 | R15: 342241 | S15: =P15+R15 -> 342241
A17: Operating Income | B17: =B13-B15 -> 596509 | C17: =C13-C15 -> -193418 | D17: =D13-D15 -> 9330 | E17: =E13-E15 -> 66562 | F17: =F13-F15 -> 741513 | K17: Cash and bank balances | L17: 537788 | M17: 387973 | N17: 508107 | O17: 707171 | P17: 253871 | Q17: 1099123 | R17: 732538
A19: Other Income / (expenses) | B19: 91645 | C19: 258581 | D19: 74842 | E19: 51017 | F19: 199652 | K19: Total Current Assets | L19: =SUM(L9:L17) -> 1522767 | M19: =SUM(M9:M17) -> 1430500 | N19: =SUM(N9:N17) -> 1588597 | O19: =SUM(O9:O17) -> 1742205 | P19: =SUM(P9:P17) -> 1814255 | Q19: =SUM(Q9:Q17) -> 1853614 | R19: =SUM(R9:R17) -> 1487421 | S19: =SUM(S9:S17) -> 2315267
A21: Net Pre-Tax Income | B21: =B17+B19 -> 688154 | C21: =C17+C19 -> 65163 | D21: =D17+D19 -> 84172 | E21: =E17+E19 -> 117579 | F21: =F17+F19 -> 941165 | K21: Non-Current Assets
K22: Property, plant and equipment | L22: 301783 | M22: 279139 | N22: 277755 | O22: 270688 | P22: 4859035 | Q22: 4684353 | R22: 4617812 | S22: =P22+R22 -> 9476847
A23: Taxes | B23: 56830 | C23: 0 | D23: 0 | E23: 8706 | F23: 149213 | K23: Investment in subsidairies E(M&S)PL | N23: 0 | O23: 0 | P23: 0 | R23: 150000 | S23: =P23+R23 -> 150000
K24: Available for sale financial assets | N24: 0 | O24: 0 | P24: 0 | S24: =P24+R24 -> 0
A25: Net Income | B25: =B21-B23 -> 631324 | C25: =C21-C23 -> 65163 | D25: =D21-D23 -> 84172 | E25: =E21-E23 -> 108873 | F25: =F21-F23 -> 791952 | K25: Loan to subsidiary | N25: 0 | O25: 0 | P25: 0 | S25: =P25+R25 -> 0
A27: Adjustments to the SCDF: | B27: =SUM(B28:B34)-B56 -> 361896 | C27: =SUM(C28:C34)-C56 -> -172451 | D27: =SUM(D28:D34)-D56 -> 59181 | E27: =SUM(E28:E34)-E56 -> 229772 | F27: =SUM(F28:F34)-F56 -> 331340
A28: Property & Plant written off | B28: 0 | C28: 0 | D28: 0 | E28: 18342 | F28: 17695 | K28: Total Fixed Assets | L28: =SUM(L22:L26) -> 301783 | M28: =SUM(M22:M26) -> 279139 | N28: =SUM(N22:N26) -> 277755 | O28: =SUM(O22:O26) -> 270688 | P28: =SUM(P22:P26) -> 4859035 | Q28: =SUM(Q22:Q26) -> 4684353 | R28: =SUM(R22:R26) -> 4767812 | S28: =SUM(S22:S26) -> 9626847
A29: Bad Debt written off | E29: 6221 | F29: 214000
A30: Depreciation and Amortisation expense | B30: 68957 | C30: 57025 | D30: 64015 | E30: 48775 | F30: 39347 | K30: Less accumulated depreciation
A31: Finance expenses & interest on lease liability | B31: 1985 | C31: 6882 | D31: 2856 | E31: 5201 | F31: 12843 | K31: Plant & Machinery | N31: 0 | O31: 0 | P31: 0 | S31: =P31+R31 -> 0
A32: Government grants | B32: -82546 | C32: -227901 | D32: -40000 | E32: -45232 | F32: -183907 | K32: Renovation | N32: 0 | O32: 0 | P32: 0 | S32: =P32+R32 -> 0
A33: Loss/(Gain) on disposal of plant and equipment | B33: 0 | C33: =-16382+16725 -> 343 | D33: 32310 | E33: -2248 | F33: 31362 | K33: Office equipment | N33: 0 | O33: 0 | P33: 0 | S33: =P33+R33 -> 0
A34: Interest income | B34: 0 | C34: -8800 | D34: 0 | E34: -1287 | F34: 0 | K34: Motor Vehicles | N34: 0 | O34: 0 | P34: 0 | S34: =P34+R34 -> 0
K35: Computer & software | N35: 0 | O35: 0 | P35: 0 | S35: =P35+R35 -> 0
A36: Seller's discretionary cash flow + Dividend paid | B36: =B25+SUM(B28:B34)-B56 -> 993220 | C36: =C25+SUM(C28:C34)-C56 -> -107288 | D36: =D25+SUM(D28:D34)-D56 -> 143353 | E36: =E25+SUM(E28:E34)-E56 -> 338645 | F36: =F25+SUM(F28:F34)-F56 -> 1123292 | N36: =SUM(N31:N35) -> 0
A38: EBIT | B38: =B21+B31+B90 -> 694605 | C38: =C21+C31+C90 -> 80793 | D38: =D21+D31+D90 -> 91492 | E38: =E21+E31+E90 -> 129794 | F38: =F21+F31+F90 -> 967817 | K38: Net Fixed Assets | L38: =L28-L36 -> 301783 | M38: =M28-M36 -> 279139 | N38: =N28-N36 -> 277755 | O38: =O28-O36 -> 270688 | P38: =P28-P36 -> 4859035 | Q38: =Q28-Q36 -> 4684353 | R38: =R28-R36 -> 4767812 | S38: =S28-S36 -> 9626847
A40: EBITDA | B40: =B38+B30 -> 763562 | C40: =C38+C30 -> 137818 | D40: =D38+D30 -> 155507 | E40: =E38+E30 -> 178569 | F40: =F38+F30 -> 1007164 | K40: Total Assets | L40: =L38+L19 -> 1824550 | M40: =M38+M19 -> 1709639 | N40: =N38+N19 -> 1866352 | O40: =O38+O19 -> 2012893 | P40: =P38+P19 -> 6673290 | Q40: =Q38+Q19 -> 6537967 | R40: =R38+R19 -> 6255233 | S40: =S38+S19 -> 11942114
A41: EBITDA less grants (normalised) | B41: =B40+B32 -> 681016 | C41: =C40+C32 -> -90083 | D41: =D40+D32 -> 115507 | E41: =E40+E32 -> 133337 | F41: =F40+F32 -> 823257
A42: Changes in working capital | B42: =SUM(B43:B48) -> -137098 | C42: =SUM(C43:C48) -> -32390 | D42: =SUM(D43:D48) -> -56127 | E42: =SUM(E43:E48) -> 72568 | F42: =SUM(F43:F48) -> -601856 | K42: Current Liabiities
A43: -Inventories | B43: 6576 | C43: -12160 | D43: 0 | E43: 12160 | F43: 0
A44: -Trade receivable | B44: -393392 | C44: 203581 | D44: -110304 | E44: -172925 | F44: -739350 | K44: Contract liabilities | L44: 316979 | M44: 431479 | N44: 456815 | O44: 360834 | P44: 120793 | S44: =P44+R44 -> 120793
A45: -Income tax paid | B45: 0 | C45: -54353 | D45: -4711 | E45: -8706 | F45: -5631 | K45: Trade and other payables | L45: 972708 | M45: 728919 | N45: 698930 | O45: =1397784-360834 -> 1036950 | P45: =1540909-120793 -> 1420116 | Q45: =615246+52321 -> 667567 | R45: =570911+54835 -> 625746 | S45: =P45+R45 -> 2045862
A46: -Other receivables | B46: 0 | C46: 0 | D46: 0 | E46: 0 | F46: 0 | K46: Finance lease payables | L46: 66071 | M46: 9901 | N46: 22287 | O46: 32537 | P46: 11974 | S46: =P46+R46 -> 11974
A47: -Trade and other payables | B47: =370791-121073 -> 249718 | C47: =-243789+74331 -> -169458 | D47: 58888 | E47: 242039 | F47: 143125 | K47: Provision for taxation | L47: 59417 | M47: 5064 | N47: 353 | O47: 353 | P47: 143935 | S47: =P47+R47 -> 143935
B48: 0 | C48: 0 | D48: 0 | E48: 0 | F48: 0 | K48: Term Loans - secured | L48: 0 | M48: 0 | N48: 0 | O48: 0 | P48: 442662 | S48: =P48+R48 -> 442662
A50: Changes in investing & financing | B50: =SUM(B51:B62) -> -663697 | C50: =SUM(C51:C62) -> -238038 | D50: =SUM(D51:D62) -> -7092 | E50: =SUM(E51:E62) -> -66087 | F50: =SUM(F51:F62) -> -1107856
A51: -Amount due from shareholders | B51: 0 | C51: -200000 | D51: 8800 | E51: 200000 | F51: 0 | K51: Total Current Liabiities | L51: =SUM(L44:L48) -> 1415175 | M51: =SUM(M44:M48) -> 1175363 | N51: =SUM(N44:N48) -> 1178385 | O51: =SUM(O44:O48) -> 1430674 | P51: =SUM(P44:P48) -> 2139480 | Q51: =SUM(Q44:Q48) -> 667567 | R51: =SUM(R44:R48) -> 625746 | S51: =SUM(S44:S48) -> 2765226
A52: -Acquisition of property, plant & equipment | B52: -279283 | C52: -16436 | D52: -99441 | E52: -82512 | F52: -4781734
A53: -Proceed from disposal of property, plant & equipment | B53: 0 | C53: 75000 | D53: 101000 | E53: 139898 | F53: 188883 | K53: Non-current liabilities
A54: -Interest received | B54: 0 | C54: 0 | D54: 0 | E54: 1287 | F54: 0
K55: Finance Lease payable | L55: 0 | M55: 59738 | N55: 129257 | O55: 114636 | P55: 66937 | Q55: 105141 | R55: 99882
A56: -Dividend paid | B56: -373500 | C56: 0 | D56: 0 | E56: -200000 | F56: -200000 | K56: Term Loans | O56: 0 | P56: 3207338 | Q56: 3207800 | R56: 3179420
A57: -Interest paid | B57: -1985 | C57: -6882 | D57: -2856 | E57: -5201 | F57: -12843 | S57: =P57+R57 -> 0
A58: -Repayment of finance lease payable | B58: -8929 | C58: -89720 | D58: -14595 | E58: -119559 | F58: -152162 | S58: =N58+R58 -> 0
A59: -Proceed from issuance of ordinary shares | B59: 0 | C59: 0 | D59: 0 | E59: 0 | F59: 200000 | K59: Total Non-current liabilities | L59: =SUM(L55:L57) -> 0 | M59: =SUM(M55:M57) -> 59738 | N59: =SUM(N55:N57) -> 129257 | O59: =SUM(O55:O57) -> 114636 | P59: =SUM(P55:P57) -> 3274275 | Q59: =SUM(Q55:Q57) -> 3312941 | R59: =SUM(R55:R57) -> 3279302 | S59: =SUM(S55:S57) -> 0
A60: -Proceed from term loans | B60: 0 | C60: 0 | D60: 0 | E60: 0 | F60: 3650000
B61: 0 | C61: 0 | D61: 0 | E61: 0 | K61: Total Liabilities | L61: =L59+L51 -> 1415175 | M61: =M59+M51 -> 1235101 | N61: =N59+N51 -> 1307642 | O61: =O59+O51 -> 1545310 | P61: =P59+P51 -> 5413755 | Q61: =Q59+Q51 -> 3980508 | R61: =R59+R51 -> 3905048 | S61: =S59+S51 -> 2765226
K63: Preference shares | O63: 0 | P63: 0 | Q63: 0 | S63: 0
A65: Free Cash Flow after Interest & repayment of finance lease | B65: =B21+SUM(B28:B34)+B42+B50-B32 -> -41699 | C65: =C21+SUM(C28:C34)+C42+C50-C32 -> -149815 | D65: =D21+SUM(D28:D34)+D42+D50-D32 -> 120134 | E65: =E21+SUM(E28:E34)+E42+E50-E32 -> 199064 | F65: =F21+SUM(F28:F34)+F42+F50-F32 -> -453300 | K65: Net Worth | L65: =L40-L61+L63 -> 409375 | M65: =M40-M61+M63 -> 474538 | N65: =N40-N61+N63 -> 558710 | O65: =O40-O61+O63 -> 467583 | P65: =P40-P61+P63 -> 1259535 | Q65: =Q40-Q61+Q63 -> 2557459 | R65: =R40-R61+R63 -> 2350185 | S65: =S40-S61+S63 -> 9176888
A66: Free Cash Flow before dividend payment | B66: =B65-B56 -> 331801 | C66: =C65-C56 -> -149815 | D66: =D65-D56 -> 120134 | E66: =E65-E56 -> 399064 | F66: =F65-F56 -> -253300 | K66: Net worth before dividend payment | L66: =L65+L48 -> 409375 | M66: =M65+M48 -> 474538 | N66: =N65+N48 -> 558710 | O66: =O65+O48 -> 467583 | P66: =P65+P48 -> 1702197 | Q66: =Q65+Q48 -> 2557459 | R66: =R65+R48 -> 2350185 | S66: =S65+S48 -> 9619550
A67: Table 1. Income Statement Reconstruction | K67: Table 2. Balance Sheet Reconstruction
A69: Normalised EBT (add back director fees + benefits) | B69: =B21 -> 688154 | C69: =C21 -> 65163 | D69: =D21 -> 84172 | E69: =E21 -> 117579 | F69: =F21 -> 941165 | K69: Cash on hand has been adjusted down to the amount required to support normal business operations.
K70: Amounts deemed uncollectible have been removed from the value of the accounts receivable.
A71: Calculation of growth rate:
A72: Net Income | B72: =B25 -> 631324 | C72: =C25 -> 65163 | D72: =D25 -> 84172 | E72: =E25 -> 108873 | F72: =F25 -> 791952
A73: Dividend paid | B73: =B56 -> -373500 | C73: =C56 -> 0 | D73: =D56 -> 0 | E73: =E56 -> -200000 | F73: =F56 -> -200000
A74: Dividend Payout Ratio | B74: =-B73/B72 -> 0.59161381 | C74: =-C73/C72 -> 0 | D74: =-D73/D72 -> 0 | E74: =-E73/E72 -> 1.8370027 | F74: =-F73/F72 -> 0.25254056
A75: Retention Ratio = (1-Dividend Payout Ratio) | B75: =1-B74 -> 0.40838619 | C75: =1-C74 -> 1 | D75: =1-D74 -> 1 | E75: =1-E74 -> -0.83700275 | F75: =1-F74 -> 0.74745944
A76: Return on Equity (ROE)=Net Income/Equity | B76: =B72/L65 -> 1.5421655 | C76: =C72/M65 -> 0.13731882 | D76: =D72/N65 -> 0.15065419 | E76: =E72/O65 -> 0.23284208 | F76: =F72/P65 -> 0.62876538
A77: Sustainable Long term Growth Rate (ROE X Retention Ratio) | B77: =B76*B75 -> 0.62979908 | C77: =C76*C75 -> 0.13731882 | D77: =D76*D75 -> 0.15065419 | E77: =E76*E75 -> -0.19488946 | F77: =F76*F75 -> 0.46997662 | G77: =AVERAGE(B77:F77) -> 0.23857185 | H77: average
A78: Total Capital/Equity (net worth) | B78: =L65 -> 409375 | C78: =M65 -> 474538 | D78: =N65 -> 558710 | E78: =O65 -> 467583 | F78: =P65 -> 1259535
A81: Note
A82: Although the company’s historical sustainable growth averaged 24%, the terminal growth rate has been capped at 3% to align with Singapore’s long‑term economic growth expectations.
G84: For the year ended
B85: Audited Accounts | H85: Annual
A86: Historic Income / Expense Items | B86: 2016 | C86: 2017 | D86: 2018 | E86: 2019 | F86: 2020 | G86: 44561 | H86: Average
A87: Administrative expenses | B87: 867671 | C87: 1043856 | D87: 986753 | E87: 1027409 | F87: 1329187 | G87: 913419
A88: Selling expenses | B88: 9600 | C88: 17328 | D88: 8926 | E88: 16576 | F88: 7976 | G88: 4376
A89: Other expenses | B89: 68957 | C89: 74725 | D89: 96403 | E89: 73338 | F89: 302404 | G89: 504692
A90: Finance costs | B90: 4466 | C90: 8748 | D90: 4464 | E90: 7014 | F90: 13809 | G90: 53313
A91: Total Operating expenses | B91: =SUM(B87:B90) -> 950694 | C91: =SUM(C87:C90) -> 1144657 | D91: =SUM(D87:D90) -> 1096546 | E91: =SUM(E87:E90) -> 1124337 | F91: =SUM(F87:F90) -> 1653376 | G91: =SUM(G87:G90) -> 1475800 | H91: =SUM(H87:H90) -> 0
A93: Breakdown of Misc Income @ 31 December 2021:
A94: Govt grants:
A95: -Employment credit | G95: =9015+25823+1409+6110 -> 42357
A96: -Job Support Scheme & skillsfuture credit | G96: =854992+157295+1147+89607 -> 1103041
A97: -Enterprise grants | G97: =4046+11946 -> 15992
A98: -Skillsfuture absentee payroll & training grants | G98: =160+120 -> 280
G99: =SUM(G95:G98) -> 1161670
A101: Other income
A102: -Nature 2000 takeover fee | G102: 1200
A103: -Omega Security Utilities & Cleaning, Service fee & adm | G103: =10833+1840+27268 -> 39941
A104: -Explomo Service fee & sale of antigen | G104: =79274+6447 -> 85721
A105: -Misc fm various parties | G105: =3+15+480+5 -> 503
A106: -Ant Enterprises Consultancy services | G106: =31963 -> 31963
A107: -AIMS Learning Utilities charge | G107: 839
A108: Subtotal | G108: =SUM(G102:G107) -> 160167
A110: Gain on disposal of Fixed assets
A111: -Porsche | G111: =148000 -> 148000
A112: -toyota Harrier | G112: =130000 -> 130000
A113: Subtotal | G113: =SUM(G111:G112) -> 278000
A115: Rental Income
A116: -Omega | G116: =12000 -> 12000
A117: -Explomo | G117: =148000 -> 148000
A118: -AIMS Learning | G118: =23400 -> 23400
A119: Subtotal | G119: =SUM(G116:G118) -> 183400
A120: grant total | G120: =G108+G113+G119+G99 -> 1783237
A122: Loss on disposal of fixed assets
A123: -Porsche | G123: =123034 -> 123034
A124: -Toyota Harrier | G124: =129488 -> 129488
...

Sheet 03_Beta_Calculation
B1: Adjustments of unlevered beta (UB) due to the Middle East Conflict which may have a negative effect on the Singapore Real Estate Industry:
B2: Factors to adjust as of (April 2026):
B3: 1. Cost Factor (Increase Risk)
B4: 2. Capital Flow Factor (Decrease Risk): Heightened tensions can cause a flight to safety, where wealthy individuals and investors move capital into Singapore, increasing property demand
B5: 3. Valuation Factor (Mixed): A prolonged conflict might cause higher inflation, raising long-term borrowing costs, which is negative for S-REITs
B6: 4. Suggested Adjustment Magnitude:
B7: 4a. If the REIT has high exposure to Industrial/logistics assets: -Increase beta by +0.05 to +0.10 to account for supply chain disruption risks, despite potential logistical benefits.
B8: 4b. If the REIT is a prime office/residential "Safe Haven" play: The beta might actually remain stable or slightly decrease due to capital inflows, but the higher interest rate environment suggests a modest increase of +0.05 to account for valuation volatility.
B9: Summary Recommendation: Instead of a straight addition to the final levered beta, increase the Unlevered Beta of the comparable peer set by a factor reflecting your specific risk scenario (e.g. 5-10%) higher for a moderate risk scenario then re-lever it.
A10: A | B10: Calculations of Industry Risk in a Buildup Model
C12: Total Mkt Cap $ | D12: LB (obtained from SGX) | E12: UB = LB /(1+ (1-T)* (D/E)) | F12: D %age of debts | G12: E %age of equity | H12: Total debt | I12: Total Equity | J12: Total Equity Total Debts | K12: P/E ratio | L12: Dividend yield | M12: Sh price on 10 May 2022 | N12: Sh price on 31 Decc 2021 | O12: Percentage +ve drop/-ve increase | P12: Gross Revenue ($million) | Q12: EBITDA | R12: Total Assets | S12: Free Cash Flow (FCF) | T12: Price/Gross Revenue | U12: Price/EBITDA | V12: Price/Total Assests | W12: Price/FCF
A13: 1 | B13: ='16_DB-SGX_Loading'!B10 -> COSCO SHP SG | C13: ='16_DB-SGX_Loading'!C10 -> 510.548 | D13: ='16_DB-SGX_Loading'!D10 -> 0.71 | E13: =D13/(1+(1-0.17)*(F13/G13)) -> 0.64578105 | F13: =H13/J13% -> 10.699284 | G13: =I13/J13% -> 89.300716 | H13: ='16_DB-SGX_Loading'!E10 -> 93.583 | I13: ='16_DB-SGX_Loading'!F10 -> 781.083 | J13: =H13+I13 -> 874.666 | K13: ='16_DB-SGX_Loading'!H10 -> 0 | L13: ='16_DB-SGX_Loading'!I10 -> 0.78 | M13: ='16_DB-SGX_Loading'!J10 -> 0.114 | N13: ='16_DB-SGX_Loading'!K10 -> 0.121 | O13: =(M13-N13)/N13*100 -> -5.785124 | P13: ='16_DB-SGX_Loading'!M10 -> 193.999 | Q13: ='16_DB-SGX_Loading'!N10 -> 61.285 | R13: ='16_DB-SGX_Loading'!O10 -> 980.308 | S13: ='16_DB-SGX_Loading'!P10 -> 33.245 | T13: =C13/P13 -> 2.6317043 | U13: =C13/Q13 -> 8.3307171 | V13: =C13/R13 -> 0.52080367 | W13: =C13/S13 -> 15.357136
A14: 2 | B14: ='16_DB-SGX_Loading'!B11 -> SATS | C14: ='16_DB-SGX_Loading'!C11 -> 5321 | D14: ='16_DB-SGX_Loading'!D11 -> 0.52 | E14: =D14/(1+(1-0.17)*(F14/G14)) -> 0.33495355 | F14: =H14/J14% -> 39.961838 | G14: =I14/J14% -> 60.038162 | H14: ='16_DB-SGX_Loading'!E11 -> 1843 | I14: ='16_DB-SGX_Loading'!F11 -> 2768.9 | J14: =H14+I14 -> 4611.9 | K14: ='16_DB-SGX_Loading'!H11 -> 19.89 | L14: ='16_DB-SGX_Loading'!I11 -> 1.54 | M14: ='16_DB-SGX_Loading'!J11 -> 3.58 | N14: ='16_DB-SGX_Loading'!K11 -> 3.81 | O14: =(M14-N14)/N14*100 -> -6.0367454 | P14: ='16_DB-SGX_Loading'!M11 -> 5821 | Q14: ='16_DB-SGX_Loading'!N11 -> 1166 | R14: ='16_DB-SGX_Loading'!O11 -> 8882 | S14: ='16_DB-SGX_Loading'!P11 -> 669.4 | T14: =C14/P14 -> 0.91410411 | U14: =C14/Q14 -> 4.5634648 | V14: =C14/R14 -> 0.59907678 | W14: =C14/S14 -> 7.9489095
A15: 3 | B15: ='16_DB-SGX_Loading'!B12 -> SIA | C15: ='16_DB-SGX_Loading'!C12 -> 20973 | D15: ='16_DB-SGX_Loading'!D12 -> 0.5 | E15: =D15/(1+(1-0.17)*(F15/G15)) -> 0.29993801 | F15: =H15/J15% -> 44.556191 | G15: =I15/J15% -> 55.443809 | H15: ='16_DB-SGX_Loading'!E12 -> 12914.3 | I15: ='16_DB-SGX_Loading'!F12 -> 16070 | J15: =H15+I15 -> 28984.3 | K15: ='16_DB-SGX_Loading'!H12 -> 17.5 | L15: ='16_DB-SGX_Loading'!I12 -> 5.26 | M15: ='16_DB-SGX_Loading'!J12 -> 6.65 | N15: ='16_DB-SGX_Loading'!K12 -> 6.4 | O15: =(M15-N15)/N15*100 -> 3.90625 | P15: ='16_DB-SGX_Loading'!M12 -> 19539.8 | Q15: ='16_DB-SGX_Loading'!N12 -> 5711.9 | R15: ='16_DB-SGX_Loading'!O12 -> 43086.8 | S15: ='16_DB-SGX_Loading'!P12 -> 2834 | T15: =C15/P15 -> 1.0733477 | U15: =C15/Q15 -> 3.671808 | V15: =C15/R15 -> 0.48676161 | W15: =C15/S15 -> 7.400494
A16: 4 | B16: ='16_DB-SGX_Loading'!B13 -> SIA Engineering | C16: ='16_DB-SGX_Loading'!C13 -> 3651 | D16: ='16_DB-SGX_Loading'!D13 -> 0.32 | E16: =D16/(1+(1-0.17)*(F16/G16)) -> 0.30751392 | F16: =H16/J16% -> 4.6638129 | G16: =I16/J16% -> 95.336187 | H16: ='16_DB-SGX_Loading'!E13 -> 85.199 | I16: ='16_DB-SGX_Loading'!F13 -> 1741.611 | J16: =H16+I16 -> 1826.81 | K16: ='16_DB-SGX_Loading'!H13 -> 23.29 | L16: ='16_DB-SGX_Loading'!I13 -> 2.91 | M16: ='16_DB-SGX_Loading'!J13 -> 3.26 | N16: ='16_DB-SGX_Loading'!K13 -> 3.6 | O16: =(M16-N16)/N16*100 -> -9.4444444 | P16: ='16_DB-SGX_Loading'!M13 -> 1245 | Q16: ='16_DB-SGX_Loading'!N13 -> 214.881 | R16: ='16_DB-SGX_Loading'!O13 -> 2141.393 | S16: ='16_DB-SGX_Loading'!P13 -> 102.603 | T16: =C16/P16 -> 2.9325301 | U16: =C16/Q16 -> 16.9908 | V16: =C16/R16 -> 1.7049649 | W16: =C16/S16 -> 35.583755
A17: 5 | B17: ='16_DB-SGX_Loading'!B14 -> SingPost | C17: ='16_DB-SGX_Loading'!C14 -> 776.687 | D17: ='16_DB-SGX_Loading'!D14 -> 0.21 | E17: =D17/(1+(1-0.17)*(F17/G17)) -> 0.17629808 | F17: =H17/J17% -> 18.720237 | G17: =I17/J17% -> 81.279763 | H17: ='16_DB-SGX_Loading'!E14 -> 370.232 | I17: ='16_DB-SGX_Loading'!F14 -> 1607.478 | J17: =H17+I17 -> 1977.71 | K17: ='16_DB-SGX_Loading'!H14 -> 3.14 | L17: ='16_DB-SGX_Loading'!I14 -> 1.22 | M17: ='16_DB-SGX_Loading'!J14 -> 0.345 | N17: ='16_DB-SGX_Loading'!K14 -> 0.405 | O17: =(M17-N17)/N17*100 -> -14.814815 | P17: ='16_DB-SGX_Loading'!M14 -> 813.704 | Q17: ='16_DB-SGX_Loading'!N14 -> 387.25 | R17: ='16_DB-SGX_Loading'!O14 -> 2390.424 | S17: ='16_DB-SGX_Loading'!P14 -> 26.671 | T17: =C17/P17 -> 0.95450803 | U17: =C17/Q17 -> 2.0056475 | V17: =C17/R17 -> 0.324916 | W17: =C17/S17 -> 29.12103
A18: 6 | B18: ='16_DB-SGX_Loading'!B15 -> Wing Tai | C18: ='16_DB-SGX_Loading'!C15 -> 1222 | D18: ='16_DB-SGX_Loading'!D15 -> 0.23 | E18: =D18/(1+(1-0.17)*(F18/G18)) -> 0.16972396 | F18: =H18/J18% -> 29.966174 | G18: =I18/J18% -> 70.033826 | H18: ='16_DB-SGX_Loading'!E15 -> 1242.121 | I18: ='16_DB-SGX_Loading'!F15 -> 2902.956 | J18: =H18+I18 -> 4145.077 | K18: ='16_DB-SGX_Loading'!H15 -> 0 | L18: ='16_DB-SGX_Loading'!I15 -> 1.88 | M18: ='16_DB-SGX_Loading'!J15 -> 1.6 | N18: ='16_DB-SGX_Loading'!K15 -> 1.42 | O18: =(M18-N18)/N18*100 -> 12.676056 | P18: ='16_DB-SGX_Loading'!M15 -> 230.206 | Q18: ='16_DB-SGX_Loading'!N15 -> -4.157 | R18: ='16_DB-SGX_Loading'!O15 -> 4275.552 | S18: ='16_DB-SGX_Loading'!P15 -> -447.444 | T18: =C18/P18 -> 5.3082891 | U18: =C18/Q18 -> -293.96199 | V18: =C18/R18 -> 0.28581105 | W18: =C18/S18 -> -2.731068
A19: 7 | B19: ='16_DB-SGX_Loading'!B16 -> CapitaLandInvest | C19: ='16_DB-SGX_Loading'!C16 -> 13679 | D19: ='16_DB-SGX_Loading'!D16 -> 0.61 | E19: =D19/(1+(1-0.17)*(F19/G19)) -> 0.40149196 | F19: =H19/J19% -> 38.488129 | G19: =I19/J19% -> 61.511871 | H19: ='16_DB-SGX_Loading'!E16 -> 8462 | I19: ='16_DB-SGX_Loading'!F16 -> 13524 | J19: =H19+I19 -> 21986 | K19: ='16_DB-SGX_Loading'!H16 -> 91.33 | L19: ='16_DB-SGX_Loading'!I16 -> 4.38 | M19: ='16_DB-SGX_Loading'!J16 -> 2.74 | N19: ='16_DB-SGX_Loading'!K16 -> 2.71 | O19: =(M19-N19)/N19*100 -> 1.1070111 | P19: ='16_DB-SGX_Loading'!M16 -> 2133 | Q19: ='16_DB-SGX_Loading'!N16 -> 735 | R19: ='16_DB-SGX_Loading'!O16 -> 24211 | S19: ='16_DB-SGX_Loading'!P16 -> 479 | T19: =C19/P19 -> 6.4130333 | U19: =C19/Q19 -> 18.610884 | V19: =C19/R19 -> 0.56499112 | W19: =C19/S19 -> 28.557411
A20: 8 | B20: ='16_DB-SGX_Loading'!B17 -> ComfortDelGro | C20: ='16_DB-SGX_Loading'!C17 -> 3120 | D20: ='16_DB-SGX_Loading'!D17 -> 0.24 | E20: =D20/(1+(1-0.17)*(F20/G20)) -> 0.15923447 | F20: =H20/J20% -> 37.930532 | G20: =I20/J20% -> 62.069468 | H20: ='16_DB-SGX_Loading'!E17 -> 1821.5 | I20: ='16_DB-SGX_Loading'!F17 -> 2980.7 | J20: =H20+I20 -> 4802.2 | K20: ='16_DB-SGX_Loading'!H17 -> 13.09 | L20: ='16_DB-SGX_Loading'!I17 -> 5.9 | M20: ='16_DB-SGX_Loading'!J17 -> 1.44 | N20: ='16_DB-SGX_Loading'!K17 -> 1.48 | O20: =(M20-N20)/N20*100 -> -2.7027027 | P20: ='16_DB-SGX_Loading'!M17 -> 5058 | Q20: ='16_DB-SGX_Loading'!N17 -> 793.8 | R20: ='16_DB-SGX_Loading'!O17 -> 6138.9 | S20: ='16_DB-SGX_Loading'!P17 -> -136.5 | T20: =C20/P20 -> 0.6168446 | U20: =C20/Q20 -> 3.9304611 | V20: =C20/R20 -> 0.50823437 | W20: =C20/S20 -> -22.857143
A21: 9 | B21: ='16_DB-SGX_Loading'!B18 -> Frasers Property | C21: ='16_DB-SGX_Loading'!C18 -> 3808 | D21: ='16_DB-SGX_Loading'!D18 -> 0.33 | E21: =D21/(1+(1-0.17)*(F21/G21)) -> 0.17398972 | F21: =H21/J21% -> 51.930422 | G21: =I21/J21% -> 48.069578 | H21: ='16_DB-SGX_Loading'!E18 -> 18525.843 | I21: ='16_DB-SGX_Loading'!F18 -> 17148.512 | J21: =H21+I21 -> 35674.355 | K21: ='16_DB-SGX_Loading'!H18 -> 16.17 | L21: ='16_DB-SGX_Loading'!I18 -> 4.64 | M21: ='16_DB-SGX_Loading'!J18 -> 0.97 | N21: ='16_DB-SGX_Loading'!K18 -> 1.13 | O21: =(M21-N21)/N21*100 -> -14.159292 | P21: ='16_DB-SGX_Loading'!M18 -> 3403.519 | Q21: ='16_DB-SGX_Loading'!N18 -> 1322.534 | R21: ='16_DB-SGX_Loading'!O18 -> 39747.618 | S21: ='16_DB-SGX_Loading'!P18 -> 981.788 | T21: =C21/P21 -> 1.118842 | U21: =C21/Q21 -> 2.8793211 | V21: =C21/R21 -> 0.095804483 | W21: =C21/S21 -> 3.8786378
B23: Total: | D23: =SUM(D13:D21) -> 3.67 | E23: =SUM(E13:E21) -> 2.6689247 | F23: =AVERAGE(H13:H21)/AVERAGE(I13:I21) -> 0.76199236 | G23: Average D/Average L
B24: Average: | D24: =AVERAGE(D13:D21) -> 0.40777778 | E24: =AVERAGE(E13:E21) -> 0.29654719 | F24: =E24*(1+(1-E70)*F23) -> 0.48409955 | G24: rel-levered beta using the industry component stocks D/L
A25: 4 | B25: Premium for Industry specific: | E25: =D29 -> -2.3989371
B26: *Where T is the corporate tax rate of 17%
B27: Re-levered beta of average 9 comparables | C27: Ri | D27: =F24 -> 0.48409955
C28: ERP | D28: =' 04_CAPM'!D7 -> 4.65
B29: IRPί = (Rί X ERP) - ERP | C29: IRPi | D29: =(D27*D28)-D28 -> -2.3989371
B30: IRPί = (1.234 X 4.65) - 4.65 = 5.7381 -4.65 = 1.0881
B32: assuming Rί = 1.234 re-levered beta for the Event Management industry
A34: where:
A35: IRPί = the expected industry risk premium for industry ί, or the amount by which investors expect the future return of the industry to exceed that of the market as a whole;
A36: Ri = the risk index (full information beta) for the industry ί; and
A37: ERP = the expected equity risk premium
A42: B | B42: Calculations of Unlevered beta for small cap stocks
B43: Data/Information from SGX website
C44: Total Mkt Cap $ million | D44: LB | E44: UB = LB / (1+ (1-T)* (D/E)) | F44: D %age of debts [Total Debt / (Total Equity + Total Debt)] | G44: E %age of equity [Total Equity / (Total Equity + Total Debt)] | H44: Total debt | I44: Total Equity | J44: Total Equity + Total Debts | K44: P/E ratio | L44: Dividend yield | M44: Sh price on 30 Apr 2025 | N44: Sh price on 31 Dec 2024 | O44: Percentage +ve drop/-ve increase | P44: Gross Revenue ($million) | Q44: EBITDA | R44: Total Assets | S44: Free Cash Flow (FCF) | T44: Price/Gross Revenue | U44: Price/EBITDA | V44: Price/Total Assests | W44: Price/FCF | X44: Stk code | Y44: Currency
A45: 1 | B45: ='16_DB-SGX_Loading'!B22 -> Audience | C45: ='16_DB-SGX_Loading'!C22 -> 60.492 | D45: ='16_DB-SGX_Loading'!D22 -> 0.08 | E45: =D45/(1+(1-$D$76)*(F45/G45)) -> 0.079920179 | F45: =H45/J45% -> 0.12018715 | G45: =I45/J45% -> 99.879813 | H45: ='16_DB-SGX_Loading'!E22 -> 0.028 | I45: ='16_DB-SGX_Loading'!F22 -> 23.269 | J45: =H45+I45 -> 23.297 | K45: ='16_DB-SGX_Loading'!H22 -> 13 | L45: ='16_DB-SGX_Loading'!I22 -> 5.77 | M45: ='16_DB-SGX_Loading'!J22 -> 0.26 | N45: ='16_DB-SGX_Loading'!K22 -> 0.26 | O45: =(N45-M45)/N45*100 -> 0 | P45: ='16_DB-SGX_Loading'!M22 -> 15.956 | Q45: ='16_DB-SGX_Loading'!N22 -> 5.788 | R45: ='16_DB-SGX_Loading'!O22 -> 26.015 | S45: ='16_DB-SGX_Loading'!P22 -> 4.436 | T45: ='16_DB-SGX_Loading'!Q22 -> 3.7911757 | U45: ='16_DB-SGX_Loading'!R22 -> 10.451279 | V45: ='16_DB-SGX_Loading'!S22 -> 2.3252739 | W45: ='16_DB-SGX_Loading'!T22 -> 13.63661 | X45: 1AZ
A46: 2 | B46: ='16_DB-SGX_Loading'!B23 -> Dezign Format | C46: ='16_DB-SGX_Loading'!C23 -> 38 | D46: ='16_DB-SGX_Loading'!D23 -> 1 | E46: =D46/(1+(1-$D$76)*(F46/G46)) -> 0.84807461 | F46: =H46/J46% -> 17.751875 | G46: =I46/J46% -> 82.248125 | H46: ='16_DB-SGX_Loading'!E23 -> 2.391 | I46: ='16_DB-SGX_Loading'!F23 -> 11.078 | J46: =H46+I46 -> 13.469 | K46: ='16_DB-SGX_Loading'!H23 -> 19 | L46: ='16_DB-SGX_Loading'!I23 -> 0 | M46: ='16_DB-SGX_Loading'!J23 -> 0.19 | N46: ='16_DB-SGX_Loading'!K23 -> 0.23 | O46: =(N46-M46)/N46*100 -> 17.391304 | P46: ='16_DB-SGX_Loading'!M23 -> 33.104 | Q46: ='16_DB-SGX_Loading'!N23 -> 3.03 | R46: ='16_DB-SGX_Loading'!O23 -> 24.951 | S46: ='16_DB-SGX_Loading'!P23 -> -6.511 | T46: ='16_DB-SGX_Loading'!Q23 -> 1.1478975 | U46: ='16_DB-SGX_Loading'!R23 -> 12.541254 | V46: ='16_DB-SGX_Loading'!S23 -> 1.5229851 | W46: ='16_DB-SGX_Loading'!T23 -> -5.8362771 | X46: UZF
A47: 3 | B47: ='16_DB-SGX_Loading'!B24 -> GKE | C47: ='16_DB-SGX_Loading'!C24 -> 64.395 | D47: ='16_DB-SGX_Loading'!D24 -> 0.28 | E47: =D47/(1+(1-$D$76)*(F47/G47)) -> 0.1943974 | F47: =H47/J47% -> 34.663595 | G47: =I47/J47% -> 65.336405 | H47: ='16_DB-SGX_Loading'!E24 -> 53.123 | I47: ='16_DB-SGX_Loading'!F24 -> 100.13 | J47: =H47+I47 -> 153.253 | K47: ='16_DB-SGX_Loading'!H24 -> 7.5 | L47: ='16_DB-SGX_Loading'!I24 -> 5.33 | M47: ='16_DB-SGX_Loading'!J24 -> 0.075 | N47: ='16_DB-SGX_Loading'!K24 -> 0.095 | O47: =(N47-M47)/N47*100 -> 21.052632 | P47: ='16_DB-SGX_Loading'!M24 -> 126.519 | Q47: ='16_DB-SGX_Loading'!N24 -> 29.927 | R47: ='16_DB-SGX_Loading'!O24 -> 184.24 | S47: ='16_DB-SGX_Loading'!P24 -> 14.761 | T47: ='16_DB-SGX_Loading'!Q24 -> 0.50897494 | U47: ='16_DB-SGX_Loading'!R24 -> 2.1517359 | V47: ='16_DB-SGX_Loading'!S24 -> 0.34951693 | W47: ='16_DB-SGX_Loading'!T24 -> 4.3625093 | X47: 595 | Y47: JPY
A48: 4 | B48: ='16_DB-SGX_Loading'!B25 -> Hiap Tong | C48: ='16_DB-SGX_Loading'!C25 -> 35.545 | D48: ='16_DB-SGX_Loading'!D25 -> -0.04 | E48: =D48/(1+(1-$D$76)*(F48/G48)) -> -0.027828632 | F48: =H48/J48% -> 34.509974 | G48: =I48/J48% -> 65.490026 | H48: ='16_DB-SGX_Loading'!E25 -> 52.646 | I48: ='16_DB-SGX_Loading'!F25 -> 99.907 | J48: =H48+I48 -> 152.553 | K48: ='16_DB-SGX_Loading'!H25 -> 11.2 | L48: ='16_DB-SGX_Loading'!I25 -> 0.89 | M48: ='16_DB-SGX_Loading'!J25 -> 0.112 | N48: ='16_DB-SGX_Loading'!K25 -> 0.096 | O48: =(N48-M48)/N48*100 -> -16.666667 | P48: ='16_DB-SGX_Loading'!M25 -> 91.916 | Q48: ='16_DB-SGX_Loading'!N25 -> 23.985 | R48: ='16_DB-SGX_Loading'!O25 -> 182.026 | S48: ='16_DB-SGX_Loading'!P25 -> 19.872 | T48: ='16_DB-SGX_Loading'!Q25 -> 0.38671178 | U48: ='16_DB-SGX_Loading'!R25 -> 1.4819679 | V48: ='16_DB-SGX_Loading'!S25 -> 0.1952743 | W48: ='16_DB-SGX_Loading'!T25 -> 1.7886977 | X48: 5PO
A49: 5 | B49: ='16_DB-SGX_Loading'!B26 -> LS 2 Holdings | C49: ='16_DB-SGX_Loading'!C26 -> 14.8 | D49: ='16_DB-SGX_Loading'!D26 -> 4.11 | E49: =D49/(1+(1-$D$76)*(F49/G49)) -> 3.7729933 | F49: =H49/J49% -> 9.7159543 | G49: =I49/J49% -> 90.284046 | H49: ='16_DB-SGX_Loading'!E26 -> 2.562 | I49: ='16_DB-SGX_Loading'!F26 -> 23.807 | J49: =H49+I49 -> 26.369 | K49: ='16_DB-SGX_Loading'!H26 -> 4 | L49: ='16_DB-SGX_Loading'!I26 -> 0 | M49: ='16_DB-SGX_Loading'!J26 -> 0.08 | N49: ='16_DB-SGX_Loading'!K26 -> 0.074 | O49: =(N49-M49)/N49*100 -> -8.1081081 | P49: ='16_DB-SGX_Loading'!M26 -> 71.805 | Q49: ='16_DB-SGX_Loading'!N26 -> 7.614 | R49: ='16_DB-SGX_Loading'!O26 -> 37.841 | S49: ='16_DB-SGX_Loading'!P26 -> 6.154 | T49: ='16_DB-SGX_Loading'!Q26 -> 0.20611378 | U49: ='16_DB-SGX_Loading'!R26 -> 1.9437878 | V49: ='16_DB-SGX_Loading'!S26 -> 0.39111017 | W49: ='16_DB-SGX_Loading'!T26 -> 2.4049399 | X49: ENV
A50: 6 | B50: ='16_DB-SGX_Loading'!B27 -> VCPlus | C50: ='16_DB-SGX_Loading'!C27 -> 17.012 | D50: ='16_DB-SGX_Loading'!D27 -> 0.69 | E50: =D50/(1+(1-$D$76)*(F50/G50)) -> 0.56308174 | F50: =H50/J50% -> 21.356784 | G50: =I50/J50% -> 78.643216 | H50: ='16_DB-SGX_Loading'!E27 -> 0.17 | I50: ='16_DB-SGX_Loading'!F27 -> 0.626 | J50: =H50+I50 -> 0.796 | K50: ='16_DB-SGX_Loading'!H27 -> 0 | L50: ='16_DB-SGX_Loading'!I27 -> 0 | M50: ='16_DB-SGX_Loading'!J27 -> 0.003 | N50: ='16_DB-SGX_Loading'!K27 -> 0.003 | O50: =(N50-M50)/N50*100 -> 0 | P50: ='16_DB-SGX_Loading'!M27 -> 0.191 | Q50: ='16_DB-SGX_Loading'!N27 -> -2.281 | R50: ='16_DB-SGX_Loading'!O27 -> 1.471 | S50: ='16_DB-SGX_Loading'!P27 -> -1.388 | T50: ='16_DB-SGX_Loading'!Q27 -> 89.068063 | U50: ='16_DB-SGX_Loading'!R27 -> -7.4581324 | V50: ='16_DB-SGX_Loading'!S27 -> 11.564922 | W50: ='16_DB-SGX_Loading'!T27 -> -12.256484 | X50: 43E
A51: 7 | B51: ='16_DB-SGX_Loading'!B28 -> ZICO Hldgs | C51: ='16_DB-SGX_Loading'!C28 -> 19.707 | D51: ='16_DB-SGX_Loading'!D28 -> 0.18 | E51: =D51/(1+(1-$D$76)*(F51/G51)) -> 0.142867 | F51: =H51/J51% -> 23.847139 | G51: =I51/J51% -> 76.152861 | H51: ='16_DB-SGX_Loading'!E28 -> 8.936 | I51: ='16_DB-SGX_Loading'!F28 -> 28.536 | J51: =H51+I51 -> 37.472 | K51: ='16_DB-SGX_Loading'!H28 -> 0 | L51: ='16_DB-SGX_Loading'!I28 -> 0 | M51: ='16_DB-SGX_Loading'!J28 -> 0.048 | N51: ='16_DB-SGX_Loading'!K28 -> 0.055 | O51: =(M51-N51)/N51*100 -> -12.727273 | P51: ='16_DB-SGX_Loading'!M28 -> 14.312 | Q51: ='16_DB-SGX_Loading'!N28 -> 3.549 | R51: ='16_DB-SGX_Loading'!O28 -> 42.196 | S51: ='16_DB-SGX_Loading'!P28 -> -0.504 | T51: ='16_DB-SGX_Loading'!Q28 -> 1.3769564 | U51: ='16_DB-SGX_Loading'!R28 -> 5.5528318 | V51: ='16_DB-SGX_Loading'!S28 -> 0.46703479 | W51: ='16_DB-SGX_Loading'!T28 -> -39.10119 | X51: 40W
A52: 8 | B52: ='16_DB-SGX_Loading'!B29 -> UnUsUaL | C52: ='16_DB-SGX_Loading'!C29 -> 25.553 | D52: ='16_DB-SGX_Loading'!D29 -> -0.38 | E52: =D52/(1+(1-$D$76)*(F52/G52)) -> -0.36048031 | F52: =H52/J52% -> 6.124434 | G52: =I52/J52% -> 93.875566 | H52: ='16_DB-SGX_Loading'!E29 -> 1.826 | I52: ='16_DB-SGX_Loading'!F29 -> 27.989 | J52: =H52+I52 -> 29.815 | K52: ='16_DB-SGX_Loading'!H29 -> 0 | L52: ='16_DB-SGX_Loading'!I29 -> 0 | M52: ='16_DB-SGX_Loading'!J29 -> 0.025 | N52: ='16_DB-SGX_Loading'!K29 -> 0.036 | O52: =(M52-N52)/N52*100 -> -30.555556 | P52: ='16_DB-SGX_Loading'!M29 -> 53.219 | Q52: ='16_DB-SGX_Loading'!N29 -> -18.575 | R52: ='16_DB-SGX_Loading'!O29 -> 37.47 | S52: ='16_DB-SGX_Loading'!P29 -> 4.373 | T52: ='16_DB-SGX_Loading'!Q29 -> 0.48014807 | U52: ='16_DB-SGX_Loading'!R29 -> -1.3756662 | V52: ='16_DB-SGX_Loading'!S29 -> 0.6819589 | W52: ='16_DB-SGX_Loading'!T29 -> 5.843357 | X52: 1D1
A53: 9 | B53: ='16_DB-SGX_Loading'!B30 -> Abundante | C53: ='16_DB-SGX_Loading'!C30 -> 15.26 | D53: ='16_DB-SGX_Loading'!D30 -> 0.3 | E53: =D53/(1+(1-$D$76)*(F53/G53)) -> 0.29999866 | F53: =H53/J53% -> 0.00053647781 | G53: =I53/J53% -> 99.999464 | H53: 0.0001 | I53: ='16_DB-SGX_Loading'!F30 -> 18.64 | J53: =H53+I53 -> 18.6401 | K53: ='16_DB-SGX_Loading'!H30 -> 0 | L53: ='16_DB-SGX_Loading'!I30 -> 0 | M53: ='16_DB-SGX_Loading'!J30 -> 0.15 | N53: ='16_DB-SGX_Loading'!K30 -> 0.16 | O53: =(M53-N53)/N53*100 -> -6.25 | P53: ='16_DB-SGX_Loading'!M30 -> 7.326 | Q53: ='16_DB-SGX_Loading'!N30 -> 0.781 | R53: ='16_DB-SGX_Loading'!O30 -> 19.592 | S53: ='16_DB-SGX_Loading'!P30 -> 0.2511 | T53: ='16_DB-SGX_Loading'!Q30 -> 2.0829921 | U53: ='16_DB-SGX_Loading'!R30 -> 19.539052 | V53: ='16_DB-SGX_Loading'!S30 -> 0.77888934 | W53: ='16_DB-SGX_Loading'!T30 -> 60.772601 | X53: 570
A54: 10 | B54: ='16_DB-SGX_Loading'!B32 -> Chasen | C54: ='16_DB-SGX_Loading'!C32 -> 29.45 | D54: ='16_DB-SGX_Loading'!D32 -> 0.28 | E54: =D54/(1+(1-$D$76)*(F54/G54)) -> 0.13883524 | F54: =H54/J54% -> 55.056886 | G54: =I54/J54% -> 44.943114 | H54: ='16_DB-SGX_Loading'!E32 -> 100.704 | I54: ='16_DB-SGX_Loading'!F32 -> 82.205 | J54: =H54+I54 -> 182.909 | K54: ='16_DB-SGX_Loading'!H32 -> 0 | L54: ='16_DB-SGX_Loading'!I32 -> 0 | M54: ='16_DB-SGX_Loading'!J32 -> 0.077 | N54: ='16_DB-SGX_Loading'!K32 -> 0.087 | O54: =(M54-N54)/N54*100 -> -11.494253 | P54: ='16_DB-SGX_Loading'!M32 -> 116.322 | Q54: ='16_DB-SGX_Loading'!N32 -> 5.151 | R54: ='16_DB-SGX_Loading'!O32 -> 205.471 | S54: ='16_DB-SGX_Loading'!P32 -> -53.247 | T54: ='16_DB-SGX_Loading'!Q32 -> 0.25317653 | U54: ='16_DB-SGX_Loading'!R32 -> 5.7173364 | V54: ='16_DB-SGX_Loading'!S32 -> 0.14332923 | W54: ='16_DB-SGX_Loading'!T32 -> -0.5530828 | X54: 5NV
A55: 11 | B55: ='16_DB-SGX_Loading'!B33 -> Eneco Energy | C55: ='16_DB-SGX_Loading'!C33 -> 34.208 | D55: ='16_DB-SGX_Loading'!D33 -> 0.66 | E55: =D55/(1+(1-$D$76)*(F55/G55)) -> 0.48144479 | F55: =H55/J55% -> 30.883656 | G55: =I55/J55% -> 69.116344 | H55: ='16_DB-SGX_Loading'!E33 -> 9.758 | I55: ='16_DB-SGX_Loading'!F33 -> 21.838 | J55: =H55+I55 -> 31.596 | K55: ='16_DB-SGX_Loading'!H33 -> 0 | L55: ='16_DB-SGX_Loading'!I33 -> 0 | M55: ='16_DB-SGX_Loading'!J33 -> 0.009 | N55: ='16_DB-SGX_Loading'!K33 -> 0.01 | O55: =(M55-N55)/N55*100 -> -10 | P55: ='16_DB-SGX_Loading'!M33 -> 31.302 | Q55: ='16_DB-SGX_Loading'!N33 -> 6.523 | R55: ='16_DB-SGX_Loading'!O33 -> 37.445 | S55: ='16_DB-SGX_Loading'!P33 -> 3.373 | T55: ='16_DB-SGX_Loading'!Q33 -> 1.0928375 | U55: ='16_DB-SGX_Loading'!R33 -> 5.2442128 | V55: ='16_DB-SGX_Loading'!S33 -> 0.91355321 | W55: ='16_DB-SGX_Loading'!T33 -> 10.141714 | X55: R14
A56: 12 | B56: ='16_DB-SGX_Loading'!B34 -> KingsmenCreative | C56: ='16_DB-SGX_Loading'!C34 -> 120.159 | D56: ='16_DB-SGX_Loading'!D34 -> 0.22 | E56: =D56/(1+(1-$D$76)*(F56/G56)) -> 0.19939953 | F56: =H56/J56% -> 11.069445 | G56: =I56/J56% -> 88.930555 | H56: ='16_DB-SGX_Loading'!E34 -> 15.468 | I56: ='16_DB-SGX_Loading'!F34 -> 124.268 | J56: =H56+I56 -> 139.736 | K56: ='16_DB-SGX_Loading'!H34 -> 8.5 | L56: ='16_DB-SGX_Loading'!I34 -> 5.04 | M56: ='16_DB-SGX_Loading'!J34 -> 0.595 | N56: ='16_DB-SGX_Loading'!K34 -> 0.5 | O56: =(M56-N56)/N56*100 -> 19 | P56: ='16_DB-SGX_Loading'!M34 -> 372.544 | Q56: ='16_DB-SGX_Loading'!N34 -> 23.413 | R56: ='16_DB-SGX_Loading'!O34 -> 284.754 | S56: ='16_DB-SGX_Loading'!P34 -> 27.541 | T56: ='16_DB-SGX_Loading'!Q34 -> 0.3225364 | U56: ='16_DB-SGX_Loading'!R34 -> 5.1321488 | V56: ='16_DB-SGX_Loading'!S34 -> 0.42197476 | W56: ='16_DB-SGX_Loading'!T34 -> 4.3629135 | X56: 5MZ
A57: 13 | B57: ='16_DB-SGX_Loading'!B19 -> Raffles Edu | C57: ='16_DB-SGX_Loading'!C19 -> 224.357 | D57: ='16_DB-SGX_Loading'!D19 -> 0.72 | E57: =D57/(1+(1-0.17)*(F57/G57)) -> 0.56091346 | F57: =H57/J57% -> 25.468324 | G57: =I57/J57% -> 74.531676 | H57: ='16_DB-SGX_Loading'!E19 -> 218.887 | I57: ='16_DB-SGX_Loading'!F19 -> 640.561 | J57: =H57+I57 -> 859.448 | K57: ='16_DB-SGX_Loading'!H19 -> 0 | L57: ='16_DB-SGX_Loading'!I19 -> 0 | M57: ='16_DB-SGX_Loading'!J19 -> 0.126 | N57: ='16_DB-SGX_Loading'!K19 -> 0.139 | O57: =(M57-N57)/N57*100 -> -9.352518 | P57: ='16_DB-SGX_Loading'!M19 -> 111.71 | Q57: ='16_DB-SGX_Loading'!N19 -> 43.6 | R57: ='16_DB-SGX_Loading'!O19 -> 1018.751 | S57: ='16_DB-SGX_Loading'!P19 -> 0.145 | T57: =C57/P57 -> 2.0083878 | U57: =C57/Q57 -> 5.1458028 | V57: =C57/R57 -> 0.22022751 | W57: =C57/S57 -> 1547.2897 | X57: NR7
B58: Total: | D58: =SUM(D45:D57) -> 8.1 | E58: =SUM(E45:E57) -> 6.8936169 | F58: =AVERAGE(H45:H57)/AVERAGE(I45:I57) -> 0.38782687 | G58: average D/L | S58: total | T58: =SUM(T45:T48)+SUM(T68:T70) -> 5.83476 | U58: =SUM(U45:U48)+SUM(U68:U70) -> 26.626236 | V58: =SUM(V45:V48)+SUM(V68:V70) -> 4.3930502 | W58: =SUM(W45:W48)+SUM(W68:W70) -> 13.951539
B59: Average: | D59: =AVERAGE(D45:D57) -> 0.62307692 | E59: =AVERAGE(E45:E57) -> 0.53027823 | F59: =E59*(1+(1-E70)*F58) -> 0.70097283 | G59: Re-levered beta of small cap components average D/L | S59: average | T59: =T58/11 -> 0.53043273 | U59: =U58/11 -> 2.4205669 | V59: =V58/11 -> 0.3993682 | W59: =W58/11 -> 1.2683218
A60: 3 | B60: Premium for small company size: | E60: =E59 * D28 -> 2.4657938 | H60: Formula: | I60: [Average unlevered beta X Premium for equity investment] | S60: median | T60: =MEDIAN(T45:T48) -> 0.82843624 | U60: =MEDIAN(U45:U48) -> 6.3015072 | V60: =MEDIAN(V45:V48) -> 0.93625099 | W60: =MEDIAN(W45:W48) -> 3.0756035
B61: *Where T is the corporate tax rate of 17%
C62: Total I+S Cap | D62: =D58+D23 -> 11.77 | E62: =E58+E23 -> 9.5625417 | F62: =(AVERAGE(H13:H21)+AVERAGE(H45:H57))/(AVERAGE(I13:I21)+AVERAGE(I45:I57)) -> 0.75683008
D63: =AVERAGE(D45:D57)+AVERAGE(D13:D21) -> 1.0308547 | E63: =AVERAGE(E45:E57)+AVERAGE(E13:E21) -> 0.82682542 | F63: =E63*(1+(1-E70)*F62) -> 1.3462115 | G63: Industry premium = (1.346 X 4.65)-4.65 | J63: =(E67*D28)-D28 -> 1.6098834
A65: C | B65: Re-Levered Beta for subject company:
B66: where:
B67: βL=βU×(1+(1−T)*D/E) | E67: =E69*(1+(1-E70)*F62) -> 1.3462115
B68: βL\beta_L = Levered beta (re-levered beta) | H68: Ind +Small Cap (TD) | J68: =SUM(H13:H21)+SUM(H45:H57) -> 45824.277
B69: βU\beta_U = Unlevered beta (from peer analysis -Industry) | E69: =E63 -> 0.82682542 | H69: Ind +Small Cap (TL) | J69: =SUM(I13:I21)+SUM(I45:I57) -> 60728.094
B70: TT = Corporate tax rate (e.g., 0.17 for Singapore) | E70: ='01_Inputs'!E13 -> 0.17 | H70: Ind+Small Cap (TD/TL) | J70: =J68/J69 -> 0.75458118
H71: Ind +Small Average UB | J71: =(AVERAGE(E13:E21)+AVERAGE(E45:E57)) -> 0.82682542
H72: ERP | J72: =D28 -> 4.65
B73: Assumption: | D73: 46022 | H73: Relevered Beta | J73: =J71*(1+(1-E70)*J70) -> 1.3446681
A74: a | B74: Malaysia Corp Tax rate (T) = | D74: 0.24
A75: b | B75: Malaysia 1 MYR/S$ = | D75: 0.32
A76: c | B76: Singapore Corp Tax rate (T) | D76: 0.17

Sheet 03i_Beta_Calculation
A1: 1 | B1: Calculations of Industry Risk in a Buildup Model
A3: a | B3: Mid and Large Cap Stock
B4: Data/Information from SGX or Yahoo Finance website
C5: Total Mkt Cap $ million | D5: LB | E5: UB = LB / (1+ (1-T)* (D/E)) | F5: D %age of debts [Total Debt / (Total Equity + Total Debt)] | G5: E %age of equity [Total Equity / (Total Equity + Total Debt)] | H5: Total debt | I5: Total Equity | J5: Total Equity + Total Debts | K5: P/E ratio | L5: Dividend yield | M5: Sh price on 3 Apr 2026 | N5: Sh price on 31 Dec 2025 | O5: Percentage +ve drop/-ve increase | P5: Gross Revenue ($million) | Q5: EBITDA | R5: Total Assets | S5: Free Cash Flow (FCF) | T5: Price/Gross Revenue | U5: Price/EBITDA | V5: Price/Total Assests | W5: Price/FCF | X5: Stk code | Y5: Currency
A6: 1 | B6: ='16_DB-SGX_Loading'!B10 -> COSCO SHP SG | C6: ='16_DB-SGX_Loading'!C10 -> 510.548 | D6: ='16_DB-SGX_Loading'!D10 -> 0.71 | E6: =D6/(1+(1-0.17)*(F6/G6)) -> 0.64578105 | F6: =H6/J6% -> 10.699284 | G6: =I6/J6% -> 89.300716 | H6: ='16_DB-SGX_Loading'!E10 -> 93.583 | I6: ='16_DB-SGX_Loading'!F10 -> 781.083 | J6: =H6+I6 -> 874.666 | K6: ='16_DB-SGX_Loading'!H10 -> 0 | L6: ='16_DB-SGX_Loading'!I10 -> 0.78 | M6: ='16_DB-SGX_Loading'!J10 -> 0.114 | N6: ='16_DB-SGX_Loading'!K10 -> 0.121 | O6: =(M6-N6)/N6*100 -> -5.785124 | P6: ='16_DB-SGX_Loading'!M10 -> 193.999 | Q6: ='16_DB-SGX_Loading'!N10 -> 61.285 | R6: ='16_DB-SGX_Loading'!O10 -> 980.308 | S6: ='16_DB-SGX_Loading'!P10 -> 33.245 | T6: =C6/P6 -> 2.6317043 | U6: =C6/Q6 -> 8.3307171 | V6: =C6/R6 -> 0.52080367 | W6: =C6/S6 -> 15.357136 | X6: ='16_DB-SGX_Loading'!W10 -> F83
A7: 2 | B7: ='16_DB-SGX_Loading'!B11 -> SATS | C7: ='16_DB-SGX_Loading'!C11 -> 5321 | D7: ='16_DB-SGX_Loading'!D11 -> 0.52 | E7: =D7/(1+(1-0.17)*(F7/G7)) -> 0.33495355 | F7: =H7/J7% -> 39.961838 | G7: =I7/J7% -> 60.038162 | H7: ='16_DB-SGX_Loading'!E11 -> 1843 | I7: ='16_DB-SGX_Loading'!F11 -> 2768.9 | J7: =H7+I7 -> 4611.9 | K7: ='16_DB-SGX_Loading'!H11 -> 19.89 | L7: ='16_DB-SGX_Loading'!I11 -> 1.54 | M7: ='16_DB-SGX_Loading'!J11 -> 3.58 | N7: ='16_DB-SGX_Loading'!K11 -> 3.81 | O7: =(M7-N7)/N7*100 -> -6.0367454 | P7: ='16_DB-SGX_Loading'!M11 -> 5821 | Q7: ='16_DB-SGX_Loading'!N11 -> 1166 | R7: ='16_DB-SGX_Loading'!O11 -> 8882 | S7: ='16_DB-SGX_Loading'!P11 -> 669.4 | T7: =C7/P7 -> 0.91410411 | U7: =C7/Q7 -> 4.5634648 | V7: =C7/R7 -> 0.59907678 | W7: =C7/S7 -> 7.9489095 | X7: ='16_DB-SGX_Loading'!W11 -> S58
A8: 3 | B8: ='16_DB-SGX_Loading'!B12 -> SIA | C8: ='16_DB-SGX_Loading'!C12 -> 20973 | D8: ='16_DB-SGX_Loading'!D12 -> 0.5 | E8: =D8/(1+(1-0.17)*(F8/G8)) -> 0.29993801 | F8: =H8/J8% -> 44.556191 | G8: =I8/J8% -> 55.443809 | H8: ='16_DB-SGX_Loading'!E12 -> 12914.3 | I8: ='16_DB-SGX_Loading'!F12 -> 16070 | J8: =H8+I8 -> 28984.3 | K8: ='16_DB-SGX_Loading'!H12 -> 17.5 | L8: ='16_DB-SGX_Loading'!I12 -> 5.26 | M8: ='16_DB-SGX_Loading'!J12 -> 6.65 | N8: ='16_DB-SGX_Loading'!K12 -> 6.4 | O8: =(M8-N8)/N8*100 -> 3.90625 | P8: ='16_DB-SGX_Loading'!M12 -> 19539.8 | Q8: ='16_DB-SGX_Loading'!N12 -> 5711.9 | R8: ='16_DB-SGX_Loading'!O12 -> 43086.8 | S8: ='16_DB-SGX_Loading'!P12 -> 2834 | T8: =C8/P8 -> 1.0733477 | U8: =C8/Q8 -> 3.671808 | V8: =C8/R8 -> 0.48676161 | W8: =C8/S8 -> 7.400494 | X8: ='16_DB-SGX_Loading'!W12 -> C6L
A9: 4 | B9: ='16_DB-SGX_Loading'!B13 -> SIA Engineering | C9: ='16_DB-SGX_Loading'!C13 -> 3651 | D9: ='16_DB-SGX_Loading'!D13 -> 0.32 | E9: =D9/(1+(1-0.17)*(F9/G9)) -> 0.30751392 | F9: =H9/J9% -> 4.6638129 | G9: =I9/J9% -> 95.336187 | H9: ='16_DB-SGX_Loading'!E13 -> 85.199 | I9: ='16_DB-SGX_Loading'!F13 -> 1741.611 | J9: =H9+I9 -> 1826.81 | K9: ='16_DB-SGX_Loading'!H13 -> 23.29 | L9: ='16_DB-SGX_Loading'!I13 -> 2.91 | M9: ='16_DB-SGX_Loading'!J13 -> 3.26 | N9: ='16_DB-SGX_Loading'!K13 -> 3.6 | O9: =(M9-N9)/N9*100 -> -9.4444444 | P9: ='16_DB-SGX_Loading'!M13 -> 1245 | Q9: ='16_DB-SGX_Loading'!N13 -> 214.881 | R9: ='16_DB-SGX_Loading'!O13 -> 2141.393 | S9: ='16_DB-SGX_Loading'!P13 -> 102.603 | T9: =C9/P9 -> 2.9325301 | U9: =C9/Q9 -> 16.9908 | V9: =C9/R9 -> 1.7049649 | W9: =C9/S9 -> 35.583755 | X9: ='16_DB-SGX_Loading'!W13 -> S59
A10: 5 | B10: ='16_DB-SGX_Loading'!B14 -> SingPost | C10: ='16_DB-SGX_Loading'!C14 -> 776.687 | D10: ='16_DB-SGX_Loading'!D14 -> 0.21 | E10: =D10/(1+(1-0.17)*(F10/G10)) -> 0.17629808 | F10: =H10/J10% -> 18.720237 | G10: =I10/J10% -> 81.279763 | H10: ='16_DB-SGX_Loading'!E14 -> 370.232 | I10: ='16_DB-SGX_Loading'!F14 -> 1607.478 | J10: =H10+I10 -> 1977.71 | K10: ='16_DB-SGX_Loading'!H14 -> 3.14 | L10: ='16_DB-SGX_Loading'!I14 -> 1.22 | M10: ='16_DB-SGX_Loading'!J14 -> 0.345 | N10: ='16_DB-SGX_Loading'!K14 -> 0.405 | O10: =(M10-N10)/N10*100 -> -14.814815 | P10: ='16_DB-SGX_Loading'!M14 -> 813.704 | Q10: ='16_DB-SGX_Loading'!N14 -> 387.25 | R10: ='16_DB-SGX_Loading'!O14 -> 2390.424 | S10: ='16_DB-SGX_Loading'!P14 -> 26.671 | T10: =C10/P10 -> 0.95450803 | U10: =C10/Q10 -> 2.0056475 | V10: =C10/R10 -> 0.324916 | W10: =C10/S10 -> 29.12103 | X10: ='16_DB-SGX_Loading'!W14 -> S08
A11: 6 | B11: ='16_DB-SGX_Loading'!B15 -> Wing Tai | C11: ='16_DB-SGX_Loading'!C15 -> 1222 | D11: ='16_DB-SGX_Loading'!D15 -> 0.23 | E11: =D11/(1+(1-0.17)*(F11/G11)) -> 0.16972396 | F11: =H11/J11% -> 29.966174 | G11: =I11/J11% -> 70.033826 | H11: ='16_DB-SGX_Loading'!E15 -> 1242.121 | I11: ='16_DB-SGX_Loading'!F15 -> 2902.956 | J11: =H11+I11 -> 4145.077 | K11: ='16_DB-SGX_Loading'!H15 -> 0 | L11: ='16_DB-SGX_Loading'!I15 -> 1.88 | M11: ='16_DB-SGX_Loading'!J15 -> 1.6 | N11: ='16_DB-SGX_Loading'!K15 -> 1.42 | O11: =(M11-N11)/N11*100 -> 12.676056 | P11: ='16_DB-SGX_Loading'!M15 -> 230.206 | Q11: ='16_DB-SGX_Loading'!N15 -> -4.157 | R11: ='16_DB-SGX_Loading'!O15 -> 4275.552 | S11: ='16_DB-SGX_Loading'!P15 -> -447.444 | T11: =C11/P11 -> 5.3082891 | U11: =C11/Q11 -> -293.96199 | V11: =C11/R11 -> 0.28581105 | W11: =C11/S11 -> -2.731068 | X11: ='16_DB-SGX_Loading'!W15 -> W05
A12: 7 | B12: ='16_DB-SGX_Loading'!B16 -> CapitaLandInvest | C12: ='16_DB-SGX_Loading'!C16 -> 13679 | D12: ='16_DB-SGX_Loading'!D16 -> 0.61 | E12: =D12/(1+(1-0.17)*(F12/G12)) -> 0.40149196 | F12: =H12/J12% -> 38.488129 | G12: =I12/J12% -> 61.511871 | H12: ='16_DB-SGX_Loading'!E16 -> 8462 | I12: ='16_DB-SGX_Loading'!F16 -> 13524 | J12: =H12+I12 -> 21986 | K12: ='16_DB-SGX_Loading'!H16 -> 91.33 | L12: ='16_DB-SGX_Loading'!I16 -> 4.38 | M12: ='16_DB-SGX_Loading'!J16 -> 2.74 | N12: ='16_DB-SGX_Loading'!K16 -> 2.71 | O12: =(M12-N12)/N12*100 -> 1.1070111 | P12: ='16_DB-SGX_Loading'!M16 -> 2133 | Q12: ='16_DB-SGX_Loading'!N16 -> 735 | R12: ='16_DB-SGX_Loading'!O16 -> 24211 | S12: ='16_DB-SGX_Loading'!P16 -> 479 | T12: =C12/P12 -> 6.4130333 | U12: =C12/Q12 -> 18.610884 | V12: =C12/R12 -> 0.56499112 | W12: =C12/S12 -> 28.557411 | X12: ='16_DB-SGX_Loading'!W16 -> 9CI
A13: 8 | B13: ='16_DB-SGX_Loading'!B17 -> ComfortDelGro | C13: ='16_DB-SGX_Loading'!C17 -> 3120 | D13: ='16_DB-SGX_Loading'!D17 -> 0.24 | E13: =D13/(1+(1-0.17)*(F13/G13)) -> 0.15923447 | F13: =H13/J13% -> 37.930532 | G13: =I13/J13% -> 62.069468 | H13: ='16_DB-SGX_Loading'!E17 -> 1821.5 | I13: ='16_DB-SGX_Loading'!F17 -> 2980.7 | J13: =H13+I13 -> 4802.2 | K13: ='16_DB-SGX_Loading'!H17 -> 13.09 | L13: ='16_DB-SGX_Loading'!I17 -> 5.9 | M13: ='16_DB-SGX_Loading'!J17 -> 1.44 | N13: ='16_DB-SGX_Loading'!K17 -> 1.48 | O13: =(M13-N13)/N13*100 -> -2.7027027 | P13: ='16_DB-SGX_Loading'!M17 -> 5058 | Q13: ='16_DB-SGX_Loading'!N17 -> 793.8 | R13: ='16_DB-SGX_Loading'!O17 -> 6138.9 | S13: ='16_DB-SGX_Loading'!P17 -> -136.5 | T13: =C13/P13 -> 0.6168446 | U13: =C13/Q13 -> 3.9304611 | V13: =C13/R13 -> 0.50823437 | W13: =C13/S13 -> -22.857143 | X13: ='16_DB-SGX_Loading'!W17 -> C52
A14: 9 | B14: ='16_DB-SGX_Loading'!B18 -> Frasers Property | C14: ='16_DB-SGX_Loading'!C18 -> 3808 | D14: ='16_DB-SGX_Loading'!D18 -> 0.33 | E14: =D14/(1+(1-0.17)*(F14/G14)) -> 0.17398972 | F14: =H14/J14% -> 51.930422 | G14: =I14/J14% -> 48.069578 | H14: ='16_DB-SGX_Loading'!E18 -> 18525.843 | I14: ='16_DB-SGX_Loading'!F18 -> 17148.512 | J14: =H14+I14 -> 35674.355 | K14: ='16_DB-SGX_Loading'!H18 -> 16.17 | L14: ='16_DB-SGX_Loading'!I18 -> 4.64 | M14: ='16_DB-SGX_Loading'!J18 -> 0.97 | N14: ='16_DB-SGX_Loading'!K18 -> 1.13 | O14: =(M14-N14)/N14*100 -> -14.159292 | P14: ='16_DB-SGX_Loading'!M18 -> 3403.519 | Q14: ='16_DB-SGX_Loading'!N18 -> 1322.534 | R14: ='16_DB-SGX_Loading'!O18 -> 39747.618 | S14: ='16_DB-SGX_Loading'!P18 -> 981.788 | T14: =C14/P14 -> 1.118842 | U14: =C14/Q14 -> 2.8793211 | V14: =C14/R14 -> 0.095804483 | W14: =C14/S14 -> 3.8786378 | X14: ='16_DB-SGX_Loading'!W18 -> TQ5
B16: Total: | D16: =SUM(D6:D14) -> 3.67 | E16: =SUM(E6:E14) -> 2.6689247 | F16: =AVERAGE(H6:H14)/AVERAGE(I6:I14) -> 0.76199236 | G16: Average D/Average L
B17: Average: | D17: =AVERAGE(D6:D14) -> 0.40777778 | E17: =AVERAGE(E6:E14) -> 0.29654719 | F17: =E17*(1+(1-D50)*F16) -> 0.48409955 | G17: rel-levered beta using the industry component stocks D/L
B18: *Where T is the corporate tax rate of 17%
A20: b | B20: Small and Micro Cap Stocks
B21: Data/Information from SGX or Yahoo Finance website
C22: Total Mkt Cap $ million | D22: LB | E22: UB = LB / (1+ (1-T)* (D/E)) | F22: D %age of debts [Total Debt / (Total Equity + Total Debt)] | G22: E %age of equity [Total Equity / (Total Equity + Total Debt)] | H22: Total debt | I22: Total Equity | J22: Total Equity + Total Debts | K22: P/E ratio | L22: Dividend yield | M22: Sh price on 3 Apr 2026 | N22: Sh price on 31 Dec 2025 | O22: Percentage +ve drop/-ve increase | P22: Gross Revenue ($million) | Q22: EBITDA | R22: Total Assets | S22: Free Cash Flow (FCF) | T22: Price/Gross Revenue | U22: Price/EBITDA | V22: Price/Total Assests | W22: Price/FCF | X22: Stk code | Y22: Currency
A23: 1 | B23: ='16_DB-SGX_Loading'!B22 -> Audience | C23: ='16_DB-SGX_Loading'!C22 -> 60.492 | D23: ='16_DB-SGX_Loading'!D22 -> 0.08 | E23: =D23/(1+(1-$C$55)*(F23/G23)) -> 0.079920179 | F23: =H23/J23% -> 0.12018715 | G23: =I23/J23% -> 99.879813 | H23: ='16_DB-SGX_Loading'!E22 -> 0.028 | I23: ='16_DB-SGX_Loading'!F22 -> 23.269 | J23: =H23+I23 -> 23.297 | K23: ='16_DB-SGX_Loading'!H22 -> 13 | L23: ='16_DB-SGX_Loading'!I22 -> 5.77 | M23: ='16_DB-SGX_Loading'!J22 -> 0.26 | N23: ='16_DB-SGX_Loading'!K22 -> 0.26 | O23: =(N23-M23)/N23*100 -> 0 | P23: ='16_DB-SGX_Loading'!M22 -> 15.956 | Q23: ='16_DB-SGX_Loading'!N22 -> 5.788 | R23: ='16_DB-SGX_Loading'!O22 -> 26.015 | S23: ='16_DB-SGX_Loading'!P22 -> 4.436 | T23: ='16_DB-SGX_Loading'!Q22 -> 3.7911757 | U23: ='16_DB-SGX_Loading'!R22 -> 10.451279 | V23: ='16_DB-SGX_Loading'!S22 -> 2.3252739 | W23: ='16_DB-SGX_Loading'!T22 -> 13.63661 | X23: 1AZ
A24: 2 | B24: ='16_DB-SGX_Loading'!B23 -> Dezign Format | C24: ='16_DB-SGX_Loading'!C23 -> 38 | D24: ='16_DB-SGX_Loading'!D23 -> 1 | E24: =D24/(1+(1-$C$55)*(F24/G24)) -> 0.84807461 | F24: =H24/J24% -> 17.751875 | G24: =I24/J24% -> 82.248125 | H24: ='16_DB-SGX_Loading'!E23 -> 2.391 | I24: ='16_DB-SGX_Loading'!F23 -> 11.078 | J24: =H24+I24 -> 13.469 | K24: ='16_DB-SGX_Loading'!H23 -> 19 | L24: ='16_DB-SGX_Loading'!I23 -> 0 | M24: ='16_DB-SGX_Loading'!J23 -> 0.19 | N24: ='16_DB-SGX_Loading'!K23 -> 0.23 | O24: =(N24-M24)/N24*100 -> 17.391304 | P24: ='16_DB-SGX_Loading'!M23 -> 33.104 | Q24: ='16_DB-SGX_Loading'!N23 -> 3.03 | R24: ='16_DB-SGX_Loading'!O23 -> 24.951 | S24: ='16_DB-SGX_Loading'!P23 -> -6.511 | T24: ='16_DB-SGX_Loading'!Q23 -> 1.1478975 | U24: ='16_DB-SGX_Loading'!R23 -> 12.541254 | V24: ='16_DB-SGX_Loading'!S23 -> 1.5229851 | W24: ='16_DB-SGX_Loading'!T23 -> -5.8362771 | X24: UZF
A25: 3 | B25: ='16_DB-SGX_Loading'!B24 -> GKE | C25: ='16_DB-SGX_Loading'!C24 -> 64.395 | D25: ='16_DB-SGX_Loading'!D24 -> 0.28 | E25: =D25/(1+(1-$C$55)*(F25/G25)) -> 0.1943974 | F25: =H25/J25% -> 34.663595 | G25: =I25/J25% -> 65.336405 | H25: ='16_DB-SGX_Loading'!E24 -> 53.123 | I25: ='16_DB-SGX_Loading'!F24 -> 100.13 | J25: =H25+I25 -> 153.253 | K25: ='16_DB-SGX_Loading'!H24 -> 7.5 | L25: ='16_DB-SGX_Loading'!I24 -> 5.33 | M25: ='16_DB-SGX_Loading'!J24 -> 0.075 | N25: ='16_DB-SGX_Loading'!K24 -> 0.095 | O25: =(N25-M25)/N25*100 -> 21.052632 | P25: ='16_DB-SGX_Loading'!M24 -> 126.519 | Q25: ='16_DB-SGX_Loading'!N24 -> 29.927 | R25: ='16_DB-SGX_Loading'!O24 -> 184.24 | S25: ='16_DB-SGX_Loading'!P24 -> 14.761 | T25: ='16_DB-SGX_Loading'!Q24 -> 0.50897494 | U25: ='16_DB-SGX_Loading'!R24 -> 2.1517359 | V25: ='16_DB-SGX_Loading'!S24 -> 0.34951693 | W25: ='16_DB-SGX_Loading'!T24 -> 4.3625093 | X25: 595 | Y25: JPY
A26: 4 | B26: ='16_DB-SGX_Loading'!B25 -> Hiap Tong | C26: ='16_DB-SGX_Loading'!C25 -> 35.545 | D26: ='16_DB-SGX_Loading'!D25 -> -0.04 | E26: =D26/(1+(1-$C$55)*(F26/G26)) -> -0.027828632 | F26: =H26/J26% -> 34.509974 | G26: =I26/J26% -> 65.490026 | H26: ='16_DB-SGX_Loading'!E25 -> 52.646 | I26: ='16_DB-SGX_Loading'!F25 -> 99.907 | J26: =H26+I26 -> 152.553 | K26: ='16_DB-SGX_Loading'!H25 -> 11.2 | L26: ='16_DB-SGX_Loading'!I25 -> 0.89 | M26: ='16_DB-SGX_Loading'!J25 -> 0.112 | N26: ='16_DB-SGX_Loading'!K25 -> 0.096 | O26: =(N26-M26)/N26*100 -> -16.666667 | P26: ='16_DB-SGX_Loading'!M25 -> 91.916 | Q26: ='16_DB-SGX_Loading'!N25 -> 23.985 | R26: ='16_DB-SGX_Loading'!O25 -> 182.026 | S26: ='16_DB-SGX_Loading'!P25 -> 19.872 | T26: ='16_DB-SGX_Loading'!Q25 -> 0.38671178 | U26: ='16_DB-SGX_Loading'!R25 -> 1.4819679 | V26: ='16_DB-SGX_Loading'!S25 -> 0.1952743 | W26: ='16_DB-SGX_Loading'!T25 -> 1.7886977 | X26: 5PO
A27: 5 | B27: ='16_DB-SGX_Loading'!B26 -> LS 2 Holdings | C27: ='16_DB-SGX_Loading'!C26 -> 14.8 | D27: ='16_DB-SGX_Loading'!D26 -> 4.11 | E27: =D27/(1+(1-$C$55)*(F27/G27)) -> 3.7729933 | F27: =H27/J27% -> 9.7159543 | G27: =I27/J27% -> 90.284046 | H27: ='16_DB-SGX_Loading'!E26 -> 2.562 | I27: ='16_DB-SGX_Loading'!F26 -> 23.807 | J27: =H27+I27 -> 26.369 | K27: ='16_DB-SGX_Loading'!H26 -> 4 | L27: ='16_DB-SGX_Loading'!I26 -> 0 | M27: ='16_DB-SGX_Loading'!J26 -> 0.08 | N27: ='16_DB-SGX_Loading'!K26 -> 0.074 | O27: =(N27-M27)/N27*100 -> -8.1081081 | P27: ='16_DB-SGX_Loading'!M26 -> 71.805 | Q27: ='16_DB-SGX_Loading'!N26 -> 7.614 | R27: ='16_DB-SGX_Loading'!O26 -> 37.841 | S27: ='16_DB-SGX_Loading'!P26 -> 6.154 | T27: ='16_DB-SGX_Loading'!Q26 -> 0.20611378 | U27: ='16_DB-SGX_Loading'!R26 -> 1.9437878 | V27: ='16_DB-SGX_Loading'!S26 -> 0.39111017 | W27: ='16_DB-SGX_Loading'!T26 -> 2.4049399 | X27: ENV
A28: 6 | B28: ='16_DB-SGX_Loading'!B27 -> VCPlus | C28: ='16_DB-SGX_Loading'!C27 -> 17.012 | D28: ='16_DB-SGX_Loading'!D27 -> 0.69 | E28: =D28/(1+(1-$C$55)*(F28/G28)) -> 0.56308174 | F28: =H28/J28% -> 21.356784 | G28: =I28/J28% -> 78.643216 | H28: ='16_DB-SGX_Loading'!E27 -> 0.17 | I28: ='16_DB-SGX_Loading'!F27 -> 0.626 | J28: =H28+I28 -> 0.796 | K28: ='16_DB-SGX_Loading'!H27 -> 0 | L28: ='16_DB-SGX_Loading'!I27 -> 0 | M28: ='16_DB-SGX_Loading'!J27 -> 0.003 | N28: ='16_DB-SGX_Loading'!K27 -> 0.003 | O28: =(N28-M28)/N28*100 -> 0 | P28: ='16_DB-SGX_Loading'!M27 -> 0.191 | Q28: ='16_DB-SGX_Loading'!N27 -> -2.281 | R28: ='16_DB-SGX_Loading'!O27 -> 1.471 | S28: ='16_DB-SGX_Loading'!P27 -> -1.388 | T28: ='16_DB-SGX_Loading'!Q27 -> 89.068063 | U28: ='16_DB-SGX_Loading'!R27 -> -7.4581324 | V28: ='16_DB-SGX_Loading'!S27 -> 11.564922 | W28: ='16_DB-SGX_Loading'!T27 -> -12.256484 | X28: 43E
A29: 7 | B29: ='16_DB-SGX_Loading'!B28 -> ZICO Hldgs | C29: ='16_DB-SGX_Loading'!C28 -> 19.707 | D29: ='16_DB-SGX_Loading'!D28 -> 0.18 | E29: =D29/(1+(1-$C$55)*(F29/G29)) -> 0.142867 | F29: =H29/J29% -> 23.847139 | G29: =I29/J29% -> 76.152861 | H29: ='16_DB-SGX_Loading'!E28 -> 8.936 | I29: ='16_DB-SGX_Loading'!F28 -> 28.536 | J29: =H29+I29 -> 37.472 | K29: ='16_DB-SGX_Loading'!H28 -> 0 | L29: ='16_DB-SGX_Loading'!I28 -> 0 | M29: ='16_DB-SGX_Loading'!J28 -> 0.048 | N29: ='16_DB-SGX_Loading'!K28 -> 0.055 | O29: =(M29-N29)/N29*100 -> -12.727273 | P29: ='16_DB-SGX_Loading'!M28 -> 14.312 | Q29: ='16_DB-SGX_Loading'!N28 -> 3.549 | R29: ='16_DB-SGX_Loading'!O28 -> 42.196 | S29: ='16_DB-SGX_Loading'!P28 -> -0.504 | T29: ='16_DB-SGX_Loading'!Q28 -> 1.3769564 | U29: ='16_DB-SGX_Loading'!R28 -> 5.5528318 | V29: ='16_DB-SGX_Loading'!S28 -> 0.46703479 | W29: ='16_DB-SGX_Loading'!T28 -> -39.10119 | X29: 40W
A30: 8 | B30: ='16_DB-SGX_Loading'!B29 -> UnUsUaL | C30: ='16_DB-SGX_Loading'!C29 -> 25.553 | D30: ='16_DB-SGX_Loading'!D29 -> -0.38 | E30: =D30/(1+(1-$C$55)*(F30/G30)) -> -0.36048031 | F30: =H30/J30% -> 6.124434 | G30: =I30/J30% -> 93.875566 | H30: ='16_DB-SGX_Loading'!E29 -> 1.826 | I30: ='16_DB-SGX_Loading'!F29 -> 27.989 | J30: =H30+I30 -> 29.815 | K30: ='16_DB-SGX_Loading'!H29 -> 0 | L30: ='16_DB-SGX_Loading'!I29 -> 0 | M30: ='16_DB-SGX_Loading'!J29 -> 0.025 | N30: ='16_DB-SGX_Loading'!K29 -> 0.036 | O30: =(M30-N30)/N30*100 -> -30.555556 | P30: ='16_DB-SGX_Loading'!M29 -> 53.219 | Q30: ='16_DB-SGX_Loading'!N29 -> -18.575 | R30: ='16_DB-SGX_Loading'!O29 -> 37.47 | S30: ='16_DB-SGX_Loading'!P29 -> 4.373 | T30: ='16_DB-SGX_Loading'!Q29 -> 0.48014807 | U30: ='16_DB-SGX_Loading'!R29 -> -1.3756662 | V30: ='16_DB-SGX_Loading'!S29 -> 0.6819589 | W30: ='16_DB-SGX_Loading'!T29 -> 5.843357 | X30: 1D1
A31: 9 | B31: ='16_DB-SGX_Loading'!B30 -> Abundante | C31: ='16_DB-SGX_Loading'!C30 -> 15.26 | D31: ='16_DB-SGX_Loading'!D30 -> 0.3 | E31: =D31/(1+(1-$C$55)*(F31/G31)) -> 0.29999866 | F31: =H31/J31% -> 0.00053647781 | G31: =I31/J31% -> 99.999464 | H31: 0.0001 | I31: ='16_DB-SGX_Loading'!F30 -> 18.64 | J31: =H31+I31 -> 18.6401 | K31: ='16_DB-SGX_Loading'!H30 -> 0 | L31: ='16_DB-SGX_Loading'!I30 -> 0 | M31: ='16_DB-SGX_Loading'!J30 -> 0.15 | N31: ='16_DB-SGX_Loading'!K30 -> 0.16 | O31: =(M31-N31)/N31*100 -> -6.25 | P31: ='16_DB-SGX_Loading'!M30 -> 7.326 | Q31: ='16_DB-SGX_Loading'!N30 -> 0.781 | R31: ='16_DB-SGX_Loading'!O30 -> 19.592 | S31: ='16_DB-SGX_Loading'!P30 -> 0.2511 | T31: ='16_DB-SGX_Loading'!Q30 -> 2.0829921 | U31: ='16_DB-SGX_Loading'!R30 -> 19.539052 | V31: ='16_DB-SGX_Loading'!S30 -> 0.77888934 | W31: ='16_DB-SGX_Loading'!T30 -> 60.772601 | X31: 570
A32: 10 | B32: ='16_DB-SGX_Loading'!B32 -> Chasen | C32: ='16_DB-SGX_Loading'!C32 -> 29.45 | D32: ='16_DB-SGX_Loading'!D32 -> 0.28 | E32: =D32/(1+(1-$C$55)*(F32/G32)) -> 0.13883524 | F32: =H32/J32% -> 55.056886 | G32: =I32/J32% -> 44.943114 | H32: ='16_DB-SGX_Loading'!E32 -> 100.704 | I32: ='16_DB-SGX_Loading'!F32 -> 82.205 | J32: =H32+I32 -> 182.909 | K32: ='16_DB-SGX_Loading'!H32 -> 0 | L32: ='16_DB-SGX_Loading'!I32 -> 0 | M32: ='16_DB-SGX_Loading'!J32 -> 0.077 | N32: ='16_DB-SGX_Loading'!K32 -> 0.087 | O32: =(M32-N32)/N32*100 -> -11.494253 | P32: ='16_DB-SGX_Loading'!M32 -> 116.322 | Q32: ='16_DB-SGX_Loading'!N32 -> 5.151 | R32: ='16_DB-SGX_Loading'!O32 -> 205.471 | S32: ='16_DB-SGX_Loading'!P32 -> -53.247 | T32: ='16_DB-SGX_Loading'!Q32 -> 0.25317653 | U32: ='16_DB-SGX_Loading'!R32 -> 5.7173364 | V32: ='16_DB-SGX_Loading'!S32 -> 0.14332923 | W32: ='16_DB-SGX_Loading'!T32 -> -0.5530828 | X32: 5NV
A33: 11 | B33: ='16_DB-SGX_Loading'!B33 -> Eneco Energy | C33: ='16_DB-SGX_Loading'!C33 -> 34.208 | D33: ='16_DB-SGX_Loading'!D33 -> 0.66 | E33: =D33/(1+(1-$C$55)*(F33/G33)) -> 0.48144479 | F33: =H33/J33% -> 30.883656 | G33: =I33/J33% -> 69.116344 | H33: ='16_DB-SGX_Loading'!E33 -> 9.758 | I33: ='16_DB-SGX_Loading'!F33 -> 21.838 | J33: =H33+I33 -> 31.596 | K33: ='16_DB-SGX_Loading'!H33 -> 0 | L33: ='16_DB-SGX_Loading'!I33 -> 0 | M33: ='16_DB-SGX_Loading'!J33 -> 0.009 | N33: ='16_DB-SGX_Loading'!K33 -> 0.01 | O33: =(M33-N33)/N33*100 -> -10 | P33: ='16_DB-SGX_Loading'!M33 -> 31.302 | Q33: ='16_DB-SGX_Loading'!N33 -> 6.523 | R33: ='16_DB-SGX_Loading'!O33 -> 37.445 | S33: ='16_DB-SGX_Loading'!P33 -> 3.373 | T33: ='16_DB-SGX_Loading'!Q33 -> 1.0928375 | U33: ='16_DB-SGX_Loading'!R33 -> 5.2442128 | V33: ='16_DB-SGX_Loading'!S33 -> 0.91355321 | W33: ='16_DB-SGX_Loading'!T33 -> 10.141714 | X33: R14
A34: 12 | B34: ='16_DB-SGX_Loading'!B34 -> KingsmenCreative | C34: ='16_DB-SGX_Loading'!C34 -> 120.159 | D34: ='16_DB-SGX_Loading'!D34 -> 0.22 | E34: =D34/(1+(1-$C$55)*(F34/G34)) -> 0.19939953 | F34: =H34/J34% -> 11.069445 | G34: =I34/J34% -> 88.930555 | H34: ='16_DB-SGX_Loading'!E34 -> 15.468 | I34: ='16_DB-SGX_Loading'!F34 -> 124.268 | J34: =H34+I34 -> 139.736 | K34: ='16_DB-SGX_Loading'!H34 -> 8.5 | L34: ='16_DB-SGX_Loading'!I34 -> 5.04 | M34: ='16_DB-SGX_Loading'!J34 -> 0.595 | N34: ='16_DB-SGX_Loading'!K34 -> 0.5 | O34: =(M34-N34)/N34*100 -> 19 | P34: ='16_DB-SGX_Loading'!M34 -> 372.544 | Q34: ='16_DB-SGX_Loading'!N34 -> 23.413 | R34: ='16_DB-SGX_Loading'!O34 -> 284.754 | S34: ='16_DB-SGX_Loading'!P34 -> 27.541 | T34: ='16_DB-SGX_Loading'!Q34 -> 0.3225364 | U34: ='16_DB-SGX_Loading'!R34 -> 5.1321488 | V34: ='16_DB-SGX_Loading'!S34 -> 0.42197476 | W34: ='16_DB-SGX_Loading'!T34 -> 4.3629135 | X34: 5MZ
A35: 13 | B35: ='16_DB-SGX_Loading'!B19 -> Raffles Edu | C35: ='16_DB-SGX_Loading'!C19 -> 224.357 | D35: ='16_DB-SGX_Loading'!D19 -> 0.72 | E35: =D35/(1+(1-0.17)*(F35/G35)) -> 0.56091346 | F35: =H35/J35% -> 25.468324 | G35: =I35/J35% -> 74.531676 | H35: ='16_DB-SGX_Loading'!E19 -> 218.887 | I35: ='16_DB-SGX_Loading'!F19 -> 640.561 | J35: =H35+I35 -> 859.448 | K35: ='16_DB-SGX_Loading'!H19 -> 0 | L35: ='16_DB-SGX_Loading'!I19 -> 0 | M35: ='16_DB-SGX_Loading'!J19 -> 0.126 | N35: ='16_DB-SGX_Loading'!K19 -> 0.139 | O35: =(M35-N35)/N35*100 -> -9.352518 | P35: ='16_DB-SGX_Loading'!M19 -> 111.71 | Q35: ='16_DB-SGX_Loading'!N19 -> 43.6 | R35: ='16_DB-SGX_Loading'!O19 -> 1018.751 | S35: ='16_DB-SGX_Loading'!P19 -> 0.145 | T35: =C35/P35 -> 2.0083878 | U35: =C35/Q35 -> 5.1458028 | V35: =C35/R35 -> 0.22022751 | W35: =C35/S35 -> 1547.2897 | X35: NR7
B37: Total: | D37: =SUM(D23:D35) -> 8.1 | E37: =SUM(E23:E35) -> 6.8936169 | F37: =AVERAGE(H23:H35)/AVERAGE(I23:I35) -> 0.38782687 | G37: average D/L | S37: total | T37: =SUM(T23:T26)+SUM(T48:T50) -> 5.83476 | U37: =SUM(U23:U26)+SUM(U48:U50) -> 26.626236 | V37: =SUM(V23:V26)+SUM(V48:V50) -> 4.3930502 | W37: =SUM(W23:W26)+SUM(W48:W50) -> 13.951539
B38: Average: | D38: =AVERAGE(D23:D35) -> 0.62307692 | E38: =AVERAGE(E23:E35) -> 0.53027823 | F38: =E38*(1+(1-D50)*F37) -> 0.70097283 | G38: Re-levered beta of small cap components average D/L | S38: average | T38: =T37/11 -> 0.53043273 | U38: =U37/11 -> 2.4205669 | V38: =V37/11 -> 0.3993682 | W38: =W37/11 -> 1.2683218
B39: *Where T is the corporate tax rate of 17% | S39: median | T39: =MEDIAN(T23:T26) -> 0.82843624 | U39: =MEDIAN(U23:U26) -> 6.3015072 | V39: =MEDIAN(V23:V26) -> 0.93625099 | W39: =MEDIAN(W23:W26) -> 3.0756035
B41: Total Industry + Small Cap | D41: =D37+D16 -> 11.77 | E41: =E37+E16 -> 9.5625417 | F41: =(AVERAGE(H6:H14)+AVERAGE(H23:H35))/(AVERAGE(I6:I14)+AVERAGE(I23:I35)) -> 0.75683008 | G41: Total average D/L
D42: =AVERAGE(D23:D35)+AVERAGE(D6:D14) -> 1.0308547 | E42: =AVERAGE(E23:E35)+AVERAGE(E6:E14) -> 0.82682542 | F42: =E42*(1+(1-D50)*F41) -> 1.3462115 | G42: Total re-levered beta
A43: c | B43: Industry premium = (1.346 X 4.65)-4.65 | C43: =(D47*C56)-C56 -> 1.6098834
A45: d | B45: Re-Levered Beta for subject company:
B46: where:
B47: βL=βU×(1+(1−T)*D/E) | D47: =D49*(1+(1-D50)*F41) -> 1.3462115
B48: βL\beta_L = Levered beta (re-levered beta)
B49: βU\beta_U = Unlevered beta (from peer analysis -Industry) | D49: =E42 -> 0.82682542
B50: TT = Corporate tax rate (e.g., 0.17 for Singapore) | D50: ='01_Inputs'!E13 -> 0.17
B52: Assumption:
A53: a | B53: Malaysia Corp Tax rate (T) = | C53: 0.24 | E53: Ind +Small Cap (TD) | G53: =SUM(H6:H14)+SUM(H23:H35) -> 45824.277
A54: b | B54: Malaysia 1 MYR/S$ = | C54: 0.32 | E54: Ind +Small Cap (TL) | G54: =SUM(I6:I14)+SUM(I23:I35) -> 60728.094
A55: c | B55: Singapore Corp Tax rate (T) | C55: 0.17 | E55: Ind+Small Cap (TD/TL) | G55: =G53/G54 -> 0.75458118
B56: ERP | C56: =' 04_CAPM'!D7 -> 4.65 | E56: Ind +Small Average UB | G56: =(AVERAGE(E6:E14)+AVERAGE(E23:E35)) -> 0.82682542
E57: ERP | G57: =C56 -> 4.65
E58: Relevered Beta | G58: =G56*(1+(1-D50)*G55) -> 1.3446681

Sheet 03b_Size Premium Method 15Y
A1: B. Portfolio (Decile) Returns
A2: Stocks | B2: 1 | C2: 2 | D2: 3 | E2: 4 | F2: 5 | G2: 6 | H2: 7 | I2: 8 | J2: 9 | K2: 10 | L2: 11 | M2: 12 | N2: 13
A3: Year | B3: =B51 -> Audience | C3: =B70 -> Dezign Format | D3: =B89 -> GKE | E3: =B108 -> Hiap Tong | F3: =B127 -> LS 2 Holdings | G3: =I51 -> VCPlus | H3: =I70 -> ZICO Hldgs | I3: =I89 -> UnUsUaL | J3: =I108 -> Abundante | K3: =I127 -> Chasen | L3: =P51 -> Eneco Energy | M3: =P70 -> KingsmenCreative | N3: =P89 -> Raffles Edu | O3: Portfolio Average
A4: 2010 | B4: =E53 -> #DIV/0! | C4: =E72 -> 0 | D4: =E91 -> 0 | E4: =E110 -> 0 | F4: =E129 -> #DIV/0! | G4: =L53 -> #DIV/0! | H4: =L72 -> 0 | I4: =L91 -> 0 | J4: =L110 -> 0.11764706 | K4: =L129 -> 0.15435095 | L4: =S53 -> -0.2531191 | M4: =S72 -> 0.052631579 | N4: =S91 -> -0.23751422 | O4: =AVERAGE(E4+H4+J4+K4+L4+M4+N4) -> -0.16600373
A5: 2011 | B5: =E54 -> #DIV/0! | C5: =E73 -> 0 | D5: =E92 -> 0 | E5: =E111 -> -0.54 | F5: =E130 -> #DIV/0! | G5: =L54 -> #DIV/0! | H5: =L73 -> 0 | I5: =L92 -> 0 | J5: =L111 -> -0.028571429 | K5: =L130 -> -0.39453188 | L5: =S54 -> 0.21415992 | M5: =S73 -> 0.079646018 | N5: =S92 -> -0.48189043 | O5: =AVERAGE(E5+H5+J5+K5+L5+M5+N5) -> -1.1511878
A6: 2012 | B6: =E55 -> #DIV/0! | C6: =E74 -> 0 | D6: =E93 -> 0 | E6: =E112 -> 1.2463768 | F6: =E131 -> #DIV/0! | G6: =L55 -> #DIV/0! | H6: =L74 -> 0 | I6: =L93 -> 0 | J6: =L112 -> -0.015873016 | K6: =L131 -> 0.12103364 | L6: =S55 -> 0.74064404 | M6: =S74 -> 0.42105263 | N6: =S93 -> -0.13180363 | O6: =AVERAGE(E6+H6+J6+K6+L6+M6+N6) -> 2.3814305
A7: 2013 | B7: =E56 -> #DIV/0! | C7: =E75 -> 0 | D7: =E94 -> -0.1778697 | E7: =E113 -> 0.02 | F7: =E132 -> #DIV/0! | G7: =L56 -> #DIV/0! | H7: =L75 -> 0 | I7: =L94 -> 0 | J7: =L113 -> 0.32758621 | K7: =L132 -> -0.27248885 | L7: =S56 -> -0.066666667 | M7: =S75 -> 0.24675325 | N7: =S94 -> -0.23601721 | O7: =AVERAGE(E7+H7+J7+K7+L7+M7+N7) -> 0.019166728
A8: 2014 | B8: =E57 -> #DIV/0! | C8: =E76 -> #DIV/0! | D8: =E95 -> 0.023285899 | E8: =E114 -> 0.061643836 | F8: =E133 -> #DIV/0! | G8: =L57 -> #DIV/0! | H8: =L76 -> 0.17073171 | I8: =L95 -> 0 | J8: =L114 -> 0.26388889 | K8: =L133 -> -0.15971464 | L8: =S57 -> -0.49107143 | M8: =S76 -> 0.086956522 | N8: =S95 -> 0.23627514 | O8: =AVERAGE(E8+H8+J8+K8+L8+M8+N8) -> 0.16871003
A9: 2015 | B9: =E58 -> #DIV/0! | C9: =E77 -> #DIV/0! | D9: =E96 -> -0.11183355 | E9: =E115 -> -0.47741935 | F9: =E134 -> #DIV/0! | G9: =L58 -> #DIV/0! | H9: =L77 -> -0.32291667 | I9: =L96 -> 0 | J9: =L115 -> 0.37647059 | K9: =L134 -> -0.7475539 | L9: =S58 -> -0.50877193 | M9: =S77 -> -0.29166667 | N9: =S96 -> -0.24258129 | O9: =AVERAGE(E9+H9+J9+K9+L9+M9+N9) -> -2.2144392
A10: 2016 | B10: =E59 -> #DIV/0! | C10: =E78 -> #DIV/0! | D10: =E97 -> 0.13161876 | E10: =E116 -> -0.037037037 | F10: =E135 -> #DIV/0! | G10: =L59 -> -0.16935484 | H10: =L78 -> -0.10769231 | I10: =L97 -> 0 | J10: =L116 -> 0.25688073 | K10: =L135 -> -0.075757576 | L10: =S59 -> 0.12857143 | M10: =S78 -> -0.023255814 | N10: =S97 -> -0.19594283 | O10: =AVERAGE(E10+H10+J10+K10+L10+M10+N10) -> -0.054233403
A11: 2017 | B11: =E60 -> #DIV/0! | C11: =E79 -> #DIV/0! | D11: =E98 -> 0.20523416 | E11: =E117 -> 0.53846154 | F11: =E136 -> #DIV/0! | G11: =L60 -> -0.5631068 | H11: =L79 -> -0.15517241 | I11: =L98 -> 0.53250253 | J11: =L117 -> -0.25384615 | K11: =L136 -> 1.6666667 | L11: =S60 -> -0.46202532 | M11: =S79 -> 0.040983607 | N11: =S98 -> 0.37327982 | O11: =AVERAGE(E11+H11+J11+K11+L11+M11+N11) -> 1.7483477
A12: 2018 | B12: =E61 -> #DIV/0! | C12: =E80 -> #DIV/0! | D12: =E99 -> -0.15240328 | E12: =E118 -> -0.4 | F12: =E137 -> #DIV/0! | G12: =L61 -> -0.44444444 | H12: =L80 -> -0.42857143 | I12: =L99 -> -0.34065934 | J12: =L118 -> -0.50537634 | K12: =L137 -> -0.063291139 | L12: =S61 -> 0.058823529 | M12: =S80 -> -0.15748031 | N12: =S99 -> -0.54488518 | O12: =AVERAGE(E12+H12+J12+K12+L12+M12+N12) -> -2.0407809
A13: 2019 | B13: =E62 -> #DIV/0! | C13: =E81 -> #DIV/0! | D13: =E100 -> 0.017118402 | E13: =E119 -> -0.048611111 | F13: =E138 -> #DIV/0! | G13: =L62 -> -0.64 | H13: =L81 -> 0.035714286 | I13: =L100 -> -0.25526667 | J13: =L119 -> -0.54347826 | K13: =L138 -> 0.028169014 | L13: =S62 -> -0.68888889 | M13: =S81 -> -0.21568627 | N13: =S100 -> -0.26605505 | O13: =AVERAGE(E13+H13+J13+K13+L13+M13+N13) -> -1.6988363
A14: 2020 | B14: =E63 -> #DIV/0! | C14: =E82 -> #DIV/0! | D14: =E101 -> 0.29377713 | E14: =E120 -> -0.10294118 | F14: =E139 -> #DIV/0! | G14: =L63 -> 0.11111111 | H14: =L82 -> -0.40689655 | I14: =L101 -> -0.17727273 | J14: =L120 -> -0.32380952 | K14: =L139 -> -0.1884058 | L14: =S63 -> -0.071428571 | M14: =S82 -> -0.33333333 | N14: =S101 -> 0.625 | O14: =AVERAGE(E14+H14+J14+K14+L14+M14+N14) -> -0.80181495
A15: 2021 | B15: =E64 -> -0.23333333 | C15: =E83 -> #DIV/0! | D15: =E102 -> -0.14908257 | E15: =E121 -> 0.06557377 | F15: =E140 -> #DIV/0! | G15: =L64 -> 0.4 | H15: =L83 -> -0.093023256 | I15: =L102 -> -0.30939227 | J15: =L121 -> 0.95774648 | K15: =L140 -> 0.25 | L15: =S64 -> 0 | M15: =S83 -> -0.06 | N15: =S102 -> -0.47692308 | O15: =AVERAGE(E15+H15+J15+K15+L15+M15+N15) -> 0.64337392
... A19: 2025 | B19: =E68 -> -0.11666667 | C19: =E87 -> -0.13207547 | D19: =E106 -> 0.41337386 | E19: =E125 -> 0.35294118 | F19: =E144 -> 0.10447761 | G19: =L68 -> 0.5 | H19: =L87 -> 0.35416667 | I19: =L106 -> -0.75423729 | J19: =L125 -> -0.27659574 | K19: =L144 -> 0.16901408 | L19: =S68 -> -0.090909091 | M19: =S87 -> 0.94444444 | N19: =S106 -> 3.2631579 | O19: =AVERAGE(E19+H19+J19+K19+L19+M19+N19) -> 4.7162194
K20: Average | O20: =AVERAGE(O4:O19) -> 0.11509779
G24: Note
A25: Portfolio (Yr 2025) | C25: Average Return | D25: CAPM Predicted Return | E25: Size Premium | G25: Our SGX small-cap portfolio produced a size premium of about 6.03% in 2025. This aligns with Duff & Phelps' published Decile 10 premium (4 - 6%), which are applied globally to microcap entities. For Singapore event management SMEs, we adopt a conservative premium within this range to reflect their scale disadvantage
A26: Small-Cap Decile | C26: =O20 -> 0.11509779 | D26: =(D33%+(D35*D34%)) -> 0.054795236 | E26: =C26-D26 -> 0.060302554
E27: =E26*100 -> 6.0302554
A28: 👉 Example:
A29: Average Return =AVERAGE(Portfolio_Returns)= 6.5%
A30: CAPM Predicted =Rf + Beta*ERP= 5.48%
A31: Size Premium =Average_Return - CAPM= 0.6%
A33: Rf | D33: =' 04_CAPM'!D4 -> 2.22
A34: ERP | D34: =' 04_CAPM'!D7 -> 4.65
A35: Re-levered Beta of Small Cap | D35: ='03_Beta_Calculation'!F59 -> 0.70097283
A36: Re-levered Beta of Industry | D36: ='03_Beta_Calculation'!F24 -> 0.48409955
A39: Company Type | D39: Likely Decile | G39: Typical Size Premium (2025)
A40: City Dev, UOL, Capitaland, Guccoland, SingaporeLand | D40: Decile 2-4 | G40: abt 0.8% - 1.5%
A42: Wing Tai, Ho Bee Land, Sing Hold | D42: Decile 5-7 | G42: abt 1.5% - 2.5%
A43: Oxley, Low Keng Huat, Niche Developers | D43: Decile 8-10 | G43: abt 2.5% - 4.0%
A50: A. Annual Returns calculations:
A51: 1.: | B51: ='03_Beta_Calculation'!B45 -> Audience | C51: 1AZ | H51: 6. Stock: | I51: ='03_Beta_Calculation'!B50 -> VCPlus | J51: 43E | O51: 11. Stock: | P51: ='03_Beta_Calculation'!B55 -> Eneco Energy | R51: R14
A52: Year | B52: Price (Start) | C52: Price (End) | D52: Dividend | E52: Annual Return Formula | H52: Year | I52: Price (Start) | J52: Price (End) | K52: Dividend | L52: Annual Return Formula | O52: Year | P52: Price (Start) | Q52: Price (End) | R52: Dividend | S52: Annual Return Formula
A53: 2010 | E53: =(C53-B53+D53)/B53 -> #DIV/0! | H53: 2010 | L53: =(J53-I53+K53)/I53 -> #DIV/0! | O53: 2010 | P53: 0.3812 | Q53: 0.2839 | R53: 0.000811 | S53: =(Q53-P53+R53)/P53 -> -0.2531191
A54: 2011 | E54: =(C54-B54+D54)/B54 -> #DIV/0! | H54: 2011 | L54: =(J54-I54+K54)/I54 -> #DIV/0! | O54: 2011 | P54: =Q53 -> 0.2839 | Q54: 0.3447 | S54: =(Q54-P54+R54)/P54 -> 0.21415992
A55: 2012 | E55: =(C55-B55+D55)/B55 -> #DIV/0! | H55: 2012 | L55: =(J55-I55+K55)/I55 -> #DIV/0! | O55: 2012 | P55: =Q54 -> 0.3447 | Q55: 0.6 | S55: =(Q55-P55+R55)/P55 -> 0.74064404
A56: 2013 | E56: =(C56-B56+D56)/B56 -> #DIV/0! | H56: 2013 | L56: =(J56-I56+K56)/I56 -> #DIV/0! | O56: 2013 | P56: =Q55 -> 0.6 | Q56: 0.56 | R56: 0 | S56: =(Q56-P56+R56)/P56 -> -0.066666667 | T56: Stk split 1:2
A57: 2014 | E57: =(C57-B57+D57)/B57 -> #DIV/0! | H57: 2014 | L57: =(J57-I57+K57)/I57 -> #DIV/0! | O57: 2014 | P57: =Q56 -> 0.56 | Q57: 0.285 | S57: =(Q57-P57+R57)/P57 -> -0.49107143
A58: 2015 | E58: =(C58-B58+D58)/B58 -> #DIV/0! | H58: 2015 | J58: 0.124 | L58: =(J58-I58+K58)/I58 -> #DIV/0! | O58: 2015 | P58: =Q57 -> 0.285 | Q58: 0.14 | S58: =(Q58-P58+R58)/P58 -> -0.50877193
A59: 2016 | E59: =(C59-B59+D59)/B59 -> #DIV/0! | H59: 2016 | I59: =J58 -> 0.124 | J59: 0.103 | K59: 0 | L59: =(J59-I59+K59)/I59 -> -0.16935484 | O59: 2016 | P59: =Q58 -> 0.14 | Q59: 0.158 | R59: 0 | S59: =(Q59-P59+R59)/P59 -> 0.12857143
A60: 2017 | E60: =(C60-B60+D60)/B60 -> #DIV/0! | H60: 2017 | I60: =J59 -> 0.103 | J60: 0.045 | K60: 0 | L60: =(J60-I60+K60)/I60 -> -0.5631068 | O60: 2017 | P60: =Q59 -> 0.158 | Q60: 0.085 | R60: 0 | S60: =(Q60-P60+R60)/P60 -> -0.46202532
A61: 2018 | E61: =(C61-B61+D61)/B61 -> #DIV/0! | H61: 2018 | I61: =J60 -> 0.045 | J61: 0.025 | K61: 0 | L61: =(J61-I61+K61)/I61 -> -0.44444444 | O61: 2018 | P61: =Q60 -> 0.085 | Q61: 0.09 | R61: 0 | S61: =(Q61-P61+R61)/P61 -> 0.058823529
A62: 2019 | E62: =(C62-B62+D62)/B62 -> #DIV/0! | H62: 2019 | I62: =J61 -> 0.025 | J62: 0.009 | K62: 0 | L62: =(J62-I62+K62)/I62 -> -0.64 | O62: 2019 | P62: =Q61 -> 0.09 | Q62: 0.028 | R62: 0 | S62: =(Q62-P62+R62)/P62 -> -0.68888889
A63: 2020 | E63: =(C63-B63+D63)/B63 -> #DIV/0! | H63: 2020 | I63: =J62 -> 0.009 | J63: 0.01 | K63: 0 | L63: =(J63-I63+K63)/I63 -> 0.11111111 | O63: 2020 | P63: =Q62 -> 0.028 | Q63: 0.026 | R63: 0 | S63: =(Q63-P63+R63)/P63 -> -0.071428571
A64: 2021 | B64: 0.225 | C64: 0.1725 | D64: 0 | E64: =(C64-B64+D64)/B64 -> -0.23333333 | H64: 2021 | I64: =J63 -> 0.01 | J64: 0.014 | K64: 0 | L64: =(J64-I64+K64)/I64 -> 0.4 | O64: 2021 | P64: =Q63 -> 0.026 | Q64: 0.026 | R64: 0 | S64: =(Q64-P64+R64)/P64 -> 0
A65: 2022 | B65: =C64 -> 0.1725 | C65: 0.2062 | D65: 0 | E65: =(C65-B65+D65)/B65 -> 0.19536232 | H65: 2022 | I65: =J64 -> 0.014 | J65: 0.008 | K65: 0 | L65: =(J65-I65+K65)/I65 -> -0.42857143 | O65: 2022 | P65: =Q64 -> 0.026 | Q65: 0.012 | R65: 0 | S65: =(Q65-P65+R65)/P65 -> -0.53846154
A66: 2023 | B66: =C65 -> 0.2062 | C66: 0.2475 | D66: 0.0135 | E66: =(C66-B66+D66)/B66 -> 0.2657614 | H66: 2023 | I66: =J65 -> 0.008 | J66: 0.003 | K66: 0 | L66: =(J66-I66+K66)/I66 -> -0.625 | O66: 2023 | P66: =Q65 -> 0.012 | Q66: 0.008 | R66: 0 | S66: =(Q66-P66+R66)/P66 -> -0.33333333
A67: 2024 | B67: =C66 -> 0.2475 | C67: 0.3 | D67: 0.01275 | E67: =(C67-B67+D67)/B67 -> 0.26363636 | H67: 2024 | I67: =J66 -> 0.003 | J67: 0.002 | K67: 0 | L67: =(J67-I67+K67)/I67 -> -0.33333333 | O67: 2024 | P67: =Q66 -> 0.008 | Q67: 0.011 | R67: 0 | S67: =(Q67-P67+R67)/P67 -> 0.375
A68: 2025 | B68: =C67 -> 0.3 | C68: 0.25 | D68: 0.015 | E68: =(C68-B68+D68)/B68 -> -0.11666667 | F68: 4:3 stock split | H68: 2025 | I68: =J67 -> 0.002 | J68: 0.003 | K68: 0 | L68: =(J68-I68+K68)/I68 -> 0.5 | O68: 2025 | P68: =Q67 -> 0.011 | Q68: 0.01 | R68: 0 | S68: =(Q68-P68+R68)/P68 -> -0.090909091
A70: 2. Stock: | B70: ='03_Beta_Calculation'!B46 -> Dezign Format | D70: UZF | H70: 7. Stock: | I70: ='03_Beta_Calculation'!B51 -> ZICO Hldgs | J70: 40W | O70: 12. Stock: | P70: ='03_Beta_Calculation'!B56 -> KingsmenCreative | Q70: 5MZ
A71: Year | B71: Price (Start) | C71: Price (End) | D71: Dividend | E71: Annual Return Formula | H71: Year | I71: Price (Start) | J71: Price (End) | K71: Dividend | L71: Annual Return Formula | O71: Year | P71: Price (Start) | Q71: Price (End) | R71: Dividend | S71: Annual Return Formula
A72: 2010 | H72: 2010 | O72: 2010 | P72: 0.57 | Q72: 0.565 | R72: =0.02+0.015 -> 0.035 | S72: =(Q72-P72+R72)/P72 -> 0.052631579
A73: 2011 | H73: 2011 | O73: 2011 | P73: =Q72 -> 0.565 | Q73: 0.57 | R73: =0.025+0.015 -> 0.04 | S73: =(Q73-P73+R73)/P73 -> 0.079646018
A74: 2012 | H74: 2012 | O74: 2012 | P74: =Q73 -> 0.57 | Q74: 0.77 | R74: =0.025+0.015 -> 0.04 | S74: =(Q74-P74+R74)/P74 -> 0.42105263
A75: 2013 | H75: 2013 | I75: 0.41 | J75: 0.41 | K75: 0 | L75: =(J75-I75+K75)/I75 -> 0 | M75: Start date | O75: 2013 | P75: =Q74 -> 0.77 | Q75: 0.92 | R75: =0.015+0.025 -> 0.04 | S75: =(Q75-P75+R75)/P75 -> 0.24675325
A76: 2014 | E76: =(C76-B76+D76)/B76 -> #DIV/0! | F76: Start date | H76: 2014 | I76: =J75 -> 0.41 | J76: 0.48 | K76: 0 | L76: =(J76-I76+K76)/I76 -> 0.17073171 | O76: 2014 | P76: =Q75 -> 0.92 | Q76: 0.96 | R76: =0.025+0.015 -> 0.04 | S76: =(Q76-P76+R76)/P76 -> 0.086956522
A77: 2015 | E77: =(C77-B77+D77)/B77 -> #DIV/0! | H77: 2015 | I77: =J76 -> 0.48 | J77: 0.325 | K77: 0 | L77: =(J77-I77+K77)/I77 -> -0.32291667 | O77: 2015 | P77: =Q76 -> 0.96 | Q77: 0.645 | R77: =0.025+0.01 -> 0.035 | S77: =(Q77-P77+R77)/P77 -> -0.29166667
A78: 2016 | D78: 0 | E78: =(C78-B78+D78)/B78 -> #DIV/0! | H78: 2016 | I78: =J77 -> 0.325 | J78: 0.29 | K78: 0 | L78: =(J78-I78+K78)/I78 -> -0.10769231 | O78: 2016 | P78: =Q77 -> 0.645 | Q78: 0.61 | R78: 0.02 | S78: =(Q78-P78+R78)/P78 -> -0.023255814
A79: 2017 | D79: 0 | E79: =(C79-B79+D79)/B79 -> #DIV/0! | H79: 2017 | I79: =J78 -> 0.29 | J79: 0.245 | K79: 0 | L79: =(J79-I79+K79)/I79 -> -0.15517241 | O79: 2017 | P79: =Q78 -> 0.61 | Q79: 0.635 | R79: 0 | S79: =(Q79-P79+R79)/P79 -> 0.040983607
A80: 2018 | D80: 0 | E80: =(C80-B80+D80)/B80 -> #DIV/0! | H80: 2018 | I80: =J79 -> 0.245 | J80: 0.14 | K80: 0 | L80: =(J80-I80+K80)/I80 -> -0.42857143 | O80: 2018 | P80: =Q79 -> 0.635 | Q80: 0.51 | R80: =0.01+0.015 -> 0.025 | S80: =(Q80-P80+R80)/P80 -> -0.15748031
A81: 2019 | D81: 0 | E81: =(C81-B81+D81)/B81 -> #DIV/0! | H81: 2019 | I81: =J80 -> 0.14 | J81: 0.145 | K81: 0 | L81: =(J81-I81+K81)/I81 -> 0.035714286 | O81: 2019 | P81: =Q80 -> 0.51 | Q81: 0.375 | R81: =0.015+0.01 -> 0.025 | S81: =(Q81-P81+R81)/P81 -> -0.21568627
A82: 2020 | D82: 0 | E82: =(C82-B82+D82)/B82 -> #DIV/0! | H82: 2020 | I82: =J81 -> 0.145 | J82: 0.086 | K82: 0 | L82: =(J82-I82+K82)/I82 -> -0.40689655 | O82: 2020 | P82: =Q81 -> 0.375 | Q82: 0.25 | R82: 0 | S82: =(Q82-P82+R82)/P82 -> -0.33333333
A83: 2021 | D83: 0 | E83: =(C83-B83+D83)/B83 -> #DIV/0! | H83: 2021 | I83: =J82 -> 0.086 | J83: 0.078 | K83: 0 | L83: =(J83-I83+K83)/I83 -> -0.093023256 | O83: 2021 | P83: =Q82 -> 0.25 | Q83: 0.235 | R83: 0 | S83: =(Q83-P83+R83)/P83 -> -0.06
A84: 2022 | D84: 0 | E84: =(C84-B84+D84)/B84 -> #DIV/0! | H84: 2022 | I84: =J83 -> 0.078 | J84: 0.075 | K84: 0 | L84: =(J84-I84+K84)/I84 -> -0.038461538 | O84: 2022 | P84: =Q83 -> 0.235 | Q84: 0.27 | R84: 0 | S84: =(Q84-P84+R84)/P84 -> 0.14893617
A85: 2023 | D85: 0 | E85: =(C85-B85+D85)/B85 -> #DIV/0! | H85: 2023 | I85: =J84 -> 0.075 | J85: 0.05 | K85: 0 | L85: =(J85-I85+K85)/I85 -> -0.33333333 | O85: 2023 | P85: =Q84 -> 0.27 | Q85: 0.275 | R85: 0.01 | S85: =(Q85-P85+R85)/P85 -> 0.055555556
A86: 2024 | B86: =C85 -> 0 | C86: 0.265 | D86: 0 | E86: =(C86-B86+D86)/B86 -> #DIV/0! | H86: 2024 | I86: =J85 -> 0.05 | J86: 0.048 | K86: 0 | L86: =(J86-I86+K86)/I86 -> -0.04 | O86: 2024 | P86: =Q85 -> 0.275 | Q86: 0.27 | R86: 0.01 | S86: =(Q86-P86+R86)/P86 -> 0.018181818
A87: 2025 | B87: =C86 -> 0.265 | C87: 0.23 | D87: 0 | E87: =(C87-B87+D87)/B87 -> -0.13207547 | H87: 2025 | I87: =J86 -> 0.048 | J87: 0.065 | K87: 0 | L87: =(J87-I87+K87)/I87 -> 0.35416667 | O87: 2025 | P87: =Q86 -> 0.27 | Q87: 0.505 | R87: 0.02 | S87: =(Q87-P87+R87)/P87 -> 0.94444444
A89: 3. Stock: | B89: ='03_Beta_Calculation'!B47 -> GKE | C89: 595 | D89: JPY | H89: 8. Stock: | I89: ='03_Beta_Calculation'!B52 -> UnUsUaL | J89: 1D1 | O89: 13. Stock: | P89: ='03_Beta_Calculation'!B57 -> Raffles Edu | Q89: NR7
A90: Year | B90: Price (Start) | C90: Price (End) | D90: Dividend | E90: Annual Return Formula | H90: Year | I90: Price (Start) | J90: Price (End) | K90: Dividend | L90: Annual Return Formula | O90: Year | P90: Price (Start) | Q90: Price (End) | R90: Dividend | S90: Annual Return Formula
A91: 2010 | B91: 607 | C91: 611 | H91: 2010 | O91: 2010 | P91: 0.9671 | Q91: 0.7374 | R91: 0 | S91: =(Q91-P91+R91)/P91 -> -0.23751422
A92: 2011 | B92: =C91 -> 611 | C92: 755 | D92: 18 | H92: 2011 | O92: 2011 | P92: =Q91 -> 0.7374 | Q92: 0.3748 | R92: =0.003627+0.003627 -> 0.007254 | S92: =(Q92-P92+R92)/P92 -> -0.48189043 | T92: 1:3 stk splits
A93: 2012 | B93: =C92 -> 755 | C93: 967 | D93: 22 | H93: 2012 | O93: 2012 | P93: =Q92 -> 0.3748 | Q93: 0.3254 | R93: 0 | S93: =(Q93-P93+R93)/P93 -> -0.13180363
A94: 2013 | B94: =C93 -> 967 | C94: 773 | D94: 22 | E94: =(C94-B94+D94)/B94 -> -0.1778697 | F94: Start date' | H94: 2013 | O94: 2013 | P94: =Q93 -> 0.3254 | Q94: 0.2486 | R94: 0 | S94: =(Q94-P94+R94)/P94 -> -0.23601721
A95: 2014 | B95: =C94 -> 773 | C95: 769 | D95: 22 | E95: =(C95-B95+D95)/B95 -> 0.023285899 | H95: 2014 | O95: 2014 | P95: =Q94 -> 0.2486 | Q95: 0.2983 | R95: 0.009038 | S95: =(Q95-P95+R95)/P95 -> 0.23627514
A96: 2015 | B96: =C95 -> 769 | C96: 661 | D96: 22 | E96: =(C96-B96+D96)/B96 -> -0.11183355 | H96: 2015 | O96: 2015 | P96: =Q95 -> 0.2983 | Q96: 0.2169 | R96: 0.009038 | S96: =(Q96-P96+R96)/P96 -> -0.24258129
A97: 2016 | B97: =C96 -> 661 | C97: 726 | D97: 22 | E97: =(C97-B97+D97)/B97 -> 0.13161876 | H97: 2016 | I97: 0 | J97: 0 | K97: 0 | L97: 0 | O97: 2016 | P97: =Q96 -> 0.2169 | Q97: 0.1744 | R97: 0 | S97: =(Q97-P97+R97)/P97 -> -0.19594283
A98: 2017 | B98: =C97 -> 726 | C98: 853 | D98: 22 | E98: =(C98-B98+D98)/B98 -> 0.20523416 | H98: 2017 | I98: 0.2969 | J98: 0.455 | K98: 0 | L98: =(J98-I98+K98)/I98 -> 0.53250253 | M98: 8:5 Stk Split | O98: 2017 | P98: =Q97 -> 0.1744 | Q98: 0.2395 | R98: 0 | S98: =(Q98-P98+R98)/P98 -> 0.37327982
A99: 2018 | B99: =C98 -> 853 | C99: 701 | D99: 22 | E99: =(C99-B99+D99)/B99 -> -0.15240328 | H99: 2018 | I99: =J98 -> 0.455 | J99: 0.3 | K99: 0 | L99: =(J99-I99+K99)/I99 -> -0.34065934 | O99: 2018 | P99: =Q98 -> 0.2395 | Q99: 0.109 | R99: 0 | S99: =(Q99-P99+R99)/P99 -> -0.54488518
A100: 2019 | B100: =C99 -> 701 | C100: 691 | D100: 22 | E100: =(C100-B100+D100)/B100 -> 0.017118402 | H100: 2019 | I100: =J99 -> 0.3 | J100: 0.22 | K100: 0.00342 | L100: =(J100-I100+K100)/I100 -> -0.25526667 | O100: 2019 | P100: =Q99 -> 0.109 | Q100: 0.08 | R100: 0 | S100: =(Q100-P100+R100)/P100 -> -0.26605505
A101: 2020 | B101: =C100 -> 691 | C101: 872 | D101: 22 | E101: =(C101-B101+D101)/B101 -> 0.29377713 | H101: 2020 | I101: =J100 -> 0.22 | J101: 0.181 | K101: 0 | L101: =(J101-I101+K101)/I101 -> -0.17727273 | O101: 2020 | P101: =Q100 -> 0.08 | Q101: 0.13 | R101: 0 | S101: =(Q101-P101+R101)/P101 -> 0.625
A102: 2021 | B102: =C101 -> 872 | C102: 720 | D102: 22 | E102: =(C102-B102+D102)/B102 -> -0.14908257 | H102: 2021 | I102: =J101 -> 0.181 | J102: 0.125 | K102: 0 | L102: =(J102-I102+K102)/I102 -> -0.30939227 | O102: 2021 | P102: =Q101 -> 0.13 | Q102: 0.068 | R102: 0 | S102: =(Q102-P102+R102)/P102 -> -0.47692308
A103: 2022 | B103: =C102 -> 720 | C103: 697 | D103: 22 | E103: =(C103-B103+D103)/B103 -> -0.0013888889 | H103: 2022 | I103: =J102 -> 0.125 | J103: 0.142 | K103: 0 | L103: =(J103-I103+K103)/I103 -> 0.136 | O103: 2022 | P103: =Q102 -> 0.068 | Q103: 0.055 | R103: 0 | S103: =(Q103-P103+R103)/P103 -> -0.19117647
A104: 2023 | B104: =C103 -> 697 | C104: 718 | D104: 22 | E104: =(C104-B104+D104)/B104 -> 0.06169297 | H104: 2023 | I104: =J103 -> 0.142 | J104: 0.192 | K104: 0 | L104: =(J104-I104+K104)/I104 -> 0.35211268 | O104: 2023 | P104: =Q103 -> 0.055 | Q104: 0.051 | R104: 0 | S104: =(Q104-P104+R104)/P104 -> -0.072727273
A105: 2024 | B105: =C104 -> 718 | C105: 658 | D105: 22 | E105: =(C105-B105+D105)/B105 -> -0.052924791 | H105: 2024 | I105: =J104 -> 0.192 | J105: 0.118 | K105: 0 | L105: =(J105-I105+K105)/I105 -> -0.38541667 | O105: 2024 | P105: =Q104 -> 0.051 | Q105: 0.038 | R105: 0 | S105: =(Q105-P105+R105)/P105 -> -0.25490196
A106: 2025 | B106: =C105 -> 658 | C106: 908 | D106: 22 | E106: =(C106-B106+D106)/B106 -> 0.41337386 | H106: 2025 | I106: =J105 -> 0.118 | J106: 0.029 | K106: 0 | L106: =(J106-I106+K106)/I106 -> -0.75423729 | O106: 2025 | P106: =Q105 -> 0.038 | Q106: 0.162 | R106: 0 | S106: =(Q106-P106+R106)/P106 -> 3.2631579
A108: 4. Stock: | B108: ='03_Beta_Calculation'!B48 -> Hiap Tong | H108: 9. Stock: | I108: ='03_Beta_Calculation'!B53 -> Abundante | J108: 570 | O108: 14. Stock:
A109: Year | B109: Price (Start) | C109: Price (End) | D109: Dividend | E109: Annual Return Formula | H109: Year | I109: Price (Start) | J109: Price (End) | K109: Dividend | L109: Annual Return Formula | O109: Year | P109: Price (Start) | Q109: Price (End) | R109: Dividend | S109: Annual Return Formula
A110: 2010 | B110: 0.265 | C110: 0.15 | H110: 2010 | I110: 0.34 | J110: 0.35 | K110: =0.02+0.01 -> 0.03 | L110: =(J110-I110+K110)/I110 -> 0.11764706 | O110: 2010
A111: 2011 | B111: =C110 -> 0.15 | C111: 0.069 | E111: =(C111-B111+D111)/B111 -> -0.54 | H111: 2011 | I111: =J110 -> 0.35 | J111: 0.315 | K111: =0.015+0.01 -> 0.025 | L111: =(J111-I111+K111)/I111 -> -0.028571429 | O111: 2011
A112: 2012 | B112: =C111 -> 0.069 | C112: 0.15 | D112: 0.005 | E112: =(C112-B112+D112)/B112 -> 1.2463768 | H112: 2012 | I112: =J111 -> 0.315 | J112: 0.29 | K112: =0.01+0.01 -> 0.02 | L112: =(J112-I112+K112)/I112 -> -0.015873016 | O112: 2012
A113: 2013 | B113: =C112 -> 0.15 | C113: 0.146 | D113: 0.007 | E113: =(C113-B113+D113)/B113 -> 0.02 | H113: 2013 | I113: =J112 -> 0.29 | J113: 0.36 | K113: =0.01+0.015 -> 0.025 | L113: =(J113-I113+K113)/I113 -> 0.32758621 | O113: 2013
A114: 2014 | B114: =C113 -> 0.146 | C114: 0.155 | D114: 0 | E114: =(C114-B114+D114)/B114 -> 0.061643836 | H114: 2014 | I114: =J113 -> 0.36 | J114: 0.425 | K114: =0.015+0.015 -> 0.03 | L114: =(J114-I114+K114)/I114 -> 0.26388889 | O114: 2014
A115: 2015 | B115: =C114 -> 0.155 | C115: 0.081 | D115: 0 | E115: =(C115-B115+D115)/B115 -> -0.47741935 | H115: 2015 | I115: =J114 -> 0.425 | J115: 0.545 | K115: =0.02+0.02 -> 0.04 | L115: =(J115-I115+K115)/I115 -> 0.37647059 | O115: 2015
A116: 2016 | B116: =C115 -> 0.081 | C116: 0.078 | D116: 0 | E116: =(C116-B116+D116)/B116 -> -0.037037037 | H116: 2016 | I116: =J115 -> 0.545 | J116: 0.65 | K116: =0.02+0.015 -> 0.035 | L116: =(J116-I116+K116)/I116 -> 0.25688073 | O116: 2016 | P116: 0 | Q116: 0 | R116: 0 | S116: =(Q116-P116+R116)/P116 -> #DIV/0!
A117: 2017 | B117: =C116 -> 0.078 | C117: 0.12 | D117: 0 | E117: =(C117-B117+D117)/B117 -> 0.53846154 | F117: Stk split 11:10 | H117: 2017 | I117: =J116 -> 0.65 | J117: 0.465 | K117: =0.01+0.01 -> 0.02 | L117: =(J117-I117+K117)/I117 -> -0.25384615 | O117: 2017 | P117: =Q116 -> 0 | Q117: 0 | R117: 0 | S117: =(Q117-P117+R117)/P117 -> #DIV/0!
A118: 2018 | B118: =C117 -> 0.12 | C118: 0.072 | D118: 0 | E118: =(C118-B118+D118)/B118 -> -0.4 | F118: Stk split 6:5 | H118: 2018 | I118: =J117 -> 0.465 | J118: 0.23 | K118: 0 | L118: =(J118-I118+K118)/I118 -> -0.50537634 | O118: 2018 | P118: =Q117 -> 0 | Q118: 0 | R118: 0 | S118: =(Q118-P118+R118)/P118 -> #DIV/0!
A119: 2019 | B119: =C118 -> 0.072 | C119: 0.068 | D119: 0.0005 | E119: =(C119-B119+D119)/B119 -> -0.048611111 | H119: 2019 | I119: =J118 -> 0.23 | J119: 0.105 | K119: 0 | L119: =(J119-I119+K119)/I119 -> -0.54347826 | O119: 2019 | P119: =Q118 -> 0 | Q119: 0 | R119: 0 | S119: =(Q119-P119+R119)/P119 -> #DIV/0!
...

Sheet 03c_Size Premium Method 10Y
A5: A. Annual Returns calculations: | G5: B. Portfolio (Decile) Returns
A6: 1.: | B6: ='03_Beta_Calculation'!B45 -> Audience | G6: Stocks | H6: 1 | I6: 2 | J6: 3 | K6: 4 | L6: 5 | M6: 6 | N6: 7 | O6: 8 | P6: 9 | Q6: 10 | R6: 11 | S6: 12 | T6: 13
A7: Year | B7: Price (Start) | C7: Price (End) | D7: Dividend | E7: Annual Return Formula | G7: Year | H7: =B6 -> Audience | I7: =B19 -> Dezign Format | J7: =B32 -> GKE | K7: =B45 -> CapitaLandInvest | L7: =B58 -> LS 2 Holdings | M7: =B71 -> VCPlus | N7: =B84 -> ZICO Hldgs | O7: =B97 -> UnUsUaL | P7: =B110 -> Abundante | Q7: =B123 -> Frasers Property | R7: =B136 -> SIA Engineering | S7: =B149 -> Wing Tai | T7: =B162 -> #REF! | U7: Portfolio Average
A8: 2016 | B8: 0.21 | C8: 0.17 | D8: 0 | E8: =(C8-B8+D8)/B8 -> -0.19047619 | G8: 2016 | H8: =E8 -> -0.19047619 | I8: =E21 -> -0.22033898 | J8: =E34 -> 0.13836478 | K8: =E47 -> 0.11442795 | L8: =E60 -> 0.19512195 | M8: =E73 -> 0.51428571 | N8: =E86 -> 0.0215 | O8: =E99 -> 0 | P8: =E112 -> 0.1037037 | Q8: =E125 -> 0.03968254 | R8: =E138 -> -0.9031746 | S8: =E151 -> 0.068965517 | T8: =E164 -> -0.2047619 | U8: =AVERAGE(H8:T8)-K8-S8-Q8 -> -0.24789905
A9: 2017 | B9: =C8 -> 0.17 | C9: 0.24 | D9: 0 | E9: =(C9-B9+D9)/B9 -> 0.41176471 | G9: 2017 | H9: =E9 -> 0.41176471 | I9: =E22 -> -0.54347826 | J9: =E35 -> 0.060606061 | K9: =E48 -> 0.67656947 | L9: =E61 -> -0.1122449 | M9: =E74 -> 0.32075472 | N9: =E87 -> -0.0075757576 | O9: =E100 -> 0.023255814 | P9: =E113 -> -0.054237288 | Q9: =E126 -> 0.45634921 | R9: =E139 -> -0.39344262 | S9: =E152 -> 0.26724138 | T9: =E165 -> 0.14371257 | U9: =AVERAGE(H9:T9)-K9-S9-Q9 -> -1.304062
A10: 2018 | B10: =C9 -> 0.24 | C10: 0.084 | D10: 0 | E10: =(C10-B10+D10)/B10 -> -0.65 | G10: 2018 | H10: =E10 -> -0.65 | I10: =E23 -> -0.4047619 | J10: =E36 -> -0.41542857 | K10: =E49 -> -0.45592071 | L10: =E62 -> -0.3908046 | M10: =E75 -> -0.77142857 | N10: =E88 -> -0.18974359 | O10: =E101 -> -0.29090909 | P10: =E114 -> -0.090740741 | Q10: =E127 -> -0.12359551 | R10: =E140 -> -0.51351351 | S10: =E153 -> -0.14388489 | T10: =E166 -> -0.036649215 | U10: =AVERAGE(H10:T10)-K10-S10-Q10 -> 0.37898719
A11: 2019 | B11: =C10 -> 0.084 | C11: 0.088 | D11: 0 | E11: =(C11-B11+D11)/B11 -> 0.047619048 | G11: 2019 | H11: =E11 -> 0.047619048 | I11: =E24 -> -0.86 | J11: =E37 -> 0.020833333 | K11: =E50 -> 0.20006714 | L11: =E63 -> 0.037735849 | M11: =E76 -> -0.125 | N11: =E89 -> 0.12987013 | O11: =E102 -> -0.51653846 | P11: =E115 -> -0.044680851 | Q11: =E128 -> 0.057894737 | R11: =E141 -> 0 | S11: =E154 -> -0.22608696 | T11: =E167 -> 0.048913043 | U11: =AVERAGE(H11:T11)-K11-S11-Q11 -> -0.12644207
A12: 2020 | B12: =C11 -> 0.088 | C12: 0.088 | D12: 0 | E12: =(C12-B12+D12)/B12 -> 0 | G12: 2020 | H12: =E12 -> 0 | I12: =E25 -> -0.28571429 | J12: =E38 -> -0.021052632 | K12: =E51 -> -0.3047482 | L12: =E64 -> -0.23636364 | M12: =E77 -> 1.7142857 | N12: =E90 -> -0.25287356 | O12: =E103 -> 2.3333333 | P12: =E116 -> -0.24772727 | Q12: =E129 -> -0.0038461538 | R12: =E142 -> -0.11111111 | S12: =E155 -> -0.034883721 | T12: =E168 -> 0.010362694 | U12: =AVERAGE(H12:T12)-K12-S12-Q12 -> 0.54037509
A13: 2021 | B13: =C12 -> 0.088 | C13: 0.088 | D13: 0 | E13: =(C13-B13+D13)/B13 -> 0 | G13: 2021 | H13: =E13 -> 0 | I13: =E26 -> 0 | J13: =E39 -> -0.55555556 | K13: =E52 -> -0.18442256 | L13: =E65 -> 0.5952381 | M13: =E78 -> 0.42105263 | N13: =E91 -> -0.23076923 | O13: =E104 -> -0.70833333 | P13: =E117 -> -0.083841463 | Q13: =E130 -> 0.054054054 | R13: =E143 -> 0.625 | S13: =E156 -> 0.175 | T13: =E169 -> 0.36410256 | U13: =AVERAGE(H13:T13)-K13-S13-Q13 -> -0.0083603243
A14: 2022 | B14: =C13 -> 0.088 | C14: 0.088 | D14: 0 | E14: =(C14-B14+D14)/B14 -> 0 | G14: 2022 | H14: =E14 -> 0 | I14: =E27 -> 0 | J14: =E40 -> -0.1 | K14: =E53 -> -0.17918753 | L14: =E66 -> -0.29850746 | M14: =E79 -> -0.33333333 | N14: =E92 -> 0.2 | O14: =E105 -> -0.5 | P14: =E118 -> -0.077702703 | Q14: =E131 -> -0.026315789 | R14: =E144 -> -0.076923077 | S14: =E157 -> -0.033707865 | T14: =E170 -> -0.21052632 | U14: =AVERAGE(H14:T14)-K14-S14-Q14 -> 0.11334934
A15: 2023 | B15: =C14 -> 0.088 | C15: 0.088 | D15: 0 | E15: =(C15-B15+D15)/B15 -> 0 | G15: 2023 | H15: =E15 -> 0 | I15: =E28 -> -0.6 | J15: =E41 -> -0.41666667 | K15: =E54 -> -0.36551724 | L15: =E67 -> -0.34042553 | M15: =E80 -> -0.22222222 | N15: =E93 -> 0 | O15: =E106 -> -0.42857143 | P15: =E119 -> 0.0097333333 | Q15: =E132 -> -0.055555556 | R15: =E145 -> 0.125 | S15: =E158 -> -0.17073171 | T15: =E171 -> 0.69047619 | U15: =AVERAGE(H15:T15)-K15-S15-Q15 -> 0.45530598
A16: 2024 | B16: =C15 -> 0.088 | C16: 0.088 | D16: 0 | E16: =(C16-B16+D16)/B16 -> 0 | G16: 2024 | H16: =E16 -> 0 | I16: =E29 -> -0.5 | J16: =E42 -> 0.52380952 | K16: =E55 -> -0.22826087 | L16: =E68 -> 0.032258065 | M16: =E81 -> -0.14285714 | N16: =E94 -> -0.041666667 | O16: =E107 -> 1.4 | P16: =E120 -> -0.083230769 | Q16: =E133 -> 0.060606061 | R16: =E146 -> 2.5925926 | S16: =E159 -> 0.015151515 | T16: =E172 -> -5.5511151e-17 | U16: =AVERAGE(H16:T16)-K16-S16-Q16 -> 0.43161116
A17: 2025 | B17: =C16 -> 0.088 | C17: 0.044 | D17: 0 | E17: =(C17-B17+D17)/B17 -> -0.5 | G17: 2025 | H17: =E17 -> -0.5 | I17: =E30 -> 0 | J17: =E43 -> 0.5625 | K17: =E56 -> 0.1971831 | L17: =E69 -> 0.40625 | M17: =E82 -> 0.29166667 | N17: =E95 -> -0.13913043 | O17: =E108 -> -0.20833333 | P17: =E121 -> 0.18432203 | Q17: =E134 -> 0.89705882 | R17: =E147 -> 0.46701031 | S17: =E160 -> 1.484375 | T17: =E173 -> 0.37142857 | U17: =AVERAGE(H17:T17)-K17-S17 -> -1.3727634
Q18: Average | U18: =AVERAGE(U8:U17) -> -0.11398981
A19: 2. Stock: | B19: ='03_Beta_Calculation'!B46 -> Dezign Format
A20: Year | B20: Price (Start) | C20: Price (End) | D20: Dividend | E20: Annual Return Formula | S20: Average of 13/17 X Portfolio Average | U20: =12/'15_DB_SGX_Industry'!J568*'03c_Size Premium Method 10Y'!U18 -> #DIV/0!
A21: 2016 | B21: 0.236 | C21: 0.184 | D21: 0 | E21: =(C21-B21+D21)/B21 -> -0.22033898 | S21: =13/'15_DB_SGX_Industry'!J568*'03c_Size Premium Method 10Y'!U18 -> #DIV/0!
A22: 2017 | B22: =C21 -> 0.184 | C22: 0.084 | D22: 0 | E22: =(C22-B22+D22)/B22 -> -0.54347826 | F22: Stk split 1:4
A23: 2018 | B23: =C22 -> 0.084 | C23: 0.05 | D23: 0 | E23: =(C23-B23+D23)/B23 -> -0.4047619
A24: 2019 | B24: =C23 -> 0.05 | C24: 0.007 | D24: 0 | E24: =(C24-B24+D24)/B24 -> -0.86
A25: 2020 | B25: =C24 -> 0.007 | C25: 0.005 | D25: 0 | E25: =(C25-B25+D25)/B25 -> -0.28571429
A26: 2021 | B26: =C25 -> 0.005 | C26: 0.005 | D26: 0 | E26: =(C26-B26+D26)/B26 -> 0
A27: 2022 | B27: =C26 -> 0.005 | C27: 0.005 | D27: 0 | E27: =(C27-B27+D27)/B27 -> 0
A28: 2023 | B28: =C27 -> 0.005 | C28: 0.002 | D28: 0 | E28: =(C28-B28+D28)/B28 -> -0.6
A29: 2024 | B29: =C28 -> 0.002 | C29: 0.001 | D29: 0 | E29: =(C29-B29+D29)/B29 -> -0.5
A30: 2025 | B30: =C29 -> 0.001 | C30: 0.001 | D30: 0 | E30: =(C30-B30+D30)/B30 -> 0
A32: 3. Stock: | B32: ='03_Beta_Calculation'!B47 -> GKE | M32: Note
A33: Year | B33: Price (Start) | C33: Price (End) | D33: Dividend | E33: Annual Return Formula | G33: Portfolio (Yr 2025) | I33: Average Return | J33: CAPM Predicted Return | K33: Size Premium | L33: 1 | M33: Our 5-year SGX small-cap sample produced a negative size premium (-10.57%), reflecting extreme volatility and underperformance of microcaps in this period. However, global empirical studies (Duff & Phelps, Morningstar) using longer horizons consistently show positive premiums of 2–5% for similar deciles. For conservatism and alignment with global standards, we apply a capped premium in that range.
A34: 2016 | B34: 0.159 | C34: 0.165 | D34: 0.016 | E34: =(C34-B34+D34)/B34 -> 0.13836478 | G34: Small-Cap Decile | I34: =U18 -> -0.11398981 | J34: =(' 04_CAPM'!D4+('03_Beta_Calculation'!E59*' 04_CAPM'!D7))% -> 0.046857938 | K34: =I34-J34 -> -0.16084775
A35: 2017 | B35: =C34 -> 0.165 | C35: 0.175 | D35: 0 | E35: =(C35-B35+D35)/B35 -> 0.060606061 | G35: Average of 13 out of 17 small-cap stock | I35: =U20 -> #DIV/0! | J35: =J34 -> 0.046857938 | K35: =I35-J35 -> #DIV/0! | L35: 2 | M35: Our SGX small-cap sample (2016–2025) produced a negative size premium (–6.79%), reflecting extreme volatility and underperformance of microcaps in this period. However, global empirical studies (Duff & Phelps, Morningstar) using longer horizons consistently show positive premiums of 2–5% for similar deciles. For conservatism and alignment with global standards, we apply a capped premium in that range
A36: 2018 | B36: =C35 -> 0.175 | C36: 0.096 | D36: 0.0063 | E36: =(C36-B36+D36)/B36 -> -0.41542857 | G36: 👉 Example:
A37: 2019 | B37: =C36 -> 0.096 | C37: 0.095 | D37: 0.003 | E37: =(C37-B37+D37)/B37 -> 0.020833333 | G37: Average Return =AVERAGE(Portfolio_Returns)= 6.5% | L37: 3 | M37: Our SGX small-cap portfolio (2016–2025) produced a negative size premium when including highly volatile firms such as Oxley and KOP. Excluding these outliers, the portfolio average return turns positive, aligning more closely with Duff & Phelps’ long-run empirical ranges (2–5%). This demonstrates both the sensitivity of local samples and the robustness of global decile studies
A38: 2020 | B38: =C37 -> 0.095 | C38: 0.09 | D38: 0.003 | E38: =(C38-B38+D38)/B38 -> -0.021052632 | G38: CAPM Predicted =Rf + Beta*ERP= 5.9%
A39: 2021 | B39: =C38 -> 0.09 | C39: 0.04 | D39: 0 | E39: =(C39-B39+D39)/B39 -> -0.55555556 | G39: Size Premium =Average_Return - CAPM= 0.6%
A40: 2022 | B40: =C39 -> 0.04 | C40: 0.036 | D40: 0 | E40: =(C40-B40+D40)/B40 -> -0.1
A41: 2023 | B41: =C40 -> 0.036 | C41: 0.021 | D41: 0 | E41: =(C41-B41+D41)/B41 -> -0.41666667
A42: 2024 | B42: =C41 -> 0.021 | C42: 0.032 | D42: 0 | E42: =(C42-B42+D42)/B42 -> 0.52380952
A43: 2025 | B43: =C42 -> 0.032 | C43: 0.05 | D43: 0 | E43: =(C43-B43+D43)/B43 -> 0.5625 | G43: Company Type | J43: Likely Decile | M43: Typical Size Premium (2025)
G44: City Dev, UOL, Capitaland, Guccoland, SingaporeLand | J44: Decile 2-4 | M44: abt 0.8% - 1.5%
A45: 4. Stock: | B45: ='03_Beta_Calculation'!B19 -> CapitaLandInvest
A46: Year | B46: Price (Start) | C46: Price (End) | D46: Dividend | E46: Annual Return Formula | G46: Wing Tai, Ho Bee Land, Sing Hold | J46: Decile 5-7 | M46: abt 1.5% - 2.5%
A47: 2016 | B47: 0.3234 | C47: 0.3498 | D47: =0.005682+0.00303+0.001894 -> 0.010606 | E47: =(C47-B47+D47)/B47 -> 0.11442795 | G47: Oxley, Low Keng Huat, Niche Developers | J47: Decile 8-10 | M47: abt 2.5% - 4.0%
A48: 2017 | B48: =C47 -> 0.3498 | C48: 0.5751 | D48: =0.003788+0.002273+0.005303 -> 0.011364 | E48: =(C48-B48+D48)/B48 -> 0.67656947 | F48: Stk split 11:10
A49: 2018 | B49: =C48 -> 0.5751 | C49: 0.2979 | D49: =0.0072+0.0078 -> 0.015 | E49: =(C49-B49+D49)/B49 -> -0.45592071 | F49: Stk split 6:5
A50: 2019 | B50: =C49 -> 0.2979 | C50: 0.3475 | D50: =0.0032+0.0068 -> 0.01 | E50: =(C50-B50+D50)/B50 -> 0.20006714
A51: 2020 | B51: =C50 -> 0.3475 | C51: 0.2234 | D51: =0.0032+0.015 -> 0.0182 | E51: =(C51-B51+D51)/B51 -> -0.3047482
A52: 2021 | B52: =C51 -> 0.2234 | C52: 0.1797 | D52: 0.0025 | E52: =(C52-B52+D52)/B52 -> -0.18442256
A53: 2022 | B53: =C52 -> 0.1797 | C53: 0.145 | D53: 0.0025 | E53: =(C53-B53+D53)/B53 -> -0.17918753
A54: 2023 | B54: =C53 -> 0.145 | C54: 0.092 | D54: 0 | E54: =(C54-B54+D54)/B54 -> -0.36551724
A55: 2024 | B55: =C54 -> 0.092 | C55: 0.071 | D55: 0 | E55: =(C55-B55+D55)/B55 -> -0.22826087
A56: 2025 | B56: =C55 -> 0.071 | C56: 0.085 | D56: 0 | E56: =(C56-B56+D56)/B56 -> 0.1971831
A58: 5. Stock: | B58: ='03_Beta_Calculation'!B49 -> LS 2 Holdings
A59: Year | B59: Price (Start) | C59: Price (End) | D59: Dividend | E59: Annual Return Formula
A60: 2016 | B60: 0.082 | C60: 0.098 | D60: 0 | E60: =(C60-B60+D60)/B60 -> 0.19512195
A61: 2017 | B61: =C60 -> 0.098 | C61: 0.087 | D61: 0 | E61: =(C61-B61+D61)/B61 -> -0.1122449
A62: 2018 | B62: =C61 -> 0.087 | C62: 0.053 | D62: 0 | E62: =(C62-B62+D62)/B62 -> -0.3908046
A63: 2019 | B63: =C62 -> 0.053 | C63: 0.055 | D63: 0 | E63: =(C63-B63+D63)/B63 -> 0.037735849
A64: 2020 | B64: =C63 -> 0.055 | C64: 0.042 | D64: 0 | E64: =(C64-B64+D64)/B64 -> -0.23636364
A65: 2021 | B65: =C64 -> 0.042 | C65: 0.067 | D65: 0 | E65: =(C65-B65+D65)/B65 -> 0.5952381
A66: 2022 | B66: =C65 -> 0.067 | C66: 0.047 | D66: 0 | E66: =(C66-B66+D66)/B66 -> -0.29850746
A67: 2023 | B67: =C66 -> 0.047 | C67: 0.031 | D67: 0 | E67: =(C67-B67+D67)/B67 -> -0.34042553
A68: 2024 | B68: =C67 -> 0.031 | C68: 0.032 | D68: 0 | E68: =(C68-B68+D68)/B68 -> 0.032258065
A69: 2025 | B69: =C68 -> 0.032 | C69: 0.045 | D69: 0 | E69: =(C69-B69+D69)/B69 -> 0.40625
A71: 6. Stock: | B71: ='03_Beta_Calculation'!B50 -> VCPlus
A72: Year | B72: Price (Start) | C72: Price (End) | D72: Dividend | E72: Annual Return Formula
A73: 2016 | B73: 0.035 | C73: 0.053 | D73: 0 | E73: =(C73-B73+D73)/B73 -> 0.51428571
A74: 2017 | B74: =C73 -> 0.053 | C74: 0.07 | D74: 0 | E74: =(C74-B74+D74)/B74 -> 0.32075472
A75: 2018 | B75: =C74 -> 0.07 | C75: 0.016 | D75: 0 | E75: =(C75-B75+D75)/B75 -> -0.77142857
A76: 2019 | B76: =C75 -> 0.016 | C76: 0.014 | D76: 0 | E76: =(C76-B76+D76)/B76 -> -0.125
A77: 2020 | B77: =C76 -> 0.014 | C77: 0.038 | D77: 0 | E77: =(C77-B77+D77)/B77 -> 1.7142857
A78: 2021 | B78: =C77 -> 0.038 | C78: 0.054 | D78: 0 | E78: =(C78-B78+D78)/B78 -> 0.42105263
A79: 2022 | B79: =C78 -> 0.054 | C79: 0.036 | D79: 0 | E79: =(C79-B79+D79)/B79 -> -0.33333333
A80: 2023 | B80: =C79 -> 0.036 | C80: 0.028 | D80: 0 | E80: =(C80-B80+D80)/B80 -> -0.22222222
A81: 2024 | B81: =C80 -> 0.028 | C81: 0.024 | D81: 0 | E81: =(C81-B81+D81)/B81 -> -0.14285714
A82: 2025 | B82: =C81 -> 0.024 | C82: 0.031 | D82: 0 | E82: =(C82-B82+D82)/B82 -> 0.29166667
A84: 7. Stock: | B84: ='03_Beta_Calculation'!B51 -> ZICO Hldgs
A85: Year | B85: Price (Start) | C85: Price (End) | D85: Dividend | E85: Annual Return Formula
A86: 2016 | B86: 0.2 | C86: 0.198 | D86: =0.0022+0.0041 -> 0.0063 | E86: =(C86-B86+D86)/B86 -> 0.0215
A87: 2017 | B87: =C86 -> 0.198 | C87: 0.195 | D87: 0.0015 | E87: =(C87-B87+D87)/B87 -> -0.0075757576
A88: 2018 | B88: =C87 -> 0.195 | C88: 0.154 | D88: =0.0015+0.0025 -> 0.004 | E88: =(C88-B88+D88)/B88 -> -0.18974359
A89: 2019 | B89: =C88 -> 0.154 | C89: 0.174 | D89: 0 | E89: =(C89-B89+D89)/B89 -> 0.12987013
A90: 2020 | B90: =C89 -> 0.174 | C90: 0.13 | D90: 0 | E90: =(C90-B90+D90)/B90 -> -0.25287356
A91: 2021 | B91: =C90 -> 0.13 | C91: 0.1 | D91: 0 | E91: =(C91-B91+D91)/B91 -> -0.23076923
A92: 2022 | B92: =C91 -> 0.1 | C92: 0.12 | D92: 0 | E92: =(C92-B92+D92)/B92 -> 0.2
A93: 2023 | B93: =C92 -> 0.12 | C93: 0.12 | D93: 0 | E93: =(C93-B93+D93)/B93 -> 0
A94: 2024 | B94: =C93 -> 0.12 | C94: 0.115 | D94: 0 | E94: =(C94-B94+D94)/B94 -> -0.041666667
A95: 2025 | B95: =C94 -> 0.115 | C95: 0.099 | D95: 0 | E95: =(C95-B95+D95)/B95 -> -0.13913043
A97: 8. Stock: | B97: ='03_Beta_Calculation'!B52 -> UnUsUaL
A98: Year | B98: Price (Start) | C98: Price (End) | D98: Dividend | E98: Annual Return Formula
A99: 2016 | B99: 0 | C99: 0 | D99: 0 | E99: 0
A100: 2017 | B100: 0.215 | C100: 0.22 | D100: 0 | E100: =(C100-B100+D100)/B100 -> 0.023255814 | F100: start trading Jul 2017
A101: 2018 | B101: =C100 -> 0.22 | C101: 0.156 | D101: 0 | E101: =(C101-B101+D101)/B101 -> -0.29090909
A102: 2019 | B102: =C101 -> 0.156 | C102: 0.072 | D102: 0.00342 | E102: =(C102-B102+D102)/B102 -> -0.51653846
A103: 2020 | B103: =C102 -> 0.072 | C103: 0.24 | D103: 0 | E103: =(C103-B103+D103)/B103 -> 2.3333333
A104: 2021 | B104: =C103 -> 0.24 | C104: 0.07 | D104: 0 | E104: =(C104-B104+D104)/B104 -> -0.70833333
A105: 2022 | B105: =C104 -> 0.07 | C105: 0.035 | D105: 0 | E105: =(C105-B105+D105)/B105 -> -0.5
A106: 2023 | B106: =C105 -> 0.035 | C106: 0.02 | D106: 0 | E106: =(C106-B106+D106)/B106 -> -0.42857143
A107: 2024 | B107: =C106 -> 0.02 | C107: 0.048 | D107: 0 | E107: =(C107-B107+D107)/B107 -> 1.4
A108: 2025 | B108: =C107 -> 0.048 | C108: 0.038 | D108: 0 | E108: =(C108-B108+D108)/B108 -> -0.20833333
A110: 9. Stock: | B110: ='03_Beta_Calculation'!B53 -> Abundante
...

Sheet  04_CAPM
B1: Capitalization Rate as at: | D1: 31st Dec 2025
D2: %age
A4: 1 | B4: SG 10-year Bond Yields | C4: Rf | D4: 2.22 | G4: re​=rf​+βL​(ERP)+Size Premium+CSRP
A7: 2 | B7: Market Risk Premia - Equity Risk Premium | C7: Pl | D7: 4.65
A9: 3 | B9: Industry-Specific risk Premium (Re-levered Beta X ERP)-ERP | C9: Pi | D9: =(C10*D7)-D7 -> 1.6098834
B10: a) Re-levered average industry components unlevered beta [βL=βU×(1+(1−T)*D/E)] | C10: ='03i_Beta_Calculation'!D47 -> 1.3462115
A12: 5 | B12: Small-Cap size risk premium | C12: Ps | D12: ='03b_Size Premium Method 15Y'!E27 -> 6.0302554
A14: 6 | B14: Company-specific risk premium | C14: Pc | D14: ='10_CSRP_Scoring'!B21 -> 4.4
B16: Cost of Equity (d) | C16: d | D16: =SUM(D4:D15) -> 18.910139
B18: Growth (g) -obtained from 02_Normalization | C18: g | D18: ='06b_Sustainable Growth Rate'!B82 -> 0.03
B20: Capitalization Rate | D20: =D16-D18 -> 18.880139
C21: P/E ratio | D21: =100/D20 -> 5.2965712 | E21: times
B25: ERi​=Rf​+βi​(ERm​−Rf​)where:ERi​=expected return of investmentRf​=risk-free rateβi​=beta of the investment(ERm​−Rf​)=market risk premium​
J29: =0.005*100 -> 0.5

Sheet 05_WACC
A3: Determining the Borrowing Capacity of the Company in the Excess Earnings Method (Rounded)
A4: Note: Using Book Debt/Equity (if available)
A5: Fixed Assets at cost | B5: Loan interest rates | C5: Asset Values @ 31/12/2021 | D5: Multiply Borrowing percentage from Bank (Collateral Value) | E5: Equals: Company Borrowing Capacity Based on Tangible Assets | F5: Asset average ratio (Asset Values/Total Asset Value) | G5: Weighted interest rate (average ratio X Interest rate) | H5: Remarks
A6: Term loan 1 -Property loan @ 4% | B6: 4 | C6: 4269474 | D6: =E6/C6 -> 0.77761335 | E6: 3320000 | F6: =C6/$C$11 -> 0.89106021 | G6: =B6*F6 -> 3.5642408 | H6: Numbers are based on loan agreements
A7: Term loan 2 -SME Working Capital @ 3% | B7: 3 | C7: 330000 | D7: =E7/C7 -> 1 | E7: 330000 | F7: =C7/$C$11 -> 0.068872622 | G7: =F7*B7 -> 0.20661787 | H7: Numbers are based on loan agreements
A8: Finance lease @ 4.06% | B8: 4.06 | C8: 191980 | D8: =E8/C8 -> 0.9166684 | E8: 175982 | F8: =C8/$C$11 -> 0.04006717 | G8: =F8*B8 -> 0.16267271 | H8: Numbers are based on loan agreements
E9: Cost of debt (average bank loan): | G9: =SUM(G6:G8) -> 3.9335314
F10: Tax rate of 17% | G10: =G9*(1-'01_Inputs'!E13) -> 3.2648311 | H10: =(Rd*(1-T)
A11: Total | C11: =SUM(C6:C9) -> 4791454 | D11: =E11/C11 -> 0.79850125 | E11: =SUM(E6:E9) -> 3825982
A14: Calculation of Required Rate of Return on Tangible Assets (Weighted Average Cost of Capital)
C16: Cost | D16: % of Capital Structure | E16: Weighted Cost | G16: Amount as at 30th Sept 2019
A17: Cost of Debt (De) | C17: =G10 -> 3.2648311 | D17: =G17/G19 -> 0.69959335 | E17: =D17*C17 -> 2.2840541 | G17: =C11 -> 4791454
A18: Cost of equity (Ke) | C18: =B36 -> 18.910139 | D18: =1-D17 -> 0.30040665 | E18: =D18*C18 -> 5.6807314 | G18: 2057459
D19: =D17+D18 -> 1 | E19: =E17+E18 -> 7.9647855 | G19: =G17+G18 -> 6848913
A21: Therefore, Weighted Average Cost of Capital (WACC) is: | E21: =E19 -> 7.9647855
A24: Target Company | C24: Beta
A25: Total Debt ( d ) | C25: =G17 -> 4791454
A26: Total Equity ( e ) | C26: =G18 -> 2057459
A27: d/e | C27: =C25/C26 -> 2.3288211
A28: ꞵu | C28: ='03_Beta_Calculation'!E47 -> 0.1943974 | D28: Figtree
A29: Therefore, ꞵl = | C29: =C28*(1+(1-0.17)*C27) -> 0.57015234
A30: ERP | C30: =' 04_CAPM'!D7 -> 4.65
A31: Unlevering target company beta based on comparable peer(s) unlevered beta using the following conversion:
A33: ꞵl = ꞵu [1 + (1-T)*d/e]
A34: ꞵl -Re-Levered beta of target company
A35: ꞵu - unlevered beta of average comparables peer(s). (Obtained from Worksheet 03. Beta computation)
A36: Cost of equity from CAPM build up model | B36: =' 04_CAPM'!D16 -> 18.910139
A37: Ke therefore = Rf + (ꞵl X ERP) = | B37: =' 04_CAPM'!D4+(C29*C30) -> 4.8712084
A38: where Rf is the risk free rate premium, Ke is the Cost of Equity of the target company
A40: Note: Ke is a component of WACC. Cost of debt is usually determined by the interest rate on existing debt or yield-to-maturity on bonds.
A41: WACC (Weighted Average Cost of Capital) used with unlevered Free Cash Flow (FCFF) to find Total Firm Value. Whereas, Ke (cost of equity) is used with Levered FCF (FCFE).
A42: - Unlevered FCF (FCFF): Cash flow available to all investors (debt and equity) before interest payments
A43: - Levered FCF (FCFE): Cash flow available specifically to shareholders after interest payments and debt repayment.
A45: How to arrive at the cost of debt (De)?
A46: Use the current yield-to-maturity (YTM) on the company's long term debt or the interest rate on similar debt in the market. Do not use re-levered beta for the cost of debt; cost of debt is based on market interest rates, not systematic risk.

Sheet 06_Income_Based DCF
B1: Based Year | C1: Projections
A2: Inccome Statement Forecast | B2: 202X | C2: Fyr 1 | D2: Fyr 2 | E2: Fyr 3 | F2: Fyr 4 | G2: Terminal Year Fyr 5
A4: EBIT | B4: ='02_Normalization'!G38 -> 0 | C4: 1500000 | D4: =C4+(C4*2%) -> 1530000 | E4: =D4+(D4*2%) -> 1560600 | F4: =E4+(E4*2%) -> 1591812 | G4: =F4+(F4*2%) -> 1623648.2
A6: Net Operating profit/(loss)
A7: Opening Balance | B7: 0 | C7: =B9 -> 0 | D7: =C9 -> 1500000 | E7: =D9 -> 3030000 | F7: =E9 -> 4590600 | G7: =F9 -> 6182412
A8: Current profit/(loss) | B8: =B4 -> 0 | C8: =C4 -> 1500000 | D8: =D4 -> 1530000 | E8: =E4 -> 1560600 | F8: =F4 -> 1591812 | G8: =G4 -> 1623648.2
A9: Subtotal | B9: =B7+B8 -> 0 | C9: =C7+C8 -> 1500000 | D9: =D7+D8 -> 3030000 | E9: =E7+E8 -> 4590600 | F9: =F7+F8 -> 6182412 | G9: =G7+G8 -> 7806060.2
A10: Loss used | B10: 0
A11: Closing Balance | B11: =B9-B10 -> 0 | C11: =C9-C10 -> 1500000 | D11: =D9-D10 -> 3030000 | E11: =E9-E10 -> 4590600 | F11: =F9-F10 -> 6182412 | G11: =G9-G10 -> 7806060.2
A13: Free Cash flow
A14: Earnings before tax (EBT) | B14: =B11 -> 0 | C14: =C11 -> 1500000 | D14: =D11 -> 3030000 | E14: =E11 -> 4590600 | F14: =F11 -> 6182412 | G14: =G11 -> 7806060.2
A15: Interest | B15: 0 | C15: 0 | D15: 0 | E15: 0 | F15: 0 | G15: 0
A16: EBIT | B16: =B14-B15 -> 0 | C16: =C14-C15 -> 1500000 | D16: =D14-D15 -> 3030000 | E16: =E14-E15 -> 4590600 | F16: =F14-F15 -> 6182412 | G16: =G14-G15 -> 7806060.2
A17: Less Taxes | B17: 0 | C17: =C4*0.17 -> 255000 | D17: =D4*0.17 -> 260100 | E17: =E4*0.17 -> 265302 | F17: =F4*0.17 -> 270608.04 | G17: =G4*0.17 -> 276020.2
A18: Less Capex | B18: 0 | C18: 150000 | D18: 150000 | E18: 200000 | F18: 250000 | G18: 300000
A19: Plus Depreciation | B19: ='02_Normalization'!G30 -> 0 | C19: 350000 | D19: 350000 | E19: 400000 | F19: 400000 | G19: 500000
A20: Less Changes in Working Capital | B20: ='02_Normalization'!G42 -> 0 | C20: 0 | D20: 0 | E20: 0 | F20: 0 | G20: 0
A21: Unlevered Free Cash Flow | B21: =B16-B17-B18+B19-B20 -> 0 | C21: =C4-SUM(C18:C20) -> 1000000 | D21: =D4-SUM(D18:D20) -> 1030000 | E21: =E4-SUM(E18:E20) -> 960600 | F21: =F4-SUM(F18:F20) -> 941812 | G21: =G4-SUM(G18:G20) -> 823648.24
A23: NPV of FCF = (CF/(1+r)^1) | B23: =B21/(1+$G$26%)^0 -> 0 | C23: =C21/(1+$G$26%)^1 -> 926227.93 | D23: =D21/(1+$G$26%)^2 -> 883635.13 | E23: =E21/(1+$G$26%)^3 -> 763301.65 | F23: =F21/(1+$G$26%)^4 -> 693163.54 | G23: =G21/(1+$G$26%)^5 -> 561475.93
A24: where r = WACC or the rate of return
F25: growth (g) | G25: =' 04_CAPM'!D18 -> 0.03 | H25: %age
A26: Forecast Free Cash Flow (FCF) | B26: Amount (S$) | C26: Present Value (FCF/(1+WACC)) | F26: WACC | G26: ='05_WACC'!E21 -> 7.9647855 | H26: %age
A27: Year 1 | B27: =C21 -> 1000000 | C27: =B27/(1+$G$26%)^1 -> 926227.93 | F27: (WACC - g) | G27: =G26-G25 -> 7.9347855
A28: Year 2 | B28: =D21 -> 1030000 | C28: =B28/(1+$G$26%)^2 -> 883635.13
A29: Year 3 | B29: =E21 -> 960600 | C29: =B29/(1+$G$26%)^3 -> 763301.65
A30: Year 4 | B30: =F21 -> 941812 | C30: =B30/(1+$G$26%)^4 -> 693163.54
A31: Year 5 | B31: =G21 -> 823648.24 | C31: =B31/(1+$G$26%)^5 -> 561475.93
A32: Subtotal: | C32: =SUM(C27:C31) -> 3827804.2
A33: Terminal Value = Year 5 FCF X (1+g) / (WACC-g) | B33: =(G21*(1+G25%))/(G26%-G25%) -> 10383335 | C33: =B33/(1+$G$26%)^5 -> 7078255.2
A34: Enterprise Value | C34: =C32+C33 -> 10906059

Sheet 06b_Sustainable Growth Rate
A1: 📘 1. Definition
A3: The sustainable growth rate is the rate at which a company can grow its earnings (or dividends) without changing its leverage and while maintaining a stable capital structure. It reflects growth that can be supported internally, given profitability and reinvestment.
A5: 📘 2. Formula in Market Practice
A7: The classic formula is:
A9: SGR=ROE×(1−Dividend Payout Ratio)
A11: Where:
A13: ROE = Return on Equity (Net Income ÷ Equity)
A15: Dividend Payout Ratio = Dividends ÷ Net Income
A17: Retention Ratio = (1 – Dividend Payout Ratio), i.e. the proportion of earnings reinvested.
A19: So:
A21: SGR=ROE×Retention Ratio
A23: 📘 3. How Analysts Derive It
... A59: excel
A61: =B2 * (1 - B3) -> 0
A63: Example: =0.20 * (1 - 0.40) → 0.12 (12%). | E63: used: | F63: 0.05 | G63: (5%)
A65: ✅ Bottom line: In market practice, the sustainable growth rate is derived from ROE × retention ratio, then cross‑checked against industry and macro benchmarks. For terminal value in SME valuations, it’s usually normalized to a conservative long‑term rate (≈3–5%), even if the raw formula suggests higher.
A67: In our example under 02_Normalization worksheet:
A69: Calculation of growth rate:
A70: ='02_Normalization'!A72 -> Net Income | B70: ='02_Normalization'!B72 -> 631324 | C70: ='02_Normalization'!C72 -> 65163 | D70: ='02_Normalization'!D72 -> 84172 | E70: ='02_Normalization'!E72 -> 108873 | F70: ='02_Normalization'!F72 -> 791952
A71: ='02_Normalization'!A73 -> Dividend paid | B71: ='02_Normalization'!B73 -> -373500 | C71: ='02_Normalization'!C73 -> 0 | D71: ='02_Normalization'!D73 -> 0 | E71: ='02_Normalization'!E73 -> -200000 | F71: ='02_Normalization'!F73 -> -200000
A72: ='02_Normalization'!A74 -> Dividend Payout Ratio | B72: ='02_Normalization'!B74 -> 0.59161381 | C72: ='02_Normalization'!C74 -> 0 | D72: ='02_Normalization'!D74 -> 0 | E72: ='02_Normalization'!E74 -> 1.8370027 | F72: ='02_Normalization'!F74 -> 0.25254056
A73: ='02_Normalization'!A75 -> Retention Ratio = (1-Dividend Payout Ratio) | B73: ='02_Normalization'!B75 -> 0.40838619 | C73: ='02_Normalization'!C75 -> 1 | D73: ='02_Normalization'!D75 -> 1 | E73: ='02_Normalization'!E75 -> -0.83700275 | F73: ='02_Normalization'!F75 -> 0.74745944
A74: ='02_Normalization'!A76 -> Return on Equity (ROE)=Net Income/Equity | B74: ='02_Normalization'!B76 -> 1.5421655 | C74: ='02_Normalization'!C76 -> 0.13731882 | D74: ='02_Normalization'!D76 -> 0.15065419 | E74: ='02_Normalization'!E76 -> 0.23284208 | F74: ='02_Normalization'!F76 -> 0.62876538
A75: ='02_Normalization'!A77 -> Sustainable Long term Growth Rate (ROE X Retention Ratio) | B75: ='02_Normalization'!B77 -> 0.62979908 | C75: ='02_Normalization'!C77 -> 0.13731882 | D75: ='02_Normalization'!D77 -> 0.15065419 | E75: ='02_Normalization'!E77 -> -0.19488946 | F75: ='02_Normalization'!F77 -> 0.46997662 | G75: ='02_Normalization'!G77 -> 0.23857185 | H75: ='02_Normalization'!H77 -> average
A76: ='02_Normalization'!A78 -> Total Capital/Equity (net worth) | B76: ='02_Normalization'!B78 -> 409375 | C76: ='02_Normalization'!C78 -> 474538 | D76: ='02_Normalization'!D78 -> 558710 | E76: ='02_Normalization'!E78 -> 467583 | F76: ='02_Normalization'!F78 -> 1259535
A79: Note
A80: Although the company’s historical sustainable growth averaged 24%, the terminal growth rate has been capped at 3% to align with Singapore’s long‑term economic growth expectations.
A82: Therefore, adopted SGR: | B82: =3% -> 0.03

Sheet 07_Income_Based_Capitalization
B3: Income Based - Capitalization Method
C5: Ref | D5: $ | E5: $
B7: Normalised Pre-Tax Earnings before depreciation and amortization (EBITDA) and government grants | E7: ='02_Normalization'!F41 -> 823257
B9: Estimated Capitalisation Rate (CAPM) | D9: =' 04_CAPM'!D20 -> 18.880139
B11: Preliminary Value of Business | E11: =E7/D9% -> 4360439.3
B13: Add Excess Assets (Fixed Deposit + Cash) | E13: ='02_Normalization'!Q17 -> 1099123
B15: Less Assets Shortages (Working Capital) | E15: 0
B17: Value of Business | E17: =E11+E13+E15 -> 5459562.3

Sheet 08_Market_Multiple
B1: Data obtained:
C4: Total Mkt Cap $ | D4: LB (obtained from SGX) | E4: Total debt | F4: Total Equity | G4: Total Equity Total Debts | H4: P/E ratio | I4: Dividend yield | J4: Sh price on 10 May 2022 | K4: Sh price on 31 Decc 2021 | L4: Percentage +ve drop/-ve increase | M4: Gross Revenue ($million) | N4: EBITDA | O4: Total Assets | P4: Free Cash Flow (FCF) | Q4: Price/Gross Revenue | R4: Price/EBITDA | S4: Price/Total Assests | T4: Price/FCF
A5: 1 | B5: ='16_DB-SGX_Loading'!B22 -> Audience | C5: ='16_DB-SGX_Loading'!C22 -> 60.492 | D5: ='16_DB-SGX_Loading'!D22 -> 0.08 | E5: ='16_DB-SGX_Loading'!E22 -> 0.028 | F5: ='16_DB-SGX_Loading'!F22 -> 23.269 | G5: ='16_DB-SGX_Loading'!G22 -> 23.297 | H5: ='16_DB-SGX_Loading'!H22 -> 13 | I5: ='16_DB-SGX_Loading'!I22 -> 5.77 | ... T5: ='16_DB-SGX_Loading'!T22 -> 13.63661
A6: 2 | B6: ='16_DB-SGX_Loading'!B23 -> Dezign Format | C6: ='16_DB-SGX_Loading'!C23 -> 38 | D6: ='16_DB-SGX_Loading'!D23 -> 1 | E6: ='16_DB-SGX_Loading'!E23 -> 2.391 | F6: ='16_DB-SGX_Loading'!F23 -> 11.078 | G6: ='16_DB-SGX_Loading'!G23 -> 13.469 | H6: ='16_DB-SGX_Loading'!H23 -> 19 | I6: ='16_DB-SGX_Loading'!I23 -> 0 | ... T6: ='16_DB-SGX_Loading'!T23 -> -5.8362771
A7: 3 | B7: ='16_DB-SGX_Loading'!B24 -> GKE | C7: ='16_DB-SGX_Loading'!C24 -> 64.395 | D7: ='16_DB-SGX_Loading'!D24 -> 0.28 | E7: ='16_DB-SGX_Loading'!E24 -> 53.123 | F7: ='16_DB-SGX_Loading'!F24 -> 100.13 | G7: ='16_DB-SGX_Loading'!G24 -> 153.253 | H7: ='16_DB-SGX_Loading'!H24 -> 7.5 | I7: ='16_DB-SGX_Loading'!I24 -> 5.33 | ... T7: ='16_DB-SGX_Loading'!T24 -> 4.3625093
A8: 4 | B8: ='16_DB-SGX_Loading'!B25 -> Hiap Tong | C8: ='16_DB-SGX_Loading'!C25 -> 35.545 | D8: ='16_DB-SGX_Loading'!D25 -> -0.04 | E8: ='16_DB-SGX_Loading'!E25 -> 52.646 | F8: ='16_DB-SGX_Loading'!F25 -> 99.907 | G8: ='16_DB-SGX_Loading'!G25 -> 152.553 | H8: ='16_DB-SGX_Loading'!H25 -> 11.2 | I8: ='16_DB-SGX_Loading'!I25 -> 0.89 | ... T8: ='16_DB-SGX_Loading'!T25 -> 1.7886977
A9: 5 | B9: ='16_DB-SGX_Loading'!B26 -> LS 2 Holdings | C9: ='16_DB-SGX_Loading'!C26 -> 14.8 | D9: ='16_DB-SGX_Loading'!D26 -> 4.11 | E9: ='16_DB-SGX_Loading'!E26 -> 2.562 | F9: ='16_DB-SGX_Loading'!F26 -> 23.807 | G9: ='16_DB-SGX_Loading'!G26 -> 26.369 | H9: ='16_DB-SGX_Loading'!H26 -> 4 | I9: ='16_DB-SGX_Loading'!I26 -> 0 | ... T9: ='16_DB-SGX_Loading'!T26 -> 2.4049399
A10: 6 | B10: ='16_DB-SGX_Loading'!B27 -> VCPlus | C10: ='16_DB-SGX_Loading'!C27 -> 17.012 | D10: ='16_DB-SGX_Loading'!D27 -> 0.69 | E10: ='16_DB-SGX_Loading'!E27 -> 0.17 | F10: ='16_DB-SGX_Loading'!F27 -> 0.626 | G10: ='16_DB-SGX_Loading'!G27 -> 0.796 | H10: ='16_DB-SGX_Loading'!H27 -> 0 | I10: ='16_DB-SGX_Loading'!I27 -> 0 | ... T10: ='16_DB-SGX_Loading'!T27 -> -12.256484
A11: 7 | B11: ='16_DB-SGX_Loading'!B28 -> ZICO Hldgs | C11: ='16_DB-SGX_Loading'!C28 -> 19.707 | D11: ='16_DB-SGX_Loading'!D28 -> 0.18 | E11: ='16_DB-SGX_Loading'!E28 -> 8.936 | F11: ='16_DB-SGX_Loading'!F28 -> 28.536 | G11: ='16_DB-SGX_Loading'!G28 -> 37.472 | H11: ='16_DB-SGX_Loading'!H28 -> 0 | I11: ='16_DB-SGX_Loading'!I28 -> 0 | ... T11: ='16_DB-SGX_Loading'!T28 -> -39.10119
A12: 8 | B12: ='16_DB-SGX_Loading'!B29 -> UnUsUaL | C12: ='16_DB-SGX_Loading'!C29 -> 25.553 | D12: ='16_DB-SGX_Loading'!D29 -> -0.38 | E12: ='16_DB-SGX_Loading'!E29 -> 1.826 | F12: ='16_DB-SGX_Loading'!F29 -> 27.989 | G12: ='16_DB-SGX_Loading'!G29 -> 29.815 | H12: ='16_DB-SGX_Loading'!H29 -> 0 | I12: ='16_DB-SGX_Loading'!I29 -> 0 | ... T12: ='16_DB-SGX_Loading'!T29 -> 5.843357
A13: 9 | B13: ='16_DB-SGX_Loading'!B30 -> Abundante | C13: ='16_DB-SGX_Loading'!C30 -> 15.26 | D13: ='16_DB-SGX_Loading'!D30 -> 0.3 | E13: ='16_DB-SGX_Loading'!E30 -> 0 | F13: ='16_DB-SGX_Loading'!F30 -> 18.64 | G13: ='16_DB-SGX_Loading'!G30 -> 18.64 | H13: ='16_DB-SGX_Loading'!H30 -> 0 | I13: ='16_DB-SGX_Loading'!I30 -> 0 | ... T13: ='16_DB-SGX_Loading'!T30 -> 60.772601
A14: 11 | B14: ='16_DB-SGX_Loading'!B32 -> Chasen | C14: ='16_DB-SGX_Loading'!C32 -> 29.45 | D14: ='16_DB-SGX_Loading'!D32 -> 0.28 | E14: ='16_DB-SGX_Loading'!E32 -> 100.704 | F14: ='16_DB-SGX_Loading'!F32 -> 82.205 | G14: ='16_DB-SGX_Loading'!G32 -> 182.909 | H14: ='16_DB-SGX_Loading'!H32 -> 0 | I14: ='16_DB-SGX_Loading'!I32 -> 0 | ... T14: ='16_DB-SGX_Loading'!T32 -> -0.5530828
B16: Note: The number of companies are extendable and not just limited to 11 companies. | P16: Min | Q16: =ABS(MIN(Q5:Q14)) -> 0.20611378 | R16: =ABS(MIN(R5:R14)) -> 7.4581324 | S16: =ABS(MIN(S5:S14)) -> 0.14332923 | T16: =ABS(MIN(T5:T14)) -> 39.10119
P17: Median | Q17: =ABS(MEDIAN(Q5:Q14)) -> 0.82843624 | R17: =ABS(MEDIAN(R5:R14)) -> 3.8522838 | S17: =ABS(MEDIAN(S5:S14)) -> 0.57449685 | T17: =ABS(MEDIAN(T5:T14)) -> 2.0968188
P18: ='03_Beta_Calculation'!S59 -> average | Q18: =ABS(AVERAGE(Q5:Q14)) -> 9.930221 | R18: =ABS(AVERAGE(R5:R14)) -> 5.0545446 | S18: =ABS(AVERAGE(S5:S14)) -> 1.8420294 | T18: =ABS(AVERAGE(T5:T14)) -> 3.1061679
P19: Max | Q19: =ABS(MAX(Q5:Q14)) -> 89.068063 | R19: =ABS(MAX(R5:R14)) -> 19.539052 | S19: =ABS(MAX(S5:S14)) -> 11.564922 | T19: =ABS(MAX(T5:T14)) -> 60.772601
B20: Valuation Multiple | C20: Minimum | D20: Median | E20: Average | F20: Maximum | G20: Median in Millions
B21: Price / Gross Revenue | C21: =Q16 -> 0.20611378 | D21: =Q17 -> 0.82843624 | E21: =Q18 -> 9.930221 | F21: =Q19 -> 89.068063 | G21: =D21 -> 0.82843624
B22: Price / EBITDA | C22: =R16 -> 7.4581324 | D22: =R17 -> 3.8522838 | E22: =R18 -> 5.0545446 | F22: =R19 -> 19.539052 | G22: =D22 -> 3.8522838
B23: Price / Total Assets | C23: =S16 -> 0.14332923 | D23: =S17 -> 0.57449685 | E23: =S18 -> 1.8420294 | F23: =S19 -> 11.564922 | G23: =D23 -> 0.57449685
B24: Price / Free Cash Flow | C24: =T16 -> 39.10119 | D24: =T17 -> 2.0968188 | E24: =T18 -> 3.1061679 | F24: =T19 -> 60.772601 | G24: =D24 -> 2.0968188
B27: Type of Value Estimate | C27: Basis | D27: Weighted Multiple (Using Median) | E27: Estimated Value
B28: Price / Gross Revenue | C28: =('02_Normalization'!G9) -> 0 | D28: =G21 -> 0.82843624 | E28: =C28*D28 -> 0
B29: Price / Free Cash Flow | C29: ='02_Normalization'!G65 -> 0 | D29: =G22 -> 3.8522838 | E29: =C29*D29 -> 0
B30: Price / EBITDA | C30: ='02_Normalization'!G40 -> 0 | D30: =G23 -> 0.57449685 | E30: =C30*D30 -> 0
B31: Price / Total Assets | C31: ='02_Normalization'!Q40 -> 6537967 | D31: =G24 -> 2.0968188 | E31: =C31*D31 -> 13708932
B33: Average | E33: =SUM(E28:E31)/4 -> 3427233

Sheet 09_Asset_Based
B3: Asset Based - Excess Earning Method
C5: Ref | D5: $
B6: Adjusted Discretionary Cash Flow @ 31/12/2021 | C6: a | E6: 416254
B7: Net Tangible Assets | D7: 2557459
B8: Multiply by:
B9: Rate of Return on Tangible Assets (WACC) % | D9: ='05_WACC'!E21 -> 7.9647855
B10: Earnings on Net Tangible Assets | C10: b | E10: =D7*D9% -> 203696.12
B12: Excess Earnings (a) – (b) | E12: =E6-E10 -> 212557.88 | F12: This represents the contribution of intangible assets
B13: Divided by:
B14: Capitalisation Rate on Intangible Assets (CAPM) % | D14: =' 04_CAPM'!D20 -> 18.880139
B16: Indicated Value of Intangible Assets | C16: d | E16: =E12/D14% -> 1125827.9
B17: Market Value of Net Tangible Assets | C17: e | E17: ='02_Normalization'!Q65 -> 2557459
B18: Value of Non-Operating Assets | E18: 0
B19: Assets Shortages: Working Capital Deficit | E19: 0
B21: Business Equity Value by Excess Earnings Method (d) + (e) | E21: =E16+E17+E18+E19 -> 3683286.9

Sheet 10_CSRP_Scoring
A1: Purpose: To systematically translate qualitative risks into a numerical CSRP, consistent with your book's Appendix C discussion.
A4: Worksheet Table Layout
A6: Risk Factor | B6: Description | C6: Severity (Select from dropdown) | D6: % Weight Applied | E6: Contribution to CSRP (%) | F6: Evidence / Notes
A7: Customer Concentration | B7: >20% of revenue from 1 client | C7: Moderate | D7: 0.5% / 1.5% / 2.5% | F7: Eg: Client A = 38% revenue
A8: Supplier Concentration | B8: Key supplier dependency | C8: N/A | D8: As above | E8: =IF(C8="Low",0.005,IF(C8="Moderate",0.015,IF(C8="High",0.025,0))) -> 0 | F8: (Insert explanation)
A9: Financial Leverage | B9: Debt > industry average | C9: N/A | D9: As above | E9: 1 | F9: (Insert explanation)
A10: Revenue Volatility | B10: Fluctuating sales trends | C10: N/A | D10: As above | E10: =IF(C10="Low",0.005,IF(C10="Moderate",0.015,IF(C10="High",0.025,0))) -> 0 | F10: (Insert explanation)
A11: Management Depth | B11: Reliance on owner / key person | C11: Moderate | D11: As above | E11: 0.4 | F11: Founder controls 90% of relationships
A12: Litigation / Regulatory Risk | B12: Pending disputes or compliance gaps | C12: Moderate | D12: As above | F12: Case ref / newspaper report
A13: Operational Efficiency | B13: Capability to scale or update systems | C13: N/A | D13: As above | E13: 1.5 | F13: Manpower
A14: Geographic / Market Risk | B14: Exposure to non-core regions | C14: N/A | D14: As above | E14: 1.5 | F14: Middle East conflict impacts on Singapore real estate industry
E15: =SUM(E7:E14) -> 4.4
A16: Add the following cells below the table:
A18: Cell Label | B18: Formula / Value | C18: Notes
A19: Total CSRP (before cap) | B19: =SUM(E8:E14) -> 4.4 | C19: Sums contributions
A20: CSRP Cap | B20: =B19 -> 4.4 | C20: You may set 5% default
A21: Final CSRP Applied | B21: =MIN(B19, B20) -> 4.4 | C21: caps the CSRP
A23: Important:
A24: Make cell C2:C9 a dropdown with options: Low, Moderate, High.
A26: Low
A27: Moderate
A28: High
A29: N/A

Sheet 11a_DLOC
A1: Discount for Lack of Control (DLOC)
A3: Concept
A5: DLOC adjusts value when moving from a control perspective (e.g., takeover premium) to a minority perspective. Formula is derived from control premiums observed in SGX takeover announcements.
A7: Example – SGX Takeover Premium
A9: Offer price: S$0.30
A11: Last traded price: S$0.215 → Premium = 39.5% | F11: 0.395
A13: 1‑month VWAP: S$0.213 → Premium = 40.8% | F13: 0.408
A15: 3‑month VWAP: S$0.219 → Premium = 37.0% | F15: 0.37
A17: 6‑month VWAP: S$0.225 → Premium = 33.3% | F17: 0.333
A19: 12‑month VWAP: S$0.234 → Premium = 28.2% | F19: 0.282
A21: Average premium = 35.76% | F21: =AVERAGE(F11:F19) -> 0.3576
A23: Formula
A27: Excel Implementation
A29: If the average premium is in cell F21 (e.g., 0.3576):
B32: =1 - (1/(1+F21)) | D32: =1 - (1 / (1 + F21)) -> 0.26340601
A35: Result: 0.26 → 26% DLOC

Sheet 11b_DLOM
A1: 2. Discount for Lack of Marketability (DLOM)
A3: Concept
A5: DLOM reflects the illiquidity of private shares compared to listed shares. We benchmark against SGX private placements, preferential offerings, and pre‑IPO cases.
A7: Example – CapitaLand Ascendas REIT Preferential Offering
A9: Preferential price: S$2.35 | D9: 2.35
A11: VWAP: S$2.5126 | D11: 2.5126
A13: Discount = (2.35 – 2.5126) ÷ 2.5126 = –6.5% → 6.5% discount
A15: Formula
A21: DLOM=Offering Price−Reference Market PriceReference Market Price
A23: Excel Implementation
A25: If offering price is in B2 and market price in B3:
A27: excel | B27: =ABS((B2 - B3) / B3)
B29: = | C29: =ABS((D9 - D11) / D11) -> 0.064713842
A31: Result: 0.065 → 6.5% discount
A33: 3. Floors & Caps Application
A35: Concept
A37: Observed discounts can be too low (e.g., 2.9% for FCT). To ensure defensibility, we apply:
A39: Floor = 15%
A41: Cap = 35%
A43: Excel Implementation
A45: If raw discount is in C2:
A47: excel | B47: =MIN(MAX(C29, 0.15), 0.35)
C49: = | D49: =MIN(MAX(C29, 0.15), 0.35) -> 0.15
A51: This ensures the applied DLOM is always between 15% and 35%.
A53: 4. Worked Examples in Excel
A55: Case | B55: Offering Price | C55: Market Price | D55: Raw Discount Formula | E55: Raw Discount | F55: Applied DLOM
A56: FCT (REIT placement) | B56: 2.18 | C56: 2.2446 | D56: =(B56-C56)/C56 -> -0.028780184 | E56: –2.9% | F56: 0.15
A57: VOM (Catalist SME) | B57: 0.0801 | C57: 0.08762 | D57: =(B57-C57)/C57 -> -0.085825154 | E57: –8.6% | F57: 0.15
A58: Info‑Tech (Pre‑IPO) | B58: 0.7 | C58: 0.87 | D58: =(B58-C58)/C58 -> -0.1954023 | E58: –19.5% | F58: 0.195
A59: CLAR (Preferential) | B59: 2.35 | C59: 2.5126 | D59: =(B59-C59)/C59 -> -0.064713842 | E59: –6.5% | F59: 0.15

Sheet 12_Valuation Summary
A2: Valuation Summary (FMV vs FV)
A4: Section A: Inputs (Consumes)
A6: Label | B6: Value
A7: Company Name | B7: ='14_Case Study_Gamma'!B3 -> Gamma Spore Pte Ltd
A8: Valuation Date | B8: =TODAY() -> 46154
A9: Prepared By | B9: ="Isaac PC Wong, FCA (Singapore)" -> Isaac PC Wong, FCA (Singapore)
A11: Item | B11: Cell Formula Example
A12: Shares Outstanding | B12: ='01_Inputs'!E21 -> 500000
A13: Risk-Free Rate (Rf) | B13: ='01_Inputs'!E11 -> 2.22 | C13: Same
A14: ERP | B14: ='01_Inputs'!E12 -> 4.65 | C14: Same
A15: Re-levered Beta | B15: ='01_Inputs'!E14 -> 1.3462115 | C15: Same or adjusted
A16: IRP | B16: ='01_Inputs'!E15 -> 1.6098834 | C16: Same or adjusted
A17: SCP | B17: ='01_Inputs'!E16 -> 6.0302554 | C17: May be excluded
A18: CSRP | B18: ='01_Inputs'!E17 -> 4.4 | C18: May be reduced
A19: WACC | B19: ='01_Inputs'!E18 -> 7.9647855 | C19: May be lower for strategic buyer
A20: DLOC | B20: ='01_Inputs'!E20 -> 0.26340601
A21: DLOM | B21: ='01_Inputs'!E19 -> 0.15
A22: Cost of Equity | B22: =' 04_CAPM'!D16 -> 18.910139
A24: Section B: Valuation Methods (Produces)
A26: Method | B26: FMV Formula Example | C26: FV Formula Example
A27: Asset-Based | B27: ='09_Asset_Based'!E21 -> 3683286.9 | C27: ='09_Asset_Based'!E21 -> 3683286.9
A28: Income-Based (DCF) | B28: ='06_Income_Based DCF'!C32 -> 3827804.2 | C28: ='06_Income_Based DCF'!C34 -> 10906059
A29: Income-Based (Cap) | B29: ='07_Income_Based_Capitalization'!E17 -> 5459562.3 | C29: ='07_Income_Based_Capitalization'!E17 -> 5459562.3
A30: Market Multiple | B30: ='08_Market_Multiple'!E33 -> 3427233 | C30: ='08_Market_Multiple'!E33 -> 3427233
A32: Section C: Equity Value Calculation
A34: Step | B34: FMV Formula Example | C34: FV Formula Example
A35: Enterprise Value (EV) | B35: =AVERAGE(B27:B30) -> 4099471.6 | C35: =AVERAGE(C27:C30) -> 5869035.4
A36: Less: Net Debt (collateral is the Industrial Property) | B36: =('02_Normalization'!P59+'02_Normalization'!P48+'02_Normalization'!P46-'02_Normalization'!P17) -> 3475040 | C36: =('02_Normalization'!P59+'02_Normalization'!P48+'02_Normalization'!P46-'02_Normalization'!P17) -> 3475040
A37: Equity Value | B37: =B35-B36 -> 624431.61 | C37: =C35-C36 -> 2393995.4
A38: Per Share Value | B38: =B37/B12 -> 1.2488632 | C38: =C37/B12 -> 4.7879908
A39: Apply DLOC | B39: =B38*(1-B20) -> 0.91990514 | C39: Usually skipped
A40: Apply DLOM | B40: =B39*(1-B21) -> 0.78191937 | C40: Usually skipped
A41: Final Value | B41: =B40 -> 0.78191937 | C41: =C38 -> 4.7879908

Sheet 13_Report_Template
A1: Executive Summary (Updated Draft)
A3: 1. Purpose of Valuation
A5: This valuation estimates both the Fair Market Value (FMV) and Fair Value (FV) of Gamma Spore Pte Ltd as of 31 December 20XX, using asset-based, income-based (DCF and capitalization), and market multiple approaches.
A7: 2. Key Assumptions
A9: Risk-Free Rate (Rf): 3.2% (MAS 10Y benchmark) | B9: ='01_Inputs'!E11 -> 2.22
A11: Equity Risk Premium (ERP): 5.5% | B11: ='01_Inputs'!E12 -> 4.65
A13: Re-levered Beta (βR): 3.29 | B13: ='01_Inputs'!E14 -> 1.3462115
A15: Cost of Equity (Re): 22.37% | B15: ='12_Valuation Summary'!B22 -> 18.910139
A17: Weighted Average Cost of Capital (WACC): 8.97% | B17: ='01_Inputs'!E18 -> 7.9647855
A19: Terminal Growth Rate (g): 2.5% | B19: ='06_Income_Based DCF'!G25 -> 0.03
A21: Corporate Tax Rate: 17% | B21: ='01_Inputs'!E13 -> 0.17
A23: Shares Outstanding: 500,000 | B23: ='12_Valuation Summary'!B12 -> 500000
A25: Discounts:
A27: DLOC (Discount for Lack of Control): 15% | B27: ='01_Inputs'!E20 -> 0.26340601
A29: DLOM (Discount for Lack of Marketability): 30% (floor/cap applied) | B29: ='01_Inputs'!E19 -> 0.15
A31: 3. Valuation Approaches
A33: Method | B33: FMV Result (S$) | C33: FV Result (S$) | D33: Notes
A34: Asset-Based | B34: ='12_Valuation Summary'!B27 -> 3683286.9 | C34: ='12_Valuation Summary'!C27 -> 3683286.9 | D34: Adjusted net assets
A35: Income-Based (DCF) | B35: ='12_Valuation Summary'!B28 -> 3827804.2 | C35: ='12_Valuation Summary'!C28 -> 10906059 | D35: FV uses lower WACC / higher growth
A36: Income-Based (Cap) | B36: ='12_Valuation Summary'!B29 -> 5459562.3 | C36: ='12_Valuation Summary'!C29 -> 5459562.3 | D36: FV uses adjusted earnings
A37: Market Multiple | B37: ='12_Valuation Summary'!B30 -> 3427233 | C37: ='12_Valuation Summary'!C30 -> 3427233 | D37: FV applies premium multiples
A39: Average per share | B39: =AVERAGE(B34:B37)/B23 -> 8.1989432 | C39: =AVERAGE(C34:C37)/B23 -> 11.738071
A40: 4. Adjustments
A42: FMV:
A44: Apply DLOC (15%) → reduces per-share value | B44: ='12_Valuation Summary'!B39 -> 0.91990514
A46: Apply DLOM (30%) → further reduces per-share value | B46: ='12_Valuation Summary'!B40 -> 0.78191937
A48: Produces Minority, Illiquid Value | B48: =B46 -> 0.78191937
A50: FV:
A52: No DLOC/DLOM applied (control/strategic context) | B52: 0
A54: Produces Strategic Control Value | B54: ='12_Valuation Summary'!C41 -> 4.7879908
A56: 5. Final Conclusion
A58: Fair Market Value (FMV): Equity Value ≈ S$4.0m → Per Share ≈ S$8.00 After DLOC (15%) and DLOM (30%) → ≈ S$4.76 per share
A60: Fair Value (FV): Equity Value ≈ S$4.4m → Per Share ≈ S$8.80 No discounts applied → ≈ S$8.80 per share
A62: 6. Narrative Wrap-Up
A64: “Based on the application of asset-based, income-based, and market multiple approaches, the indicated Fair Market Value of Gamma Spore Pte Ltd’s minority, illiquid shares is approximately S$4.76 per share. Under a Fair Value context, assuming strategic buyer synergies and control, the indicated value is approximately S$8.80 per share. These results reflect the different consumes (assumptions and discounts) and produces (outputs) inherent in FMV versus FV frameworks.”

Sheet 14_Case Study_Gamma
A3: Target Co: | B3: Gamma Spore Pte Ltd
A4: Incorporated: | B4: 20th Sep 2011
A5: Share Cap @ $1.00 per share: | B5: 500000
A6: Shareholder: | B6: 1. Ong Huat Huat (65 years old) 150,000 shares
B7: 2. Bao Heng Heng (Not related to OHH, 55 years old) 350,000 shares
A8: Director: | B8: 1. Ong Huat Huat
B9: 2. Tiam Ai Kun (Non-executive)
A10: Accounting Period: | B10: 31st December 20XX
A11: Principal Activities: | B11: Event & Concert Organizers
A12: Company History : | B12: 12 Years history and was established and operated under the same ownership for the entire history
A13: Customer based: | B13: 60% (<12 Customers) of the customers are new and non recurring. About 20% are old customers (only 2 recurring which accounts for 25% of the total revenue) and have been with the company for more than 5 years brought in by Ong Huat Huat.
A14: Employee: | B14: 3 employees, One Office Secretary and the other 2 are involved in managing the operations.
A16: Strength:
A17: Weakness:
A18: Opportunity:
A19: Threats:
A21: Other information: | B21: During the year 2020, the company had secured a term loan of about $3.32 million to finance the purchase of an industrial leasehold property with a useful life of 37 years. The interest rate of 4% pa will be applied from the second year (year 2023) and thereafter.

Sheet 15_DB_SGX_Industry
A1: Entities | B1: Active, Non-active or Suspended | C1: Mainboard (m) or Catalyst ( c ) | D1: Industry | E1: SICC Sub-industry | F1: (Profile) | G1: Currency | H1: Code | I1: Market Cap | K1: remarks
A2: 17LIVE GROUP | B2: a | C2: m | D2: Technology | E2: Software application | F2: Live streaming | G2: USD | H2: LVR
A3: 8Telecom | B3: S | C3: c | D3: Suspended | E3: Suspended | F3: telecom infrastructure | G3: - | H3: AZG
A4: 9R | B4: a | C4: c | D4: Technology | E4: Computer Hardware | F4: Supply chain management | G4: SGD | H4: 1Y1
A5: ABR | B5: a | C5: m | D5: Consumer-Cyclical | E5: Restaurants | F5: F&B | G5: SGD | H5: 533 | K5: Swensen ice cream
A6: Abundance Intl | B6: a | C6: c | D6: Basic Materials | E6: Chemical | F6: Print & Paper Management | G6: SGD | H6: 541
A7: Abundante | B7: a | C7: m | D7: Industrials | E7: Rental & leasing services | F7: Supplier of concrete pumping services & CCTV of sewer inspection services | G7: SGD | H7: 570 | I7: 17.3 | J7: 1
A8: Accrelist Ltd | B8: a | C8: c | D8: Healthcare | E8: Medical care facilities | F8: Supply chain management | G8: SGD | H8: QZG
A9: Acesian Partners | B9: a | C9: c | D9: Industrials | E9: Specialty Industrial Machinery | F9: Environment Solutions | G9: SGD | H9: 5FW | K9: incl waste management
A10: Acma | B10: a | C10: m | D10: Consumer-Cyclical | E10: Auto Parts | F10: Plastic Injection Moulding | G10: SGD | H10: AYV
A11: AcroMeta | B11: a | C11: c | D11: Industrials | E11: Engineering & Constructions | F11: Environment Solutions | G11: SGD | H11: 43F
A12: Addvalue Tech | B12: a | C12: m | D12: Technology | E12: Communication equipments | F12: Satellite Communications | G12: USD | H12: A31
A13: Advanced | B13: a | C13: c | D13: Energy | E13: Oil & Gas Equipment & Services | F13: Oil & Gas | G13: SGD | H13: BLZ
A14: AdvancedSystems | B14: a | C14: c | D14: Technology | E14: Semiconductor Equipment & Materials | F14: Semiconductor | G14: SGD | H14: WJ9
A15: Advancer Global | B15: a | C15: c | D15: Industrials | E15: Staffing & Employment Services | F15: Facilities Management, Workforce management | G15: SGD | H15: 43Q
A16: Adventus | B16: a | C16: c | D16: Industrials | E16: Conglomerates | F16: Property & Hospitality | G16: SGD | H16: 5EF
A17: Aedge Group | B17: a | C17: c | D17: Industrials | E17: Security & Protection Services | F17: Security & Protection Services | G17: SGD | H17: XVG
A18: AEM SGD | B18: a | C18: m | D18: Technology | E18: Semiconductor Equipment & Materials | F18: Semiconductor | G18: SGD | H18: AWX
A19: AEM USD | B19: a | C19: m | D19: Technology | E19: Semiconductor Equipment & Materials | F19: Semiconductor | G19: SGD | H19: XWA
A20: AF Global | B20: a | C20: m | D20: Consumer-Cyclical | E20: Lodging | F20: Hospitality | G20: SGD | H20: L38
A21: AJJ Medtech | B21: a | C21: c | D21: Healthcare | E21: Medical devices | F21: Healthcare | G21: SGD | H21: 584
A22: Alita Resources | B22: S | C22: c | D22: Suspended | E22: Suspended | F22: Suspended | G22: SGD | H22: 40F
A23: Alliance HC | B23: a | C23: c | D23: Healthcare | E23: Medical care facilities | F23: Healthcare | G23: SGD | H23: MIJ
A24: AlphaDX | B24: S | C24: c | D24: Suspended | E24: Suspended | F24: Suspended | G24: SGD | H24: -
A25: Alpina Holdings | B25: a | C25: c | D25: Industrials | E25: Engineering & Construction | F25: Engineering & Construction | G25: SGD | H25: ZXY
A26: Alset | B26: n | C26: c | D26: Investment Holdings | E26: Real Estate - Development | F26: Real Estate, Investment, F&B,Biomedical | G26: SGD | H26: 40V
A27: Amcorp Global | B27: a | C27: m | D27: Real Estate | E27: Real Estate - Development | F27: Property Development | G27: SGD | H27: S9B | I27: 44.29 | J27: 1
A28: Amara Holdings | B28: n | C28: m | D28: Non Active | E28: Non Active | F28: Hotel & convention facilities for corporate events and banquets | G28: - | H28: - | I28: 0
A29: AMOS Group | B29: a | C29: m | D29: Energy | E29: Oil & Gas Equipment & Services | F29: Oil & Gas | G29: SGD | H29: 49B
A30: Amplefield Ltd | B30: a | C30: c | D30: Real Estate | E30: Real Estate - Diversified | F30: Investment Properties | G30: SGD | H30: AOF
A31: Asian Pay TV Tr | B31: a | C31: m | D31: Communication Services | E31: Entertainment | F31: Entertainment | G31: SGD | H31: S7OU
A32: AMTD IDEA OV | B32: a | C32: m | D32: Financial Services | E32: Asset Management | F32: Asset Management | G32: USD | H32: HKB
A33: AnAn Intl | B33: a | C33: m | D33: Energy | E33: Oil & Gas Refining & Marketing | F33: Oil & Gas | G33: USD | H33: Y35
A34: Anchun Intl | B34: a | C34: m | D34: Basic Materials | E34: Chemicals | G34: CNY | H34: BTX
A35: AnnAik | B35: a | C35: c | D35: Basic Materials | E35: Steel | G35: SGD | H35: A52
A36: Annica | B36: a | C36: c | D36: Energy | E36: Oil & Gas Equipment & Services | G36: SGD | H36: 5AL
A37: Aoxin Q & M | B37: a | C37: c | D37: Healthcare | E37: Medical care facilities | G37: CNY | H37: 1D4
A38: AP Oil | B38: a | C38: m | D38: Energy | E38: Oil & Gas Refining & Marketing | G38: SGD | H38: 5AU
A39: AP Strategic | B39: a | C39: m | D39: Consumer-Cyclical | E39: Lodging | F39: Hospitality | G39: SGD | H39: 5RA
A40: APAC Realty | B40: a | C40: c | D40: Real Estate | E40: Real Estate - Services | F40: Real estate brokerage | G40: SGD | H40: CLN | I40: 1
A41: Ascent Bridge | B41: a | C41: m | D41: Basic Materials | E41: Aluminium | G41: SGD | H41: AWG
A42: Asia Enterprises | B42: a | C42: m | D42: Basic Materials | E42: Steel | G42: SGD | H42: A55
A43: Asia Vets | B43: a | C43: c | D43: Healthcare | E43: Medical care facilities | G43: SGD | H43: 5RE
A44: AsiaMedic | B44: a | C44: c | D44: Healthcare | E44: Diagnostics & Research | G44: SGD | H44: 505
A45: Asian Micro | B45: a | C45: c | D45: Energy | E45: Oil & Gas Midstream | G45: SGD | H45: 585
A46: AsiaPhos | B46: a | C46: c | D46: Basic Materials | E46: Other industrial metals & mining | G46: SGD | H46: 5WV
A47: Asiatic | B47: a | C47: c | D47: Utilities | E47: Utilities - Independent Power Producers | G47: SGD | H47: 5CR
A48: ASL Marine | B48: a | C48: m | D48: Industrials | E48: Aerospace & Defense | G48: SGD | H48: A04
A49: A-Smart | B49: a | C49: m | D49: Industrials | E49: Specialty Business Services | F49: (a) Property development and real estate investment; and (b) Smart technologies; and (c) Print and media; and (d) Other investments. | G49: SGD | H49: BQC | I49: 29.78 | J49: 1
A50: A-Sonic Aero | B50: a | C50: m | D50: Industrials | E50: Integrated Freight & Logistics | F50: Sale and purchase of aircraft components; and Logistics (relating to supply chain management services and logistic solutions, including international and domestic multi-modal transportation, warehousing, distribution, customs clearance, and air cargo handling services). | G50: USD | H50: BTJ | J50: 1
A51: Aspen | B51: a | C51: m | D51: Real Estate | E51: Real Estate - Development | F51: Property Development | G51: MYR | H51: 1F3 | I51: 39 | J51: 1
A52: Aspial Corp | B52: a | C52: m | D52: Consumer-Cyclical | E52: Luxury Goods | G52: SGD | H52: A30
A53: Aspial Lifestyle | B53: a | C53: c | D53: Consumer-Cyclical | E53: Luxury Goods | G53: SGD | H53: 5UF
A54: Assurance HC | B54: a | C54: c | D54: Technology | E54: Information Technology Services | G54: SGD | H54: RCU
A55: Astaka | B55: a | C55: c | D55: Real Estate | E55: Real Estate - Development | F55: Property Development | G55: MYR | H55: 42S | I55: 82.26 | J55: 1
A56: ASTI | B56: S | C56: c | D56: Technology | E56: Semiconductor Equipment & Materials | G56: SGD | H56: 575
A57: Atlantic Nav | B57: a | C57: c | D57: Industrials | E57: Marine Shipping | G57: USD | H57: 5UL
A58: Attika Group | B58: a | C58: c | D58: Industrials | E58: Engineering & Construction | G58: SGD | H58: 53W
A59: Audience | B59: a | C59: c | D59: Industrials | E59: Consulting Services | F59: (i) conducting business impact assessments on companies and organising business recognition awards, (ii) organising trade and consumer exhibitions, and (iii) offering digital and print business media brands and organising networking events and conferences | G59: SGD | H59: 1AZ | I59: 58.17 | J59: 1
A60: AusGroup | B60: S | C60: c | D60: Industrials | E60: Engineering & Construction | G60: AUD | H60: 5GJ
A61: Avarga Ltd | B61: a | C61: m | D61: Industrials | E61: Industrial Distribution | G61: SGD | H61: X5N
A62: Avi-Tech Hldg | B62: a | C62: m | D62: Technology | E62: Semiconductor Equipment & Materials | G62: SGD | H62: 1R6
A63: Azeus | B63: a | C63: m | D63: Technology | E63: Information Technology Services | G63: HKD | H63: BBW
A64: Aztech Gbl | B64: a | C64: m | D64: Technology | E64: Electronic Components | G64: SGD | H64: 8AZ
A65: Autagco | B65: a | C65: c | D65: Consumer-Cyclical | E65: Restaurants | G65: SGD | H65: 1D3
A66: B&M Hldg | B66: a | C66: m | D66: Financial Services | E66: Asset Management | G66: SGD | H66: CJN
A67: BACUI TECH | B67: a | C67: c | D67: Communication Services | E67: Publishing | G67: SGD | H67: YYB
A68: Baker Technology | B68: a | C68: m | D68: Energy | E68: Oil & Gas Equipment & Services | G68: SGD | H68: BTP
A69: Banyan Tree | B69: a | C69: m | D69: Consumer-Cyclical | E69: Resorts & Casinos | G69: SGD | H69: B58
A70: BBR | B70: a | C70: m | D70: Industrials | E70: Engineering & Construction | G70: SGD | H70: KJ5
A71: Beng Kuang | B71: a | C71: m | D71: Energy | E71: Oil & Gas Equipment & Services | G71: SGD | H71: BEZ
... A75: Boldtek | B75: S | C75: c | D75: Suspended | E75: Suspended | G75: - | H75: -
A76: Bonvests | B76: a | C76: m | D76: Consumer-Cyclical | E76: Lodging | F76: Hospitality | G76: SGD | H76: B28
A77: Boustead | B77: a | C77: m | D77: Industrials | E77: Conglomerates | G77: SGD | H77: F9D
A78: BRC Asia | B78: a | C78: m | D78: Basic Materials | E78: Steel | G78: SGD | H78: BEC
A79: Broadway Ind | B79: a | C79: m | D79: Technology | E79: Computer Hardware | G79: SGD | H79: B69
A80: Bromat | B80: a | C80: c | D80: Consumer-Cyclical | E80: Restaurants | G80: SGD | H80: 9I7
A81: Brook Crompton | B81: a | C81: m | D81: Industrials | E81: Electrical Equipment & Parts | G81: SGD | H81: AWC
A82: Bukit Sembawang | B82: a | C82: m | D82: Real Estate | E82: Real Estate - Development | F82: Property Development & Investment | G82: SGD | H82: B61 | I82: 1260 | J82: 1
A83: Bumitama Agri | B83: a | C83: m | D83: Consumer Defensive | E83: Farm Products | G83: IDR | H83: P8Z
A84: Bund Center | B84: a | C84: m | D84: Real Estate | E84: Real Estate Services | F84: Investment Properties | G84: SGD | H84: BTE | I84: 314.89 | J84: 1
A85: Camsing Hc | B85: a | C85: m | D85: Consumer Defensive | E85: Food Distribution | G85: SGD | H85: BAC
A86: CapAllianz | B86: a | C86: c | D86: Energy | E86: Oil & Gas E&P | G86: USD | H86: 594
A87: Capital World | B87: a | C87: c | D87: Real Estate | E87: Real Estate - Development | F87: Marble material | G87: MYR | H87: 1D5 | I87: 16.1 | J87: 1
B88: a | C88: m | D88: Real Estate, Real Estate services | E88: Financial & Insurance activities | F88: REIT - Hospitality assets supporting MICE tourism | G88: SGD | H88: 9CI | I88: 15010
A89: Captii | B89: a | C89: m | D89: Communication Services | E89: Telecom Services | G89: SGD | H89: AWV
A90: Casa | B90: a | C90: m | D90: Consumer-Cyclical | E90: Furnishings, Fixture & Applicances | G90: SGD | H90: C04
A91: CDW | B91: a | C91: m | D91: Technology | E91: Semiconductor Equipment & Materials | G91: SGD | H91: BXE
A92: Centurion | B92: a | C92: m | D92: Consumer-Cyclical | E92: Lodging | F92: Hospitality | G92: SGD | H92: OU8
A93: CFM | B93: a | C93: c | D93: Industrials | E93: Metal Fabrication | G93: SGD | H93: 5EB
A94: CH Offshore | B94: a | C94: m | D94: Energy | E94: Oil & Gas Equipment & Services | G94: USD | H94: C13
A95: CharismaEnergy | B95: S | C95: c | D95: Suspended | E95: Suspended | G95: - | H95: -
A96: Chasen | B96: a | C96: m | D96: Industrials | E96: Integrated Freight & Logistics | F96: Specialist Relocation, Third Party Logistics, Technical & Engineering | G96: SGD | H96: 5NV | I96: 31.36 | J96: 1
A97: Chemical Ind | B97: a | C97: m | D97: Basic Materials | E97: Chemicals | G97: SGD | H97: C05
A98: China Aviation | B98: a | C98: m | D98: Energy | E98: Oil & Gas Refining & Marketing | G98: USD | H98: G92
A99: China EnvRes | B99: a | C99: m | D99: Consumer-Cyclical | E99: Auto & Truck Dealerships | G99: HKD | H99: UIX
A100: China Everbright | B100: a | C100: m | D100: Utilities | E100: Utilities - Regulated Water | G100: HKD | H100: U9E
A101: China Fishery | B101: S | C101: m | D101: Suspended | E101: Suspended | G101: - | H101: -
A102: China Intl | B102: a | C102: m | D102: Utilities | E102: Utilities - Regulated Water | G102: CNY | H102: BEH
A103: China Mining | B103: a | C103: m | D103: Consumer Defensive | E103: Farm Products | G103: CNY | H103: BHD
...

Sheet 16_DB-SGX_Loading
B2: Peer Group Criteria | E2: Classification | G2: Use Case | I2: Notes
B3: Mainboard > USD 300m market cap | E3: Industry Peers | G3: Benchmark for beta, IRP | I3: Default classification
B4: Mainboard < USD 300m market cap OR Catalyst stocks | E4: Small-Size Peers | G4: Apply SCP adjustments | I4: Default classification
B5: If most industry peers >$1000 million market cap | E5: Remaining peers <$1000 million → small-size peers | G5: Apply SCP adjustments | I5: override rule for Industry-wide scaling
B7: Note: Always check market cap classification before computing risk premium
B9: Yahoo/SGX data with 5Y-Beta (in Million) | C9: Total Mkt Cap $m | D9: LB (obtained from SGX) | E9: Total debt | F9: Total Equity | G9: Total Equity + Total Debts | H9: P/E ratio | I9: Average 5Y Dividend yield (%) | J9: Sh price on 2 Apr 2026 | K9: Sh price on 31 Decc 2025 | L9: Percentage +ve drop/-ve increase (%) | M9: Gross Revenue ($million) | N9: EBITDA | O9: Total Assets | P9: Free Cash Flow (FCF) | Q9: Price/Gross Revenue | R9: Price/EBITDA | S9: Price/Total Assests | T9: Price/FCF | U9: Financial Year Ending | V9: mainboard (m) or catalyst (c) | W9: Stk code
A10: 1 | B10: ='16b_Loading by main or catalyst'!A8 -> COSCO SHP SG | C10: 510.548 | D10: 0.71 | E10: 93.583 | F10: 781.083 | G10: =E10+F10 -> 874.666 | H10: 0 | I10: 0.78 | J10: 0.114 | K10: 0.121 | L10: =(J10-K10)/K10% -> -5.785124 | M10: 193.999 | N10: 61.285 | O10: 980.308 | P10: 33.245 | Q10: =C10/M10 -> 2.6317043 | R10: =C10/N10 -> 8.3307171 | S10: =C10/O10 -> 0.52080367 | T10: =C10/P10 -> 15.357136 | U10: 46022 | V10: m | W10: ='16b_Loading by main or catalyst'!H8 -> F83
A11: 2 | B11: ='16b_Loading by main or catalyst'!A36 -> SATS | C11: 5321 | D11: 0.52 | E11: 1843 | F11: 2768.9 | G11: =E11+F11 -> 4611.9 | H11: 19.89 | I11: 1.54 | J11: 3.58 | K11: 3.81 | L11: =(J11-K11)/K11% -> -6.0367454 | M11: 5821 | N11: 1166 | O11: 8882 | P11: 669.4 | Q11: =C11/M11 -> 0.91410411 | R11: =C11/N11 -> 4.5634648 | S11: =C11/O11 -> 0.59907678 | T11: =C11/P11 -> 7.9489095 | U11: 45747 | V11: m | W11: S58
A12: 3 | B12: ='16b_Loading by main or catalyst'!A37 -> SIA | C12: 20973 | D12: 0.5 | E12: 12914.3 | F12: 16070 | G12: =E12+F12 -> 28984.3 | H12: 17.5 | I12: 5.26 | J12: 6.65 | K12: 6.4 | L12: =(J12-K12)/K12% -> 3.90625 | M12: 19539.8 | N12: 5711.9 | O12: 43086.8 | P12: 2834 | Q12: =C12/M12 -> 1.0733477 | R12: =C12/N12 -> 3.671808 | S12: =C12/O12 -> 0.48676161 | T12: =C12/P12 -> 7.400494 | U12: 45747 | V12: m | W12: C6L
A13: 4 | B13: ='16b_Loading by main or catalyst'!A38 -> SIA Engineering | C13: 3651 | D13: 0.32 | E13: 85.199 | F13: 1741.611 | G13: =E13+F13 -> 1826.81 | H13: 23.29 | I13: 2.91 | J13: 3.26 | K13: 3.6 | L13: =(J13-K13)/K13% -> -9.4444444 | M13: 1245 | N13: 214.881 | O13: 2141.393 | P13: 102.603 | Q13: =C13/M13 -> 2.9325301 | R13: =C13/N13 -> 16.9908 | S13: =C13/O13 -> 1.7049649 | T13: =C13/P13 -> 35.583755 | U13: 45747 | V13: m | W13: S59
A14: 5 | B14: ='16b_Loading by main or catalyst'!A19 -> SingPost | C14: 776.687 | D14: 0.21 | E14: 370.232 | F14: 1607.478 | G14: =E14+F14 -> 1977.71 | H14: 3.14 | I14: 1.22 | J14: 0.345 | K14: 0.405 | L14: =(J14-K14)/K14% -> -14.814815 | M14: 813.704 | N14: 387.25 | O14: 2390.424 | P14: 26.671 | Q14: =C14/M14 -> 0.95450803 | R14: =C14/N14 -> 2.0056475 | S14: =C14/O14 -> 0.324916 | T14: =C14/P14 -> 29.12103 | U14: 45747 | V14: m | W14: S08
A15: 6 | B15: ='16b_Loading by main or catalyst'!A24 -> Wing Tai | C15: 1222 | D15: 0.23 | E15: 1242.121 | F15: 2902.956 | G15: =E15+F15 -> 4145.077 | H15: 0 | I15: 1.88 | J15: 1.6 | K15: 1.42 | L15: =(J15-K15)/K15% -> 12.676056 | M15: 230.206 | N15: -4.157 | O15: 4275.552 | P15: -447.444 | Q15: =C15/M15 -> 5.3082891 | R15: =C15/N15 -> -293.96199 | S15: =C15/O15 -> 0.28581105 | T15: =C15/P15 -> -2.731068 | U15: 45838 | V15: m | W15: ='16b_Loading by main or catalyst'!H24 -> W05
A16: 7 | B16: ='16b_Loading by main or catalyst'!A26 -> CapitaLandInvest | C16: 13679 | D16: 0.61 | E16: 8462 | F16: 13524 | G16: =E16+F16 -> 21986 | H16: 91.33 | I16: 4.38 | J16: 2.74 | K16: 2.71 | L16: =(J16-K16)/K16% -> 1.1070111 | M16: 2133 | N16: 735 | O16: 24211 | P16: 479 | Q16: =C16/M16 -> 6.4130333 | R16: =C16/N16 -> 18.610884 | S16: =C16/O16 -> 0.56499112 | T16: =C16/P16 -> 28.557411 | U16: 46022 | V16: m | W16: 9CI
A17: 8 | B17: ='16b_Loading by main or catalyst'!A27 -> ComfortDelGro | C17: 3120 | D17: 0.24 | E17: 1821.5 | F17: 2980.7 | G17: =E17+F17 -> 4802.2 | H17: 13.09 | I17: 5.9 | J17: 1.44 | K17: 1.48 | L17: =(J17-K17)/K17% -> -2.7027027 | M17: 5058 | N17: 793.8 | O17: 6138.9 | P17: -136.5 | Q17: =C17/M17 -> 0.6168446 | R17: =C17/N17 -> 3.9304611 | S17: =C17/O17 -> 0.50823437 | T17: =C17/P17 -> -22.857143 | U17: 46022 | V17: m | W17: C52
A18: 9 | B18: ='16b_Loading by main or catalyst'!A29 -> Frasers Property | C18: 3808 | D18: 0.33 | E18: 18525.843 | F18: 17148.512 | G18: =E18+F18 -> 35674.355 | H18: 16.17 | I18: 4.64 | J18: 0.97 | K18: 1.13 | L18: =(J18-K18)/K18% -> -14.159292 | M18: 3403.519 | N18: 1322.534 | O18: 39747.618 | P18: 981.788 | Q18: =C18/M18 -> 1.118842 | R18: =C18/N18 -> 2.8793211 | S18: =C18/O18 -> 0.095804483 | T18: =C18/P18 -> 3.8786378 | U18: 45930 | V18: m | W18: TQ5
A19: 10 | B19: ='16b_Loading by main or catalyst'!A34 -> Raffles Edu | C19: 224.357 | D19: 0.72 | E19: 218.887 | F19: 640.561 | G19: =E19+F19 -> 859.448 | H19: 0 | I19: 0 | J19: 0.126 | K19: 0.139 | L19: =(J19-K19)/K19% -> -9.352518 | M19: 111.71 | N19: 43.6 | O19: 1018.751 | P19: 0.145 | Q19: =C19/M19 -> 2.0083878 | R19: =C19/N19 -> 5.1458028 | S19: =C19/O19 -> 0.22022751 | T19: =C19/P19 -> 1547.2897 | U19: 45838 | W19: NR7
A22: 1 | B22: ='16b_Loading by main or catalyst'!A6 -> Audience | C22: 60.492 | D22: 0.08 | E22: 0.028 | F22: 23.269 | G22: =E22+F22 -> 23.297 | H22: 13 | I22: 5.77 | J22: 0.26 | K22: 0.26 | L22: =(J22-K22)/K22% -> 0 | M22: 15.956 | N22: 5.788 | O22: 26.015 | P22: 4.436 | Q22: =C22/M22 -> 3.7911757 | R22: =C22/N22 -> 10.451279 | S22: =C22/O22 -> 2.3252739 | T22: =C22/P22 -> 13.63661 | U22: 46022 | V22: c | W22: ='16b_Loading by main or catalyst'!H6 -> 1AZ
A23: 2 | B23: ='16b_Loading by main or catalyst'!A9 -> Dezign Format | C23: 38 | D23: 1 | E23: 2.391 | F23: 11.078 | G23: =E23+F23 -> 13.469 | H23: 19 | I23: 0 | J23: 0.19 | K23: 0.23 | L23: =(J23-K23)/K23% -> -17.391304 | M23: 33.104 | N23: 3.03 | O23: 24.951 | P23: -6.511 | Q23: =C23/M23 -> 1.1478975 | R23: =C23/N23 -> 12.541254 | S23: =C23/O23 -> 1.5229851 | T23: =C23/P23 -> -5.8362771 | U23: 46022 | V23: c | W23: ='16b_Loading by main or catalyst'!H9 -> UZF
A24: 3 | B24: ='16b_Loading by main or catalyst'!A11 -> GKE | C24: 64.395 | D24: 0.28 | E24: 53.123 | F24: 100.13 | G24: =E24+F24 -> 153.253 | H24: 7.5 | I24: 5.33 | J24: 0.075 | K24: 0.095 | L24: =(J24-K24)/K24% -> -21.052632 | M24: 126.519 | N24: 29.927 | O24: 184.24 | P24: 14.761 | Q24: =C24/M24 -> 0.50897494 | R24: =C24/N24 -> 2.1517359 | S24: =C24/O24 -> 0.34951693 | T24: =C24/P24 -> 4.3625093 | U24: 45808 | V24: c | W24: ='16b_Loading by main or catalyst'!H11 -> 595
A25: 4 | B25: ='16b_Loading by main or catalyst'!A12 -> Hiap Tong | C25: 35.545 | D25: -0.04 | E25: 52.646 | F25: 99.907 | G25: =E25+F25 -> 152.553 | H25: 11.2 | I25: 0.89 | J25: 0.112 | K25: 0.096 | L25: =(J25-K25)/K25% -> 16.666667 | M25: 91.916 | N25: 23.985 | O25: 182.026 | P25: 19.872 | Q25: =C25/M25 -> 0.38671178 | R25: =C25/N25 -> 1.4819679 | S25: =C25/O25 -> 0.1952743 | T25: =C25/P25 -> 1.7886977 | U25: 46022 | V25: c | W25: ='16b_Loading by main or catalyst'!H12 -> 5PO
A26: 5 | B26: ='16b_Loading by main or catalyst'!A14 -> LS 2 Holdings | C26: 14.8 | D26: 4.11 | E26: 2.562 | F26: 23.807 | G26: =E26+F26 -> 26.369 | H26: 4 | I26: 0 | J26: 0.08 | K26: 0.074 | L26: =(J26-K26)/K26% -> 8.1081081 | M26: 71.805 | N26: 7.614 | O26: 37.841 | P26: 6.154 | Q26: =C26/M26 -> 0.20611378 | R26: =C26/N26 -> 1.9437878 | S26: =C26/O26 -> 0.39111017 | T26: =C26/P26 -> 2.4049399 | U26: 46022 | V26: c | W26: ='16b_Loading by main or catalyst'!H14 -> ENV
A27: 6 | B27: ='16b_Loading by main or catalyst'!A22 -> VCPlus | C27: 17.012 | D27: 0.69 | E27: 0.17 | F27: 0.626 | G27: =E27+F27 -> 0.796 | H27: 0 | I27: 0 | J27: 0.003 | K27: 0.003 | L27: =(J27-K27)/K27% -> 0 | M27: 0.191 | N27: -2.281 | O27: 1.471 | P27: -1.388 | Q27: =C27/M27 -> 89.068063 | R27: =C27/N27 -> -7.4581324 | S27: =C27/O27 -> 11.564922 | T27: =C27/P27 -> -12.256484 | U27: 45747 | V27: c | W27: ='16b_Loading by main or catalyst'!H22 -> 43E
A28: 7 | B28: ='16b_Loading by main or catalyst'!A23 -> ZICO Hldgs | C28: 19.707 | D28: 0.18 | E28: 8.936 | F28: 28.536 | G28: =E28+F28 -> 37.472 | H28: 0 | I28: 0 | J28: 0.048 | K28: 0.055 | L28: =(J28-K28)/K28% -> -12.727273 | M28: 14.312 | N28: 3.549 | O28: 42.196 | P28: -0.504 | Q28: =C28/M28 -> 1.3769564 | R28: =C28/N28 -> 5.5528318 | S28: =C28/O28 -> 0.46703479 | T28: =C28/P28 -> -39.10119 | U28: 45838 | V28: c | W28: ='16b_Loading by main or catalyst'!H23 -> 40W
A29: 8 | B29: ='16b_Loading by main or catalyst'!A42 -> UnUsUaL | C29: 25.553 | D29: -0.38 | E29: 1.826 | F29: 27.989 | G29: =E29+F29 -> 29.815 | H29: 0 | I29: 0 | J29: 0.025 | K29: 0.036 | L29: =(J29-K29)/K29% -> -30.555556 | M29: 53.219 | N29: -18.575 | O29: 37.47 | P29: 4.373 | Q29: =C29/M29 -> 0.48014807 | R29: =C29/N29 -> -1.3756662 | S29: =C29/O29 -> 0.6819589 | T29: =C29/P29 -> 5.843357 | U29: 45747 | V29: c | W29: 1D1
A30: 9 | B30: ='16b_Loading by main or catalyst'!A4 -> Abundante | C30: 15.26 | D30: 0.3 | E30: 0 | F30: 18.64 | G30: =E30+F30 -> 18.64 | H30: 0 | I30: 0 | J30: 0.15 | K30: 0.16 | L30: =(J30-K30)/K30% -> -6.25 | M30: 7.326 | N30: 0.781 | O30: 19.592 | P30: 0.2511 | Q30: =C30/M30 -> 2.0829921 | R30: =C30/N30 -> 19.539052 | S30: =C30/O30 -> 0.77888934 | T30: =C30/P30 -> 60.772601 | U30: 45716 | V30: m | W30: ='16b_Loading by main or catalyst'!H4 -> 570
A31: 10 | B31: ='16b_Loading by main or catalyst'!A5 -> A-Smart | C31: 30.319 | D31: -0.34 | E31: 6.823 | F31: 0 | G31: =E31+F31 -> 6.823 | H31: 0 | I31: 0 | J31: 0.11 | K31: 0.11 | L31: 0 | M31: 0 | N31: 0 | O31: 0 | P31: -2.6 | Q31: =C31/M31 -> #DIV/0! | R31: =C31/N31 -> #DIV/0! | S31: =C31/O31 -> #DIV/0! | T31: =C31/P31 -> -11.661154 | U31: 45869 | V31: m | W31: ='16b_Loading by main or catalyst'!H5 -> BQC
A32: 11 | B32: ='16b_Loading by main or catalyst'!A7 -> Chasen | C32: 29.45 | D32: 0.28 | E32: 100.704 | F32: 82.205 | G32: =E32+F32 -> 182.909 | H32: 0 | I32: 0 | J32: 0.077 | K32: 0.087 | L32: =(J32-K32)/K32% -> -11.494253 | M32: 116.322 | N32: 5.151 | O32: 205.471 | P32: -53.247 | Q32: =C32/M32 -> 0.25317653 | R32: =C32/N32 -> 5.7173364 | S32: =C32/O32 -> 0.14332923 | T32: =C32/P32 -> -0.5530828 | U32: 45747 | V32: m | W32: ='16b_Loading by main or catalyst'!H7 -> 5NV
A33: 12 | B33: ='16b_Loading by main or catalyst'!A10 -> Eneco Energy | C33: 34.208 | D33: 0.66 | E33: 9.758 | F33: 21.838 | G33: =E33+F33 -> 31.596 | H33: 0 | I33: 0 | J33: 0.009 | K33: 0.01 | L33: =(J33-K33)/K33% -> -10 | M33: 31.302 | N33: 6.523 | O33: 37.445 | P33: 3.373 | Q33: =C33/M33 -> 1.0928375 | R33: =C33/N33 -> 5.2442128 | S33: =C33/O33 -> 0.91355321 | T33: =C33/P33 -> 10.141714 | U33: 45838 | V33: m | W33: ='16b_Loading by main or catalyst'!H10 -> R14
A34: 13 | B34: ='16b_Loading by main or catalyst'!A13 -> KingsmenCreative | C34: 120.159 | D34: 0.22 | E34: 15.468 | F34: 124.268 | G34: =E34+F34 -> 139.736 | H34: 8.5 | I34: 5.04 | J34: 0.595 | K34: 0.5 | L34: =(J34-K34)/K34% -> 19 | M34: 372.544 | N34: 23.413 | O34: 284.754 | P34: 27.541 | Q34: =C34/M34 -> 0.3225364 | R34: =C34/N34 -> 5.1321488 | S34: =C34/O34 -> 0.42197476 | T34: =C34/P34 -> 4.3629135 | U34: 46022 | V34: m | W34: ='16b_Loading by main or catalyst'!H13 -> 5MZ
B36: Assumption: | D36: 46022
A37: a | B37: Malaysia Corp Tax rate (T) = | D37: 0.24
A38: b | B38: Malaysia 1 MYR/S$ = | D38: 0.32
B42: ComfortDelgro (C52)
B43: Singpost (S08)
B44: Genting Singapore (G13)
B45: HPL (H15)
B46: Healthway Med (5NG)
B47: SBS Transit (S61)
B48: SIA (C6L)
B50: Azeus
B51: Arion Ent (YYB)
B52: HL Global Ent (AVX)
B53: Memories (1H4)
B54: Sim Leisure (URR)
... B56: Revez (RCU)

Sheet 16b_Loading by main or catalyst
A1: Selected for the risk premium calculation:
A3: Entities | B3: Active, Non-active or Suspended | C3: Mainboard (m) or Catalyst ( c ) | D3: Industry | E3: Sub-industry | F3: Profile | G3: Currency | H3: Code | I3: Market Cap
A4: Abundante | B4: a | C4: m | D4: Industrials | E4: Rental & leasing services | F4: Supplier of concrete pumping services & CCTV of sewer inspection services | G4: SGD | H4: 570 | I4: 17.3
A5: A-Smart | B5: a | C5: m | D5: Industrials | E5: Specialty Business Services | F5: (a) Property development and real estate investment; and (b) Smart technologies; and (c) Print and media; and (d) Other investments. | G5: SGD | H5: BQC | I5: 29.78
A6: Audience | B6: a | C6: c | D6: Industrials | E6: Consulting Services | F6: (i) conducting business impact assessments on companies and organising business recognition awards, (ii) organising trade and consumer exhibitions, and (iii) offering digital and print business media brands and organising networking events and conferences | G6: SGD | H6: 1AZ | I6: 58.17
A7: Chasen | B7: a | C7: m | D7: Industrials | E7: Integrated Freight & Logistics | F7: Specialist Relocation, Third Party Logistics, Technical & Engineering | G7: SGD | H7: 5NV | I7: 31.36
A8: COSCO SHP SG | B8: a | C8: m | D8: Industrials | E8: Integrated Freight & Logistics | F8: • Investment holding • Ship repair and marine engineering activities • Logistics • Property management | G8: SGD | H8: F83 | I8: 532.94
A9: Dezign Format | B9: a | C9: c | D9: Industrials | E9: Specialty Business Services | F9: design and fabrication services, provision of interior fit-out services and the development, licensing and commercialisation of immersive location-based entertainment and experiences. | G9: SGD | H9: UZF | I9: 43
A10: Eneco Energy | B10: a | C10: m | D10: Industrials | E10: Integrated Freight & Logistics | F10: provision of transportation, inventory management and warehousing services. | G10: SGD | H10: R14 | I10: 34.21
A11: GKE | B11: a | C11: c | D11: Industrials | E11: Integrated Freight & Logistics | F11: Provision of warehousing & ancillary services and trading business • Provision of freight forwarding, transportation, warehousing and logistics services • Provision of port operations and logistics services, stevedoring and freight forwarding services • Provision of indoor farming solution and growing of crops • Producing and manufacturing of environmentally friendly lightweight brick building materials and cement products • Provision of blending and manufacturing of chemical and chemical products • Provision of contracting services, sales and distribution of telecommunications mobile handsets and accessories business. | G11: SGD | H11: 595 | I11: 72.12
A12: Hiap Tong | B12: a | C12: c | D12: Industrials | E12: Rental & leasing services | F12: renting of cranes, prime movers, heavy machinery and equipment, trading of cranes and heavy equipment and supply labour for container lashing/unlashing, prime movers driving services and ancillary works. | G12: SGD | H12: 5PO | I12: 34.91
A13: KingsmenCreative | B13: a | C13: m | D13: Industrials | E13: Consulting Services | F13: provision of corporate marketing and other related services, design and production of interiors, exhibitions, decorations, museums and thematic, as well as the development and operation of experiential and themed attractions | G13: SGD | H13: 5MZ | I13: 112.04
A14: LS 2 Holdings | B14: a | C14: c | D14: Industrials | E14: Specialty Business Services | F14: an investment holding and provide management services to its subsidiary corporations’ activities, cleaning, pest control, machinery, IFM | G14: SGD | H14: ENV | I14: 12.95
A15: Metech Intl | B15: a | C15: c | D15: Industrials | E15: Specialty Business Services | F15: Manufacturing and distribution of lab-grown diamonds; Collection and processing of food waste into animal feed, bio-fuel and other by-products, and the production and sale of agricultural machinery, fermentation and renewable resource equipment (the “Food Waste Business”); and Wholesale distribution of high-quality and affordable nutritional supplements (the “Health Supplements Business”) | G15: SGD | H15: V3M | I15: 5.26
A16: SATS | B16: a | C16: m | D16: Industrials | E16: Airport & Air Services | F16: rental of premises and provision of management services to related companies. | G16: SGD | H16: S58 | I16: 5480
A17: SIA | B17: a | C17: m | D17: Industrials | E17: Airlines | F17: Aviation industry | G17: SGD | H17: C6L | I17: 21380
A18: SIA Engineering | B18: a | C18: m | D18: Industrials | E18: Airport & Air Services | F18: provision of airframe maintenance, component overhaul services and inventory technical management, the provision of line maintenance and technical ground handling services and investment holdings | G18: SGD | H18: S59 | I18: 3760
A19: SingPost | B19: a | C19: m | D19: Industrials | E19: Integrated Freight & Logistics | F19: operation and provision of postal and parcel delivery services, eCommerce logistics and property, provision of delivery services and eCommerce logistics solutions, provision of integrated supply chain and distributions services, and investment holding | G19: SGD | H19: S08 | I19: 810.46
A20: Southern Arch | B20: a | C20: m | D20: Industrials | E20: Specialty Business Services | F20: sterilisation, decontamination and polymerisation services; hospitality management and property development | G20: SGD | H20: A33 | I20: 27.57
A21: V2Y Corp | B21: s | C21: c | D21: Industrials | E21: Specialty Business Services | F21: Insurtech business, foods and beverages and distributions of fruits and vegetables segment. | G21: SGD | H21: V2Y | I21: 3.71
A22: VCPlus | B22: a | C22: c | D22: Industrials | E22: Consulting Services | F22: provision of advisory, consultancy and/or management services related to financial technology regulation and licensing as well as the adoption of financial technology strategies and technology (“FinTech Business” | G22: SGD | H22: 43E | I22: 17.01
A23: ZICO Hldgs | B23: a | C23: c | D23: Industrials | E23: Specialty Business Services | F23: integrated provider of multidisciplinary professional services, organised into business units based on advisory and transactional services | G23: SGD | H23: 40W | I23: 29.56
A24: Wing Tai | B24: a | C24: m | D24: Real Estate | E24: Real Estate - Development | F24: Property Development & Investment | G24: SGD | H24: W05
A26: CapitaLandInvest | B26: a | C26: m | D26: Real Estate, Real Estate services | E26: Financial & Insurance activities | F26: REIT - Hospitality assets supporting MICE tourism | G26: SGD | H26: 9CI | I26: 15010
A27: ComfortDelGro | B27: a | C27: m | D27: Industrials, Railroads | E27: Transport & Storage | F27: Transportation -One of the world's largest land transport companies (taxis, buses, rail - vital for event mobility) | G27: SGD | H27: C52 | I27: 3230
A28: COSCO SHP SG | B28: a | C28: m | D28: Industrials | E28: Integrated Freight & Logistics | F28: Provides shipping and logistics services | G28: SGD | H28: F83 | I28: 532.94
A29: Frasers Property | B29: a | C29: m | D29: Real Estate | E29: Real Estate - Diversified | F29: REIT - Hotels and serviced residences hosting conferences, weddings and corporate events\ | G29: SGD | H29: TQ5 | I29: 4040
A30: Keppel | B30: a | C30: m | D30: Industrials, Conglomerates | E30: Manufacturing, REIT | F30: REIT -Commercial properties with spaces for corporate events and exhibitions | G30: SGD | H30: BN4 | I30: 22470
A31: KingsmenCreative | B31: a | C31: m | D31: Industrials | E31: Consulting Services | F31: Design and production for exhibitions, museums, retail spaces and major events | G31: SGD | H31: 5MZ | I31: 112.04
A32: OUE | B32: a | C32: m | D32: Real Estate | E32: Real Estate - Diversified | F32: Owns hotels and commercial properties with event spaces (e.g. Mandarin Orchard, Crowne Plaza) | G32: SGD | H32: LJ3 | I32: 1
A33: PanUnited | B33: a | C33: m | D33: Basic Materials | E33: Building Materials | F33: Logistics and supply chain solution, including ready mix concrete for event infrastructure. Cement ready mix | G33: SGD | H33: P52 | I33: 972.95
A34: Raffles Edu | B34: a | C34: m | D34: Consumer Defensive, Education & Training Services | E34: Education | F34: Runs design schools and exhibition-related training often tied to creative events | G34: SGD | H34: NR7 | I34: 238.49
A35: SamuderaShipping | B35: a | C35: m | D35: Industrials, Marine Shipping | E35: Transport & Storage | F35: Regional container shipping services, supporting logistics for exhibitions and trade shows | G35: USD | H35: S56 | I35: 613.36
A36: SATS | B36: a | C36: m | D36: Industrials | E36: Airport & Air Services | F36: Provides ground handling, catering, and logistics at Changi Airport- supports international event arrivals | G36: SGD | H36: S58 | I36: 5480
A37: SIA | B37: a | C37: m | D37: Industrials | E37: Airlines | F37: Aviation industry -Provides logistics, travel packages and sponsorship for global events | G37: SGD | H37: C6L | I37: 21380
... A42: UnUsUaL | B42: a | C42: c | D42: Communication Services, Advertising agencies | E42: Arts, Entertainments & Recreations | F42: Concert promotion, large-scale live entertainment, event production | G42: SGD | H42: 1D1 | I42: 29.59
A45: What’s Publicly Known | E45: ComfortDelgro (C52)
E46: Singpost (S08)
A47: The pattern is consistent year to year: smaller firms → higher premiums. | E47: Genting Singapore (G13)
E48: HPL (H15)
A49: For Singapore real estate developers: | E49: Healthway Med (5NG)
E50: SBS Transit (S61)
E51: SIA (C6L)
A53: Large caps (City Developments, UOL, CapitaLand) → ~0.8–1.5% | E53: Azeus
E54: Arion Ent (YYB)
A55: Mid caps (Wing Tai, Ho Bee Land) → ~1.5–2.5% | E55: HL Global Ent (AVX)
E56: Memories (1H4)
A57: Small caps (Oxley, Low Keng Huat, niche firms) → ~2.5–4.0% | E57: Sim Leisure (URR)
E58: SingMedical (507)
A59: My size cap risk premium is based on unlevered beta X ERP, which is not a standard: | E59: Revez (RCU)
A60: “Our computed size premium of 2.66% (based on SGX small-cap betas × ERP) aligns with the empirical ranges published annually by Duff & Phelps (Kroll) for Decile 8–9 firms in Singapore, which typically fall between 2.5% and 4.0%.”
A62: How Duff & Phelps / Morningstar Derive Size Premium
A64: Step 1: Portfolio formation
A68: All listed firms are ranked by market capitalization.
A70: They are divided into deciles (10 groups) or sometimes finer “breakpoints.”
A72: Step 2: Historical return analysis
A76: Each decile’s average historical return is calculated over decades (using CRSP data in the U.S., then extended internationally).
A78: Step 3: CAPM comparison
A82: For each decile, the expected return under CAPM is computed:
A84: E(R)=Rf+β×ERP
A86: The actual average return is compared against this CAPM prediction.
A88: Step 4: Excess return = Size Premium
... A248: Here’s how you can structure it in Excel:
A250: Year | B250: Price (Start) | C250: Price (End) | D250: Dividend | E250: Annual Return Formula
A251: 2023 | B251: 0.12 | C251: 0.15 | D251: 0 | E251: =(0.15-0.12+0)/0.12 → 25%
A252: 2024 | B252: 0.15 | C252: 0.13 | D252: 0 | E252: =(0.13-0.15+0)/0.15 → -13.3%
A254: Then average across years: =AVERAGE(Return_2023, Return_2024, …)
A256: 🔄 Step 4: Size Premium
A258: Once you have the average historical return for the decile:
A260: Size Premium=Rˉdecile−(Rf+βdecile×ERP)
A262: ✅ This way, you can replicate the Duff & Phelps methodology locally using SGX data. Even if dividends are zero, the formula works fine — you just rely on price appreciation.
A264: Would you like me to design a ready-to-use Excel template layout (with formulas already embedded for annual return, portfolio average, and size premium) so you can drop in SGX stock prices and instantly compute the historical return series?
A266: Spreadsheet Layout
A268: Sheet: Annual Returns
A270: Year | B270: Price (Start) | C270: Price (End) | D270: Dividend | E270: Annual Return Formula
A271: 2023 | B271: 0.12 | C271: 0.15 | D271: 0 | E271: =(C2-B2+D2)/B2 → 25%
A272: 2024 | B272: 0.15 | C272: 0.13 | D272: 0 | E272: =(C3-B3+D3)/B3 → -13.3%
A273: 2025 | B273: 0.13 | C273: 0.14 | D273: 0 | E273: =(C4-B4+D4)/B4 → 7.7%
A275: 👉 Formula in Excel: =(Price_End - Price_Start + Dividend)/Price_Start
A277: Sheet: Portfolio (Decile) Returns
A279: Year | B279: Firm A Return | C279: Firm B Return | D279: Firm C Return | E279: Portfolio Average
A280: 2023 | B280: 0.25 | C280: 0.12 | D280: -0.05 | E280: =AVERAGE(B2:D2)
A281: 2024 | B281: -0.133 | C281: 0.08 | D281: 0.03 | E281: =AVERAGE(B3:D3)
A282: 2025 | B282: 0.077 | C282: -0.02 | D282: 0.1 | E282: =AVERAGE(B4:D4)
A284: 👉 Formula in Excel: =AVERAGE(FirmA_Return, FirmB_Return, …)
A286: Sheet: Historical Average
A288: Portfolio | B288: Average Return | C288: CAPM Predicted Return | D288: Size Premium
A289: Small-Cap Decile | B289: =AVERAGE(Portfolio_Returns) | C289: =Rf + Beta*ERP | D289: =Average_Return - CAPM
A291: 👉 Example:
A293: Average Return = 6.5%
A295: CAPM Predicted = 5.9%
A297: Size Premium = 0.6%
A299: ✅ How to Use
A301: 1. Input yearly start/end prices (and dividends if any).
A303: 2. Compute annual returns per firm.
A305: 3. Average across firms to get portfolio/decile return.
A307: 4. Average across years to get historical return.
A309: 5. Compare against CAPM prediction to derive size premium.
A311: This template mirrors the Duff & Phelps empirical method: historical return minus CAPM prediction = size premium. Even if dividends are zero, the formula works fine with just price changes.

Sheet 17_Toolkit_Overview
A4: Section 1: Overview
A6: Item | B6: Fair Market Value (FMV) | C6: Fair Value (FV)
A7: Definition | B7: Value in an open, unrestricted market | C7: Value in a specific transaction or context
A8: Common Use | B8: Tax, estate, minority sale | C8: Shareholder disputes, M&A, financial reporting
A9: Assumptions | B9: Willing buyer/seller, no compulsion | C9: May include strategic synergies or control
A11: 📊 Section 2: Inputs (Consumes)
A13: Input / Assumption | B13: FMV Source | C13: FV Source
A14: Risk-Free Rate (Rf) | B14: MAS 10Y Benchmark | C14: Same
A15: ERP | B15: SG Market Premia | C15: Same
A16: Beta | B16: Peer set (unlevered, re-levered) | C16: Same or adjusted for strategic buyer
A17: IRP | B17: Derived from peer volatility | C17: May be adjusted for industry consolidation
A18: SCP | B18: Small-cap premium | C18: May be excluded if buyer is large
A19: CSRP | B19: Qualitative risk scoring | C19: May be reduced if buyer mitigates risks
A20: WACC | B20: Weighted average cost of capital | C20: May use lower cost of capital for strategic buyer
A21: DLOC / DLOM | B21: Applied to FMV for minority, illiquid interest | C21: Often not applied in FV unless relevant
A23: 📐 Section 3: Valuation Methods (Produces)
A25: Method | B25: FMV Output | C25: FV Output
A26: Asset-Based | B26: Net adjusted assets | C26: Same or adjusted for strategic asset use
A27: Income-Based (DCF) | B27: FCF discounted at WACC | C27: May use higher growth or lower WACC
A28: Income-Based (Cap) | B28: Capitalized normalized earnings | C28: Same or adjusted for strategic buyer
A29: Market Multiple | B29: Peer-derived multiples | C29: May use premium multiples for strategic buyer
A31: 💰 Section 4: Results
A33: Output | B33: FMV | C33: FV
A34: Enterprise Value | B34: Derived from DCF, Cap, or Market Multiple | C34: May be higher due to synergies or control
A35: Less: Net Debt | B35: From normalized balance sheet | C35: Same
A36: Equity Value | B36: EV – Net Debt | C36: Same or higher
A37: Per Share Value | B37: Equity ÷ Shares | C37: Same or higher
A38: DLOC / DLOM Applied | B38: Yes | C38: Usually no
A39: Final Value | B39: Minority, illiquid value | C39: Strategic or control value
A41: 🧾 Section 5: Narrative Summary
A43: “Based on observable market data, peer betas, cost of capital, and appropriate valuation methods, the FMV of the subject entity’s minority, illiquid interest is S$___ per share. Under a fair value context, assuming strategic buyer synergies and control, the indicated value is S$___ per share.”

Sheet 18_Sensitivity_table
A1: Sensitivity Table Layout
A3: Step 1: Create the Grid
A5: In a new sheet (SensitivityDashboard), set up WACC across columns and Growth across rows: | L5: The expression you pasted is a sensitivity adjustment formula I suggested earlier to model how FMV changes when WACC or growth assumptions move away from a baseline. The constants 0.05, 0.07, and 0.01 are not “official” values from MAS or IRAS — they are scaling factors and baselines we set up to make the sensitivity grid work. Here’s what each means:
A7: Growth \ WACC | B7: 0.07 | C7: 0.08 | D7: 0.09 | E7: 0.1 | F7: 0.11 | Q7: Breaking Down the Constants
A8: 0.01 | B8: FMV / FV | C8: FMV / FV | D8: FMV / FV | E8: FMV / FV | F8: FMV / FV
A9: 0.02 | B9: FMV / FV | C9: FMV / FV | D9: FMV / FV | E9: FMV / FV | F9: FMV / FV | Q9: 0.07
A10: 0.03 | B10: FMV / FV | C10: FMV / FV | D10: FMV / FV | E10: FMV / FV | F10: FMV / FV
A11: 0.04 | B11: FMV / FV | C11: FMV / FV | D11: FMV / FV | E11: FMV / FV | F11: FMV / FV | Q11: This is the baseline WACC (7%) we used as the “anchor point” in the sensitivity grid.
A12: 0.05 | B12: FMV / FV | C12: FMV / FV | D12: FMV / FV | E12: FMV / FV | F12: FMV / FV
Q13: All adjustments are measured relative to this baseline.
A14: Step 2: Create Input Controls
Q15: Example: if WACC_Input = 0.09 (9%), then (0.09 - 0.07)/0.01 = 2 → meaning WACC is 2 steps (2%) above baseline.
A16: Parameter | B16: Cell | C16: Options | D16: Named Range
A17: WACC | B17: B2 | C17: 0.0773 | D17: 0.07 | Q17: 0.01
C18: 0.08
C19: 0.09 | Q19: This is the step size (1%) used to normalize changes in WACC or growth.
C20: 0.1
C21: 0.11 | Q21: It converts differences into “number of steps.”
A22: Growth rate | B22: B3 | C22: 0.012 | D22: 0.012
C23: 0.02 | Q23: Example: (0.09 - 0.07)/0.01 = 0.02/0.01 = 2 steps above baseline.
C24: 0.03
C25: 0.04 | Q25: 0.05
C26: 0.05
A27: DLOC | B27: B4 | C27: 0.1 | D27: 0.15 | Q27: This is the sensitivity factor (5% change in equity value per 1% change in WACC or growth).
C28: 0.15
C29: 0.2 | Q29: It’s an assumption we made to illustrate how FMV responds.
A30: DLOM | B30: B5 | C30: 0.2 | D30: 0.2
C31: 0.25 | Q31: For FV, we used 0.10 (10%) to show stronger sensitivity.
C32: 0.3
C33: 0.35 | Q33: In practice, you can calibrate this factor based on your DCF model outputs (e.g., run the DCF at WACC = 8% vs 9% and see the % change in value).
C34: 0.4
Q35: 🧠 Putting It Together
A36: Step 3: Define Base Values
Q37: So the formula:
A38: Parameter | B38: Cell | C38: Value | D38: Named Range (Adjusted)
A39: FMV Equity Value | B39: B7 | C39: 4000000 | D39: =C39 * (1 - 0.05 * ((D17 - 0.07) / 0.01)) * (1 + 0.05 * ((D22 - 0.01) / 0.01)) -> 4040000 | Q39: excel
A40: FV Equity Value | B40: B8 | C40: 4400000 | D40: =C40*(1-(0.1*(D17 - 0.07) / 0.01)) * (1 + 0.1 * ((D22 - 0.01) / 0.01)) -> 4488000
A41: Shares | B41: B9 | C41: 500000 | D41: Shares
Q42: means:
A43: Step 4: Example Calculation
A44: For: | Q44: Start from FMV_Base (e.g., 4,000,000).
A45: Growth = | B45: =D22 -> 0.012
A46: WACC = | B46: =D17 -> 0.07 | Q46: Adjust downward if WACC is above 7% (each +1% WACC reduces value by 5%).
A47: FMV per share : | C47: =D39/C41* (1 - D27) * (1 - D30) -> 5.4944 | D47: Note: Have not deducted the Net Debt (Total Debt - Cash)
A48: [ formula: = (Adjusted_FMV / Shares) * (1 - DLOC_Input) * (1 - DLOM_Input) ] | Q48: Adjust upward if growth is above 1% (each +1% growth increases value by 5%).
A49: excel
Q50: Then divide by shares and apply DLOC/DLOM.
A51: =(4000000*(1 - 0.05*((0.09-0.07)/0.01))*(1+0.05*((0.03-0.01)/0.01))/500000)*(1-0.15)*(1-0.3) -> 4.7124
Q52: ✅ Best Practice
A53: → ≈ S$5.12
Q54: 0.07 (7%) baseline WACC → set to your actual calculated WACC (8.97% in your case).
A55: FV per share : | C55: =D40 /C41 -> 8.976 | D55: Note: Have not deducted the Net Debt (Total Debt - Cash)
A56: [ formula: = Adjusted_FV / Shares ] | Q56: 0.01 step size → keep as 1% increments.
A57: excel
Q58: 0.05 sensitivity factor → calibrate by running your DCF at different WACC/growth values and measuring the % change.
A59: =(4400000*(1 - 0.1*((0.09-0.07)/0.01))*(1+0.1*((0.03-0.01)/0.01))/500000) -> 8.448
A61: → ≈ S$8.80
A63: Step 5: Visualization
A65: Highlight FMV values in blue heatmap (conditional formatting).
A67: Highlight FV values in green heatmap.
A69: Add a 3D surface chart to show how values change across WACC and growth.
A71: ✅ Outcome
A73: This table will give you:
A75: A clear matrix of FMV vs FV per share under different assumptions.
A77: A visual sensitivity chart that stakeholders can grasp quickly.
A79: Automatic updates when you change WACC, growth, DLOC, or DLOM inputs.
A81: 👉 Would you like me to also prepare a ready‑made Excel formula block (copy‑paste grid with FMV and FV formulas filled in for each cell) so you don’t have to manually enter them row by row?
A83: Yes please
... A103: excel
A105: =(4000000*(1 - 0.05*((WACC%-0.07)/0.01))*(1+0.05*((Growth%-0.01)/0.01))/500000)*(1-0.15)*(1-0.3) -> #NAME?
A107: FV Formula (paste into each cell)
A109: excel
A111: =(4400000*(1 - 0.1*((WACC%-0.07)/0.01))*(1+0.1*((Growth%-0.01)/0.01))/500000) -> #NAME?
A113: Example Filled Row (Growth = 3%)
A115: Growth \ WACC | B115: 0.07 | C115: 0.08 | D115: 0.09 | E115: 0.1 | F115: 0.11
A116: 0.03 | B116: FMV=5.44 / FV=9.68 | C116: FMV=5.28 / FV=9.24 | D116: FMV=5.12 / FV=8.80 | E116: FMV=4.96 / FV=8.36 | F116: FMV=4.80 / FV=7.92
B117: =(4000000*(1 - 0.05*((WACC%-0.07)/0.01))*(1+0.05*((Growth%-0.01)/0.01))/500000)*(1-0.15)*(1-0.3) -> #NAME?
A118: How to Implement
A120: 1. Create a table with WACC values across columns and Growth down rows.
A122: 2. Paste the FMV formula into the left half of each cell, FV formula into the right half.
A126: Or, create two separate tables: one for FMV, one for FV.
A128: 3. Apply conditional formatting (blue for FMV, green for FV).
A130: 4. Insert → Surface Chart or Heatmap to visualize sensitivity.
A132: ✅ This grid will give you a full sensitivity matrix for FMV and FV per share. 👉 Would you like me to also prepare a combined chart template (FMV vs FV plotted together for each growth/WACC pair) so you can paste it directly into your dashboard?

Sheet 19_Checklist
A1: Purpose: Track issues, corrections, and improvements transparently — critical for audit defense, consistency, and CPE compliance.
A3: Sheet | B3: Cell / Range | C3: Issue Type | D3: Description | E3: Severity | F3: Suggested Fix / Action | G3: Status
A4: 01_Inputs | B4: B2 | C4: Input Check | D4: Risk-free rate source not documented | E4: Medium | F4: Add comment: “MAS 10Y Benchmark as at dd/mm/yyyy" | G4: Open
A5: 03_BetaCalc | B5: D8:D15 | C5: Formula | D5: Beta unlevered formula references wrong cell | E5: High | F5: Replace with =C(row)/(1+(1-Inputs!TaxRate)*E(row)) | G5: Open
A6: 04_CAPM | B6: D12 | C6: Logical Consistency | D6: CSRP not linked — currently static | E6: High | F6: Link to Final CSRP in 08_CSRP_Scoring | G6: Open
A7: 05_WACC | B7: F6 | C7: Transparency | D7: WACC uses book D/E but report states market D/E | E7: Medium | F7: Add toggle: “Use Market D/E: Y/N” | G7: Open
A8: 06_DCF | B8: C22 | C8: Forecast Structure | D8: FCF forecast fixed at 5 years | E8: Low | F8: Add Forecast Years input; replace ranges with dynamic INDEX | G8: Open
A9: 09_DLOC_DLOM | B9: G4 | C9: Formula | D9: DLOM formula not applying floor/cap | E9: High | F9: Set =MIN(MAX(BaseDLOM,Floor_DLOM),Cap_DLOM) | G9: Open
A10: 10_Summary | B10: A1:G18 | C10: Reporting | D10: Final values shown but no narrative explanations | E10: Medium | F10: Add text block summarizing assumption basis | G10: In Progress
A13: Set Status column to: Open / In Progress / Resolved / Finalized.
A15: Open
A16: In Progress
A17: Resolved
A18: Finalized
